Workbook

Sheet Appendix 6.8 Contents
A2: This file contains the data tables for the sources and methods discussed Appendix 6.7 of Chapter 6
A4: Appendix Table 6.8.I.1: Measurement of the Business Sector
A5: Appendix Table 6.8.I.2: Measures of Noncorporate and Corporate Profits
A6: Appendix Table 6.8.I.3: Corrected Business Accounts
A7: Appendix Table 6.8.II.1: Accuracy of GPIM rules for chain-weighted capital stock estimates
A8: Appendix Table 6.8.II.2: Effects of different initial values for capital stock estimates
A9: Appendix Table 6.8.II.3: Effects of different depletion rates
A10: Appendix Table 6.8.II.4: Effects of the Great Depression and WWII
A11: Appendix Table 6.8.II.5: New Measures of Net and Gross Stocks
A12: Appendix Table 6.8.II.6: Measures of Corporate Inventories
A13: Appendix Table 6.8.II.7: Capacity Utilization and Final Capital Stock and Profit Rate Estimates

Sheet Appndx6.8.I.1-3
A1: Appendix Table 6.8.I.1: Measurement of the Business Sector
A2: All Tables from NIPA downloaded in 2011, and all sums in Bills=$, unless indicated otherwise
A3: Description | B3: Source | C3: Variable | D3: 1947 | E3: 1948 | F3: 1949 | G3: 1950 | H3: 1951 | I3: 1952 | J3: 1953 | K3: 1954 | L3: 1955 | M3: 1956 | N3: 1957 | O3: 1958 | P3: 1959 | Q3: 1960 | R3: 1961 | S3: 1962 | T3: 1963 | U3: 1964 | V3: 1965 | W3: 1966 | X3: 1967 | Y3: 1968 | Z3: 1969 | AA3: 1970 | AB3: 1971 | AC3: 1972 | AD3: 1973 | AE3: 1974 | AF3: 1975 | AG3: 1976 | AH3: 1977 | AI3: 1978 | AJ3: 1979 | AK3: 1980 | AL3: 1981 | AM3: 1982 | AN3: 1983 | AO3: 1984 | AP3: 1985 | AQ3: 1986 | AR3: 1987 | AS3: 1988 | AT3: 1989 | AU3: 1990 | AV3: 1991 | AW3: 1992 | AX3: 1993 | AY3: 1994 | AZ3: 1995 | BA3: 1996 | BB3: 1997 | BC3: 1998 | BD3: 1999 | BE3: 2000 | BF3: 2001 | BG3: 2002 | BH3: 2003 | BI3: 2004 | BJ3: 2005 | BK3: 2006 | BL3: 2007 | BM3: 2008 | BN3: 2009 | BO3: 2010 | BP3: 2011
A4: GDP | B4: T 1.7.5, 1 | C4: GDP | D4: 244.1 | E4: 269.1 | F4: 267.2 | G4: 293.7 | H4: 339.3 | I4: 358.3 | J4: 379.3 | K4: 380.4 | L4: 414.7 | M4: 437.4 | N4: 461.1 | O4: 467.2 | P4: 506.6 | Q4: 526.4 | R4: 544.8 | S4: 585.7 | T4: 617.8 | U4: 663.6 | V4: 719.1 | W4: 787.7 | X4: 832.4 | Y4: 909.8 | Z4: 984.4 | AA4: 1038.3 | AB4: 1126.8 | AC4: 1237.9 | AD4: 1382.3 | AE4: 1499.5 | AF4: 1637.7 | AG4: 1824.6 | AH4: 2030.1 | AI4: 2293.8 | AJ4: 2562.2 | AK4: 2788.1 | AL4: 3126.8 | AM4: 3253.2 | AN4: 3534.6 | AO4: 3930.9 | AP4: 4217.5 | AQ4: 4460.1 | AR4: 4736.4 | AS4: 5100.4 | AT4: 5482.1 | AU4: 5800.5 | AV4: 5992.1 | AW4: 6342.3 | AX4: 6667.4 | AY4: 7085.2 | AZ4: 7414.7 | BA4: 7838.5 | BB4: 8332.4 | BC4: 8793.5 | BD4: 9353.5 | BE4: 9951.5 | BF4: 10286.2 | BG4: 10642.3 | BH4: 11142.1 | BI4: 11853.3 | BJ4: 12623 | BK4: 13377.2 | BL4: 14028.7 | BM4: 14291.5 | BN4: 13973.7 | BO4: 14498.9 | BP4: 15075.7
A5: Less: SD (Stat. Discrepancy) | B5: T 1.7.5, 15 | C5: Less: SD | D5: 2.3 | E5: -0.5 | F5: 1.8 | G5: 1.4 | H5: 3.6 | I5: 2.7 | J5: 4 | K5: 3.1 | L5: 2.4 | M5: -1.8 | N5: -0.1 | O5: 1 | P5: 0.5 | Q5: -1 | R5: -0.6 | S5: 0.3 | T5: -0.8 | U5: 0.8 | V5: 1.5 | W5: 6.2 | X5: 4.5 | Y5: 4.3 | Z5: 2.9 | AA5: 6.9 | AB5: 11 | AC5: 8.9 | AD5: 8 | AE5: 9.8 | AF5: 16.3 | AG5: 23.5 | AH5: 21.2 | AI5: 26.1 | AJ5: 47 | AK5: 45.3 | AL5: 36.6 | AM5: 4.8 | AN5: 49.7 | AO5: 31.5 | AP5: 42.3 | AQ5: 67.7 | AR5: 32.9 | AS5: -9.5 | AT5: 56.1 | AU5: 84.2 | AV5: 79.7 | AW5: 110 | AX5: 135.8 | AY5: 108.8 | AZ5: 52.5 | BA5: 25.9 | BB5: -14 | BC5: -85.3 | BD5: -71.1 | BE5: -134 | BF5: -103.4 | BG5: -22.1 | BH5: 16.6 | BI5: -22.3 | BJ5: -95.1 | BK5: -242.3 | BL5: -12 | BM5: -2.4 | BN5: 118.3 | BO5: 23.3 | BP5: 31.9
A6: GDI | B6: T 1.10, 1 | C6: GDI | D6: 241.8 | E6: 269.6 | F6: 265.4 | G6: 292.3 | H6: 335.7 | I6: 355.6 | J6: 375.3 | K6: 377.3 | L6: 412.3 | M6: 439.2 | N6: 461.2 | O6: 466.2 | P6: 506.1 | Q6: 527.4 | R6: 545.4 | S6: 585.4 | T6: 618.6 | U6: 662.8 | V6: 717.6 | W6: 781.5 | X6: 827.9 | Y6: 905.5 | Z6: 981.5 | AA6: 1031.4 | AB6: 1115.8 | AC6: 1229 | AD6: 1374.3 | AE6: 1489.7 | AF6: 1621.4 | AG6: 1801.1 | AH6: 2008.9 | AI6: 2267.7 | AJ6: 2515.2 | AK6: 2742.8 | AL6: 3090.2 | AM6: 3248.4 | AN6: 3484.9 | AO6: 3899.4 | AP6: 4175.2 | AQ6: 4392.4 | AR6: 4703.5 | AS6: 5109.9 | AT6: 5426 | AU6: 5716.3 | AV6: 5912.4 | AW6: 6232.3 | AX6: 6531.6 | AY6: 6976.4 | AZ6: 7362.2 | BA6: 7812.6 | BB6: 8346.4 | BC6: 8878.8 | BD6: 9424.6 | BE6: 10085.5 | BF6: 10389.6 | BG6: 10664.4 | BH6: 11125.5 | BI6: 11875.6 | BJ6: 12718.1 | BK6: 13619.5 | BL6: 14040.7 | BM6: 14293.9 | BN6: 13855.4 | BO6: 14475.6 | BP6: 15043.8
A7: Less: EC (Empl. Comp., Paid) | B7: T 1.10, 2 | C7: Less: EC | D7: 130 | E7: 141.9 | F7: 141.8 | G7: 155.2 | H7: 181.4 | I7: 196.2 | J7: 210.2 | K7: 209.2 | L7: 225.8 | M7: 244.6 | N7: 257.6 | O7: 259.6 | P7: 281.1 | Q7: 296.6 | R7: 305.4 | S7: 327.2 | T7: 345.3 | U7: 370.7 | V7: 399.5 | W7: 442.6 | X7: 475.1 | Y7: 524.3 | Z7: 577.6 | AA7: 617.2 | AB7: 658.9 | AC7: 725.1 | AD7: 811.2 | AE7: 890.3 | AF7: 949.2 | AG7: 1059.4 | AH7: 1180.6 | AI7: 1335.6 | AJ7: 1498.4 | AK7: 1647.7 | AL7: 1819.8 | AM7: 1919.8 | AN7: 2035.7 | AO7: 2245.7 | AP7: 2412 | AQ7: 2559.4 | AR7: 2737 | AS7: 2955 | AT7: 3132.6 | AU7: 3328.6 | AV7: 3441.1 | AW7: 3634.4 | AX7: 3800.4 | AY7: 4002.5 | AZ7: 4199.3 | BA7: 4395.5 | BB7: 4670 | BC7: 5027.8 | BD7: 5359.2 | BE7: 5793.5 | BF7: 5984.5 | BG7: 6116.4 | BH7: 6388.3 | BI7: 6699.6 | BJ7: 7071.5 | BK7: 7483.6 | BL7: 7863 | BM7: 8079.1 | BN7: 7807.2 | BO7: 7977.2 | BP7: 8303.2
A8: Less: T (Taxes net of Subsidies) | B8: T 1.10, 9 - 10 | C8: Less: T | D8: 17.9 | E8: 19.4 | F8: 20.6 | G8: 22.4 | H8: 24 | I8: 26.7 | J8: 29 | K8: 29 | L8: 31.7 | M8: 33.8 | N8: 35.9 | O8: 36.8 | P8: 40 | Q8: 43.4 | R8: 45 | S8: 48.1 | T8: 51.2 | U8: 54.6 | V8: 57.7 | W8: 59.3 | X8: 64.1 | Y8: 72.2 | Z8: 79.4 | AA8: 86.6 | AB8: 95.8 | AC8: 101.3 | AD8: 112 | AE8: 121.6 | AF8: 130.8 | AG8: 141.3 | AH8: 152.6 | AI8: 162 | AJ8: 171.6 | AK8: 190.5 | AL8: 224.1 | AM8: 225.9 | AN8: 242 | AO8: 268.7 | AP8: 286.7 | AQ8: 298.5 | AR8: 317.2 | AS8: 345 | AT8: 371.5 | AU8: 398 | AV8: 429.6 | AW8: 453.3 | AX8: 466.4 | AY8: 512.7 | AZ8: 523.1 | BA8: 545.6 | BB8: 577.8 | BC8: 603.1 | BD8: 628.4 | BE8: 662.8 | BF8: 669 | BG8: 721.4 | BH8: 757.7 | BI8: 817 | BJ8: 869.3 | BK8: 935.4 | BL8: 972.6 | BM8: 985.7 | BN8: 963.5 | BO8: 998 | BP8: 1036.3
A9: Aggregate GOS | C9: Aggregate GOSnipa | D9: 93.9 | E9: 108.3 | F9: 103 | G9: 114.7 | H9: 130.3 | I9: 132.7 | J9: 136.1 | K9: 139.1 | L9: 154.8 | M9: 160.8 | N9: 167.7 | O9: 169.8 | P9: 185 | Q9: 187.4 | R9: 195 | S9: 210.1 | T9: 222.1 | U9: 237.5 | V9: 260.4 | W9: 279.6 | X9: 288.7 | Y9: 309 | Z9: 324.5 | AA9: 327.6 | AB9: 361.1 | AC9: 402.6 | AD9: 451.1 | AE9: 477.8 | AF9: 541.4 | AG9: 600.4 | AH9: 675.7 | AI9: 770.1 | AJ9: 845.2 | AK9: 904.6 | AL9: 1046.3 | AM9: 1102.7 | AN9: 1207.2 | AO9: 1385 | AP9: 1476.5 | AQ9: 1534.5 | AR9: 1649.3 | AS9: 1809.9 | AT9: 1921.9 | AU9: 1989.7 | AV9: 2041.7 | AW9: 2144.6 | AX9: 2264.8 | AY9: 2461.2 | AZ9: 2639.8 | BA9: 2871.5 | BB9: 3098.6 | BC9: 3247.9 | BD9: 3437 | BE9: 3629.2 | BF9: 3736.1 | BG9: 3826.6 | BH9: 3979.5 | BI9: 4359 | BJ9: 4777.3 | BK9: 5200.5 | BL9: 5205.1 | BM9: 5229.1 | BN9: 5084.7 | BO9: 5500.4 | BP9: 5704.3
A10: Less: CFC (Cons. of Fixed Capital) | B10: T 1.10, 23 | C10: Less: CFC | D10: 26.6 | E10: 28.5 | F10: 29.2 | G10: 29.9 | H10: 33.8 | I10: 36.3 | J10: 38.6 | K10: 40.6 | L10: 42.8 | M10: 47.1 | N10: 50.8 | O10: 53.3 | P10: 55.4 | Q10: 56.6 | R10: 58.2 | S10: 60.6 | T10: 63.3 | U10: 66.4 | V10: 70.7 | W10: 76.5 | X10: 82.9 | Y10: 90.4 | Z10: 99.2 | AA10: 108.3 | AB10: 117.8 | AC10: 127.2 | AD10: 140.8 | AE10: 163.7 | AF10: 190.4 | AG10: 208.2 | AH10: 231.8 | AI10: 261.4 | AJ10: 298.9 | AK10: 344.1 | AL10: 393.3 | AM10: 433.5 | AN10: 451.1 | AO10: 474.3 | AP10: 505.4 | AQ10: 538.5 | AR10: 571.1 | AS10: 611 | AT10: 651.5 | AU10: 691.2 | AV10: 724.4 | AW10: 744.4 | AX10: 778 | AY10: 819.2 | AZ10: 869.5 | BA10: 912.5 | BB10: 963.8 | BC10: 1020.5 | BD10: 1094.4 | BE10: 1184.3 | BF10: 1256.2 | BG10: 1305 | BH10: 1354.1 | BI10: 1432.8 | BJ10: 1541.4 | BK10: 1660.7 | BL10: 1767.5 | BM10: 1854.1 | BN10: 1866.3 | BO10: 1873.4 | BP10: 1936.8
A11: Aggregate NOS | B11: T 1.10, 11 | C11: Aggregate NOSnipa | D11: 67.3 | E11: 79.8 | F11: 73.8 | G11: 84.8 | H11: 96.5 | I11: 96.4 | J11: 97.5 | K11: 98.5 | L11: 112 | M11: 113.7 | N11: 116.9 | O11: 116.5 | P11: 129.6 | Q11: 130.8 | R11: 136.8 | S11: 149.5 | T11: 158.8 | U11: 171.1 | V11: 189.7 | W11: 203.1 | X11: 205.8 | Y11: 218.6 | Z11: 225.3 | AA11: 219.3 | AB11: 243.3 | AC11: 275.4 | AD11: 310.3 | AE11: 314.1 | AF11: 351 | AG11: 392.2 | AH11: 443.9 | AI11: 508.7 | AJ11: 546.3 | AK11: 560.5 | AL11: 653 | AM11: 669.2 | AN11: 756.1 | AO11: 910.7 | AP11: 971.1 | AQ11: 996 | AR11: 1078.2 | AS11: 1198.9 | AT11: 1270.4 | AU11: 1298.5 | AV11: 1317.3 | AW11: 1400.2 | AX11: 1486.8 | AY11: 1642 | AZ11: 1770.3 | BA11: 1959 | BB11: 2134.8 | BC11: 2227.4 | BD11: 2342.6 | BE11: 2444.9 | BF11: 2479.9 | BG11: 2521.6 | BH11: 2625.4 | BI11: 2926.2 | BJ11: 3235.9 | BK11: 3539.8 | BL11: 3437.6 | BM11: 3375 | BN11: 3218.4 | BO11: 3627 | BP11: 3767.5
A12: Net interest and miscellaneous payments, domestic industries | B12: T 1.10, 13 | C12: Net Int | D12: 2.4 | E12: 2.5 | F12: 2.8 | G12: 3.1 | H12: 3.5 | I12: 4 | J12: 4.6 | K12: 5.4 | L12: 6.1 | M12: 6.8 | N12: 8 | O12: 9.4 | P12: 9.5 | Q12: 10.4 | R12: 12.1 | S12: 13.8 | T12: 14.7 | U12: 16.9 | V12: 19.1 | W12: 21.9 | X12: 24.9 | Y12: 26.7 | Z12: 33.2 | AA12: 39.9 | AB12: 44.2 | AC12: 48.9 | AD12: 57.5 | AE12: 72.7 | AF12: 83.2 | AG12: 85.2 | AH12: 99.8 | AI12: 116.2 | AJ12: 141.5 | AK12: 183 | AL12: 228.9 | AM12: 267 | AN12: 283.1 | AO12: 327.1 | AP12: 352.8 | AQ12: 387.2 | AR12: 395.7 | AS12: 418.1 | AT12: 474 | AU12: 483.6 | AV12: 462 | AW12: 428.7 | AX12: 407 | AY12: 412.1 | AZ12: 417.5 | BA12: 437.2 | BB12: 487.3 | BC12: 560.2 | BD12: 569.9 | BE12: 642.5 | BF12: 656.9 | BG12: 609.6 | BH12: 595.5 | BI12: 569.3 | BJ12: 678.9 | BK12: 830.1 | BL12: 952.1 | BM12: 1096.8 | BN12: 841.9 | BO12: 753 | BP12: 706.4
A13: Business current transfer payments (net) | B13: T 1.10, 14 | C13: Curr Transfers | D13: 0.7 | E13: 0.7 | F13: 0.7 | G13: 0.9 | H13: 1.2 | I13: 1.3 | J13: 1.2 | K13: 1 | L13: 1.4 | M13: 1.7 | N13: 1.9 | O13: 1.8 | P13: 1.8 | Q13: 1.9 | R13: 2 | S13: 2.2 | T13: 2.7 | U13: 3.1 | V13: 3.6 | W13: 3.5 | X13: 3.8 | Y13: 4.3 | Z13: 4.9 | AA13: 4.5 | AB13: 4.3 | AC13: 4.9 | AD13: 6 | AE13: 7.1 | AF13: 9.4 | AG13: 9.5 | AH13: 8.5 | AI13: 10.8 | AJ13: 13.3 | AK13: 14.7 | AL13: 17.9 | AM13: 20.6 | AN13: 22.6 | AO13: 30.3 | AP13: 35.2 | AQ13: 36.9 | AR13: 34.1 | AS13: 33.6 | AT13: 39.2 | AU13: 40.1 | AV13: 39.9 | AW13: 40.7 | AX13: 40.5 | AY13: 41.9 | AZ13: 45.8 | BA13: 53.8 | BB13: 51.3 | BC13: 65.2 | BD13: 69 | BE13: 87 | BF13: 101.3 | BG13: 82.4 | BH13: 76.1 | BI13: 81.7 | BJ13: 95.9 | BK13: 83 | BL13: 103.3 | BM13: 123 | BN13: 133.4 | BO13: 140 | BP13: 132.6
A14: Proprietors' income with inventory valuation and capital consumption adjustments | B14: T 1.10, 15 | C14: Prop Inc w/IVA and CCAdj | D14: 34.5 | E14: 39.2 | F14: 34.6 | G14: 37.5 | H14: 42.7 | I14: 43.1 | J14: 42 | K14: 42.3 | L14: 44.3 | M14: 45.9 | N14: 47.8 | O14: 50.2 | P14: 50.3 | Q14: 50.7 | R14: 53.2 | S14: 55.3 | T14: 56.5 | U14: 59.4 | V14: 63.9 | W14: 68.2 | X14: 69.8 | Y14: 74.2 | Z14: 77.5 | AA14: 78.5 | AB14: 84.7 | AC14: 96 | AD14: 113.6 | AE14: 113.5 | AF14: 119.6 | AG14: 132.2 | AH14: 146 | AI14: 167.5 | AJ14: 181.1 | AK14: 173.5 | AL14: 181.6 | AM14: 174.8 | AN14: 190.7 | AO14: 233.1 | AP14: 246.1 | AQ14: 262.6 | AR14: 294.2 | AS14: 334.8 | AT14: 351.6 | AU14: 365.1 | AV14: 367.3 | AW14: 414.9 | AX14: 449.6 | AY14: 485.1 | AZ14: 516 | BA14: 583.7 | BB14: 628.2 | BC14: 687.5 | BD14: 746.8 | BE14: 817.5 | BF14: 870.7 | BG14: 890.3 | BH14: 930.6 | BI14: 1033.8 | BJ14: 1069.8 | BK14: 1133 | BL14: 1090.4 | BM14: 1097.9 | BN14: 979.4 | BO14: 1103.4 | BP14: 1157.3
A15: Rental income of persons with capital consumption adjustment | B15: T 1.10, 16 | C15: Rental Inc w/ CCAdj | D15: 7.2 | E15: 7.8 | F15: 8.1 | G15: 9.1 | H15: 10 | I15: 11.2 | J15: 12.4 | K15: 13.4 | L15: 13.8 | M15: 14.1 | N15: 14.5 | O15: 15.2 | P15: 16 | Q15: 17 | R15: 17.7 | S15: 18.6 | T15: 19.3 | U15: 19.4 | V15: 19.9 | W15: 20.5 | X15: 20.9 | Y15: 20.6 | Z15: 20.9 | AA15: 21.1 | AB15: 22.2 | AC15: 23.1 | AD15: 23.9 | AE15: 24 | AF15: 23.4 | AG15: 22.1 | AH15: 19.6 | AI15: 20.9 | AJ15: 22.6 | AK15: 28.5 | AL15: 36.5 | AM15: 38.1 | AN15: 38.2 | AO15: 40 | AP15: 41.9 | AQ15: 33.8 | AR15: 34.2 | AS15: 40.2 | AT15: 42.4 | AU15: 49.8 | AV15: 61.6 | AW15: 84.6 | AX15: 114.1 | AY15: 142.9 | AZ15: 154.6 | BA15: 170.4 | BB15: 176.5 | BC15: 191.5 | BD15: 208.2 | BE15: 215.3 | BF15: 232.4 | BG15: 218.7 | BH15: 204.2 | BI15: 198.4 | BJ15: 178.2 | BK15: 146.5 | BL15: 143.7 | BM15: 231.6 | BN15: 289.7 | BO15: 349.2 | BP15: 409.7
A16: Corporate profits with inventory valuation and capital consumption adjustments, domestic industries | B16: T 1.10, 17 | C16: Corp Profit w/IVA and CCAdj | D16: 22.5 | E16: 29.6 | F16: 27.6 | G16: 34.4 | H16: 39.1 | I16: 37 | J16: 37.3 | K16: 36.4 | L16: 46.6 | M16: 45.2 | N16: 44.5 | O16: 39.9 | P16: 51.1 | Q16: 50 | R16: 50.9 | S16: 58.6 | T16: 64.3 | U16: 71.1 | V16: 81.8 | W16: 88 | X16: 85.4 | Y16: 91.6 | Z16: 87.9 | AA16: 75.4 | AB16: 88.2 | AC16: 101.9 | AD16: 109.6 | AE16: 97.7 | AF16: 118.7 | AG16: 145.1 | AH16: 172.7 | AI16: 195.6 | AJ16: 190.7 | AK16: 166 | AL16: 193.6 | AM16: 173.1 | AN16: 224.8 | AO16: 282 | AP16: 294.4 | AQ16: 274.7 | AR16: 319.8 | AS16: 369.6 | AT16: 358.4 | AU16: 358.4 | AV16: 380.8 | AW16: 423.1 | AX16: 466.8 | AY16: 550.3 | AZ16: 623.2 | BA16: 699.5 | BB16: 777.3 | BC16: 709.7 | BD16: 734.8 | BE16: 673.6 | BF16: 614.5 | BG16: 714.3 | BH16: 812 | BI16: 1041.9 | BJ16: 1216.6 | BK16: 1351.5 | BL16: 1159.8 | BM16: 841.8 | BN16: 989.5 | BO16: 1300.9 | BP16: 1388.1
A17: Current surplus of government enterprises | B17: T 1.10, 22 | C17: Curr Surplus Gov. Enterp | D17: 0 | E17: 0 | F17: 0 | G17: 0 | H17: 0 | I17: 0 | J17: 0 | K17: 0 | L17: 0 | M17: 0 | N17: 0 | O17: 0 | P17: 1 | Q17: 0.9 | R17: 0.8 | S17: 0.9 | T17: 1.4 | U17: 1.3 | V17: 1.3 | W17: 1 | X17: 0.9 | Y17: 1.2 | Z17: 1 | AA17: 0 | AB17: -0.2 | AC17: 0.5 | AD17: -0.4 | AE17: -0.9 | AF17: -3.2 | AG17: -1.8 | AH17: -2.7 | AI17: -2.2 | AJ17: -2.9 | AK17: -5.1 | AL17: -5.6 | AM17: -4.5 | AN17: -3.2 | AO17: -1.9 | AP17: 0.6 | AQ17: 0.9 | AR17: 0.2 | AS17: 2.6 | AT17: 4.9 | AU17: 1.6 | AV17: 5.7 | AW17: 8.2 | AX17: 8.7 | AY17: 9.6 | AZ17: 13.1 | BA17: 14.4 | BB17: 14.1 | BC17: 13.3 | BD17: 14.1 | BE17: 9.1 | BF17: 4 | BG17: 6.3 | BH17: 7 | BI17: 1.2 | BJ17: -3.5 | BK17: -4.2 | BL17: -11.8 | BM17: -16 | BN17: -15.6 | BO17: -19.5 | BP17: -26.5
A19: GVAhh | B19: T 1.3.5, 6 | C19: GVAhh | D19: 9.7 | E19: 10.6 | F19: 11.6 | G19: 13 | H19: 14.6 | I19: 16.4 | J19: 18.3 | K19: 20 | L19: 22 | M19: 23.9 | N19: 25.8 | O19: 27.8 | P19: 30.1 | Q19: 32.6 | R19: 34.6 | S19: 37 | T19: 39.1 | U19: 41.2 | V19: 43.6 | W19: 46.2 | X19: 49.1 | Y19: 51.9 | Z19: 56 | AA19: 59.8 | AB19: 65.5 | AC19: 70.8 | AD19: 76.5 | AE19: 83 | AF19: 90.8 | AG19: 98.7 | AH19: 107.9 | AI19: 121.3 | AJ19: 136 | AK19: 156.5 | AL19: 177.8 | AM19: 196.7 | AN19: 212.5 | AO19: 231 | AP19: 250.3 | AQ19: 268 | AR19: 288 | AS19: 313.1 | AT19: 337.2 | AU19: 363.3 | AV19: 383.7 | AW19: 405.3 | AX19: 428.3 | AY19: 461.3 | AZ19: 492.2 | BA19: 519.8 | BB19: 550.9 | BC19: 583.9 | BD19: 628.4 | BE19: 673.5 | BF19: 719.5 | BG19: 746 | BH19: 762.7 | BI19: 806 | BJ19: 864.4 | BK19: 924.8 | BL19: 968.1 | BM19: 1042.8 | BN19: 1048.3 | BO19: 1038.5 | BP19: 1055.2
A20: Less: EChh | B20: GVAhh - GVAooh | C20: Less: EChh | D20: 2.4 | E20: 2.3 | F20: 2.4 | G20: 2.6 | H20: 2.6 | I20: 2.6 | J20: 2.7 | K20: 2.6 | L20: 3 | M20: 3.3 | N20: 3.4 | O20: 3.4 | P20: 3.6 | Q20: 3.8 | R20: 3.7 | S20: 3.8 | T20: 3.8 | U20: 3.9 | V20: 3.9 | W20: 4 | X20: 4.2 | Y20: 4.4 | Z20: 4.4 | AA20: 4.5 | AB20: 4.5 | AC20: 4.6 | AD20: 4.8 | AE20: 4.6 | AF20: 4.7 | AG20: 5.4 | AH20: 5.9 | AI20: 6.5 | AJ20: 6.4 | AK20: 6 | AL20: 6.1 | AM20: 6.3 | AN20: 6.2 | AO20: 7.3 | AP20: 7.4 | AQ20: 7.8 | AR20: 7.7 | AS20: 8.4 | AT20: 9 | AU20: 9.3 | AV20: 9.2 | AW20: 10.3 | AX20: 10.9 | AY20: 11.3 | AZ20: 12.1 | BA20: 12.2 | BB20: 12.2 | BC20: 14.2 | BD20: 12.9 | BE20: 13.8 | BF20: 13 | BG20: 12.8 | BH20: 14.3 | BI20: 15.1 | BJ20: 15.4 | BK20: 16.5 | BL20: 18.1 | BM20: 19.2 | BN20: 17.5 | BO20: 15.3 | BP20: 16.5
A21: Less: Thh | B21: T 7.12, 135-136 | C21: Less: Thh | D21: 1.3 | E21: 1.4 | F21: 1.6 | G21: 1.8 | H21: 2 | I21: 2.2 | J21: 2.5 | K21: 2.7 | L21: 3.1 | M21: 3.6 | N21: 4 | O21: 4.5 | P21: 4.8 | Q21: 5.3 | R21: 5.9 | S21: 6.4 | T21: 7 | U21: 7.7 | V21: 8.3 | W21: 9 | X21: 10.1 | Y21: 11.4 | Z21: 12.7 | AA21: 14.4 | AB21: 15.8 | AC21: 17.1 | AD21: 18.5 | AE21: 19.8 | AF21: 21.8 | AG21: 24.1 | AH21: 26.5 | AI21: 27.1 | AJ21: 28 | AK21: 30.5 | AL21: 33.7 | AM21: 36.7 | AN21: 39.2 | AO21: 42.2 | AP21: 44.9 | AQ21: 47.7 | AR21: 52.2 | AS21: 55.6 | AT21: 60.1 | AU21: 63.8 | AV21: 68.4 | AW21: 70.6 | AX21: 70.6 | AY21: 73.8 | AZ21: 74.1 | BA21: 76.5 | BB21: 79.2 | BC21: 80.8 | BD21: 83.4 | BE21: 86.2 | BF21: 91 | BG21: 98.4 | BH21: 104.1 | BI21: 110.2 | BJ21: 114.7 | BK21: 123.9 | BL21: 126.1 | BM21: 133.7 | BN21: 142.3 | BO21: 143.6 | BP21: 146.3
A22: GOShh | C22: GOShh | D22: 6 | E22: 6.9 | F22: 7.6 | G22: 8.6 | H22: 10 | I22: 11.6 | J22: 13.1 | K22: 14.7 | L22: 15.9 | M22: 17 | N22: 18.4 | O22: 19.9 | P22: 21.7 | Q22: 23.5 | R22: 25 | S22: 26.8 | T22: 28.3 | U22: 29.6 | V22: 31.4 | W22: 33.2 | X22: 34.8 | Y22: 36.1 | Z22: 38.9 | AA22: 40.9 | AB22: 45.2 | AC22: 49.1 | AD22: 53.2 | AE22: 58.6 | AF22: 64.3 | AG22: 69.2 | AH22: 75.5 | AI22: 87.7 | AJ22: 101.6 | AK22: 120 | AL22: 138 | AM22: 153.7 | AN22: 167.1 | AO22: 181.5 | AP22: 198 | AQ22: 212.5 | AR22: 228.1 | AS22: 249.1 | AT22: 268.1 | AU22: 290.2 | AV22: 306.1 | AW22: 324.4 | AX22: 346.8 | AY22: 376.2 | AZ22: 406 | BA22: 431.1 | BB22: 459.5 | BC22: 488.9 | BD22: 532.1 | BE22: 573.5 | BF22: 615.5 | BG22: 634.8 | BH22: 644.3 | BI22: 680.7 | BJ22: 734.3 | BK22: 784.4 | BL22: 823.9 | BM22: 889.9 | BN22: 888.5 | BO22: 879.6 | BP22: 892.4
A23: Less: CFChh | B23: T 7.12, 140 | C23: Less: CFChh | D23: 2 | E23: 2.3 | F23: 2.5 | G23: 2.8 | H23: 3.2 | I23: 3.4 | J23: 3.7 | K23: 3.9 | L23: 4.2 | M23: 4.5 | N23: 4.8 | O23: 5 | P23: 5.2 | Q23: 5.5 | R23: 5.6 | S23: 5.8 | T23: 6 | U23: 6.3 | V23: 6.8 | W23: 7.3 | X23: 7.8 | Y23: 8.5 | Z23: 9.5 | AA23: 10.1 | AB23: 11.1 | AC23: 12.3 | AD23: 13.9 | AE23: 16 | AF23: 17.9 | AG23: 19.7 | AH23: 22.5 | AI23: 26.3 | AJ23: 30.5 | AK23: 35 | AL23: 38.8 | AM23: 41.4 | AN23: 43 | AO23: 45.5 | AP23: 47.9 | AQ23: 51.2 | AR23: 54.9 | AS23: 58.9 | AT23: 62.9 | AU23: 66.4 | AV23: 68.9 | AW23: 71.3 | AX23: 75.8 | AY23: 80.9 | AZ23: 86.6 | BA23: 91.2 | BB23: 96.6 | BC23: 102.3 | BD23: 110 | BE23: 118.5 | BF23: 127.7 | BG23: 135 | BH23: 146.2 | BI23: 163.5 | BJ23: 181.4 | BK23: 199.2 | BL23: 208 | BM23: 209.5 | BN23: 204.5 | BO23: 205.5 | BP23: 209.5
A24: NOShh | C24: NOShh | D24: 4 | E24: 4.6 | F24: 5.1 | G24: 5.8 | H24: 6.8 | I24: 8.2 | J24: 9.4 | K24: 10.8 | L24: 11.7 | M24: 12.5 | N24: 13.6 | O24: 14.9 | P24: 16.5 | Q24: 18 | R24: 19.4 | S24: 21 | T24: 22.3 | U24: 23.3 | V24: 24.6 | W24: 25.9 | X24: 27 | Y24: 27.6 | Z24: 29.4 | AA24: 30.8 | AB24: 34.1 | AC24: 36.8 | AD24: 39.3 | AE24: 42.6 | AF24: 46.4 | AG24: 49.5 | AH24: 53 | AI24: 61.4 | AJ24: 71.1 | AK24: 85 | AL24: 99.2 | AM24: 112.3 | AN24: 124.1 | AO24: 136 | AP24: 150.1 | AQ24: 161.3 | AR24: 173.2 | AS24: 190.2 | AT24: 205.2 | AU24: 223.8 | AV24: 237.2 | AW24: 253.1 | AX24: 271 | AY24: 295.3 | AZ24: 319.4 | BA24: 339.9 | BB24: 362.9 | BC24: 386.6 | BD24: 422.1 | BE24: 455 | BF24: 487.8 | BG24: 499.8 | BH24: 498.1 | BI24: 517.2 | BJ24: 552.9 | BK24: 585.2 | BL24: 615.9 | BM24: 680.4 | BN24: 684 | BO24: 674.1 | BP24: 682.9
A25: Net interest | B25: T 7.12, 137 | C25: Net Int | D25: 1.1 | E25: 1.3 | F25: 1.4 | G25: 1.6 | H25: 1.9 | I25: 2.2 | J25: 2.5 | K25: 2.9 | L25: 3.3 | M25: 3.9 | N25: 4.6 | O25: 5.2 | P25: 5.9 | Q25: 6.6 | R25: 7.2 | S25: 8.1 | T25: 8.8 | U25: 9.8 | V25: 10.7 | W25: 11.5 | X25: 12.2 | Y25: 13.1 | Z25: 14.5 | AA25: 15.9 | AB25: 18.2 | AC25: 21 | AD25: 24 | AE25: 27.5 | AF25: 32.1 | AG25: 36.1 | AH25: 42.6 | AI25: 50.3 | AJ25: 60.2 | AK25: 71.5 | AL25: 83.3 | AM25: 99.3 | AN25: 112.7 | AO25: 125.6 | AP25: 142.2 | AQ25: 156.6 | AR25: 165.9 | AS25: 176.2 | AT25: 190.2 | AU25: 205 | AV25: 211.9 | AW25: 213.6 | AX25: 204.7 | AY25: 204.9 | AZ25: 221.9 | BA25: 231.3 | BB25: 246.2 | BC25: 257.7 | BD25: 276.1 | BE25: 303.2 | BF25: 324.9 | BG25: 341.2 | BH25: 348.2 | BI25: 371.9 | BJ25: 423.9 | BK25: 491.2 | BL25: 538.9 | BM25: 547.2 | BN25: 488.8 | BO25: 434 | BP25: 401.1
A26: Current transfer payments | B26: T 7.12, 138 | C26: Curr Transfers | D26: 0 | E26: 0 | F26: 0 | G26: 0 | H26: 0 | I26: 0 | J26: 0 | K26: 0 | L26: 0 | M26: 0 | N26: 0 | O26: 0 | P26: 0 | Q26: 0 | R26: -0.1 | S26: -0.1 | T26: -0.1 | U26: -0.1 | V26: -0.1 | W26: 0 | X26: 0 | Y26: 0 | Z26: 0 | AA26: 0 | AB26: 0.1 | AC26: 0.2 | AD26: 0.1 | AE26: -0.3 | AF26: -0.2 | AG26: 0.1 | AH26: 0.4 | AI26: 0.5 | AJ26: -0.1 | AK26: -0.3 | AL26: 0.2 | AM26: 0 | AN26: -0.1 | AO26: -0.1 | AP26: -0.3 | AQ26: 1 | AR26: 1.6 | AS26: 0.7 | AT26: -0.9 | AU26: -0.8 | AV26: -0.6 | AW26: -1.4 | AX26: 1.5 | AY26: 1.8 | AZ26: 1.7 | BA26: -0.7 | BB26: 4.6 | BC26: 1.8 | BD26: 2 | BE26: 0.8 | BF26: -1 | BG26: 2.6 | BH26: 4.4 | BI26: 5.8 | BJ26: 11.3 | BK26: 10.7 | BL26: 8.9 | BM26: 3.2 | BN26: 5.7 | BO26: 3.9 | BP26: -2
A27: Rental income of persons with capital consumption adjustment | B27: T 7.12, 139 | C27: Rental Inc w/ CCAdj | D27: 3 | E27: 3.2 | F27: 3.6 | G27: 4.3 | H27: 4.9 | I27: 5.9 | J27: 7 | K27: 8 | L27: 8.4 | M27: 8.6 | N27: 9.1 | O27: 9.6 | P27: 10.5 | Q27: 11.5 | R27: 12.2 | S27: 13 | T27: 13.5 | U27: 13.6 | V27: 13.9 | W27: 14.4 | X27: 14.9 | Y27: 14.5 | Z27: 14.9 | AA27: 14.8 | AB27: 15.8 | AC27: 15.7 | AD27: 15.1 | AE27: 15.5 | AF27: 14.6 | AG27: 13.3 | AH27: 9.9 | AI27: 10.5 | AJ27: 11 | AK27: 13.8 | AL27: 15.7 | AM27: 13 | AN27: 11.4 | AO27: 10.6 | AP27: 8.2 | AQ27: 3.7 | AR27: 5.7 | AS27: 13.4 | AT27: 16 | AU27: 19.4 | AV27: 25.9 | AW27: 40.9 | AX27: 64.8 | AY27: 88.8 | AZ27: 95.9 | BA27: 109.2 | BB27: 112.1 | BC27: 127.3 | BD27: 144 | BE27: 151 | BF27: 163.9 | BG27: 156 | BH27: 145.5 | BI27: 139.5 | BJ27: 117.9 | BK27: 83.4 | BL27: 68.1 | BM27: 130 | BN27: 189.5 | BO27: 236.2 | BP27: 283.9
A29: GVAnpish | B29: T 1.3.5, 7 | C29: GVAnpish | D29: 3.5 | E29: 4 | F29: 4.4 | G29: 4.8 | H29: 5.3 | I29: 5.7 | J29: 6.3 | K29: 6.8 | L29: 7.4 | M29: 8.1 | N29: 8.9 | O29: 9.7 | P29: 10.6 | Q29: 12 | R29: 12.8 | S29: 14 | T29: 15.2 | U29: 16.5 | V29: 18.2 | W29: 20.4 | X29: 22.7 | Y29: 25.6 | Z29: 29.4 | AA29: 32.8 | AB29: 36.7 | AC29: 40.5 | AD29: 45.2 | AE29: 50.6 | AF29: 56.7 | AG29: 61.8 | AH29: 67.6 | AI29: 75.6 | AJ29: 84.8 | AK29: 97 | AL29: 109.7 | AM29: 122.7 | AN29: 135.6 | AO29: 149.3 | AP29: 159.8 | AQ29: 174.3 | AR29: 194.8 | AS29: 216.6 | AT29: 237 | AU29: 260.6 | AV29: 282.2 | AW29: 305.9 | AX29: 323.8 | AY29: 338.7 | AZ29: 359.9 | BA29: 377.2 | BB29: 398.3 | BC29: 426.3 | BD29: 454.5 | BE29: 483.7 | BF29: 513.4 | BG29: 552.1 | BH29: 584.5 | BI29: 617.7 | BJ29: 642 | BK29: 678.1 | BL29: 717.8 | BM29: 762.9 | BN29: 796.5 | BO29: 812.7 | BP29: 836.9
A30: Less: ECnpish | B30: T1.3.5, 7 - T7.12, 141 - T7.9, 14 | C30: Less: ECnpish | D30: 2.9 | E30: 3.3 | F30: 3.7 | G30: 4 | H30: 4.4 | I30: 4.7 | J30: 5.3 | K30: 5.7 | L30: 6.2 | M30: 6.8 | N30: 7.5 | O30: 8.2 | P30: 9 | Q30: 10.3 | R30: 11 | S30: 12.1 | T30: 13.1 | U30: 14.2 | V30: 15.6 | W30: 17.6 | X30: 19.5 | Y30: 22.1 | Z30: 25.4 | AA30: 28.3 | AB30: 31.6 | AC30: 34.7 | AD30: 38.8 | AE30: 43.2 | AF30: 48 | AG30: 52.4 | AH30: 57.3 | AI30: 64 | AJ30: 71.7 | AK30: 81.7 | AL30: 92 | AM30: 102.6 | AN30: 113.3 | AO30: 124.2 | AP30: 133.9 | AQ30: 146.2 | AR30: 165.2 | AS30: 184.5 | AT30: 202.3 | AU30: 223.4 | AV30: 242.2 | AW30: 263.2 | AX30: 277.5 | AY30: 291.6 | AZ30: 310.2 | BA30: 325.2 | BB30: 343.5 | BC30: 367.9 | BD30: 392.5 | BE30: 418.1 | BF30: 443.9 | BG30: 479.4 | BH30: 509.4 | BI30: 538.9 | BJ30: 559.4 | BK30: 590.9 | BL30: 620.5 | BM30: 656.5 | BN30: 687.3 | BO30: 703.6 | BP30: 724.5
A31: Less: Tnpish | B31: T 7.12, 141 | C31: Less: Tnpish | D31: 0.1 | E31: 0.1 | F31: 0.1 | G31: 0.1 | H31: 0.1 | I31: 0.2 | J31: 0.2 | K31: 0.2 | L31: 0.2 | M31: 0.2 | N31: 0.2 | O31: 0.3 | P31: 0.3 | Q31: 0.3 | R31: 0.3 | S31: 0.4 | T31: 0.4 | U31: 0.4 | V31: 0.5 | W31: 0.5 | X31: 0.6 | Y31: 0.6 | Z31: 0.7 | AA31: 0.8 | AB31: 0.9 | AC31: 1 | AD31: 1 | AE31: 1.1 | AF31: 1.1 | AG31: 1.2 | AH31: 1.3 | AI31: 1.3 | AJ31: 1.3 | AK31: 1.3 | AL31: 1.5 | AM31: 1.7 | AN31: 1.8 | AO31: 2 | AP31: 2.1 | AQ31: 2.2 | AR31: 2.5 | AS31: 2.6 | AT31: 2.9 | AU31: 3.1 | AV31: 3.4 | AW31: 3.6 | AX31: 3.6 | AY31: 3.9 | AZ31: 3.9 | BA31: 4 | BB31: 4.3 | BC31: 4.4 | BD31: 4.7 | BE31: 4.9 | BF31: 5.1 | BG31: 5.6 | BH31: 5.9 | BI31: 6.3 | BJ31: 6.6 | BK31: 7.1 | BL31: 7.8 | BM31: 8.3 | BN31: 8.8 | BO31: 8.8 | BP31: 9
A32: GOSnpish | C32: GOSnpish | D32: 0.5 | E32: 0.6 | F32: 0.6 | G32: 0.7 | H32: 0.8 | I32: 0.8 | J32: 0.8 | K32: 0.9 | L32: 1 | M32: 1.1 | N32: 1.2 | O32: 1.2 | P32: 1.3 | Q32: 1.4 | R32: 1.5 | S32: 1.5 | T32: 1.7 | U32: 1.9 | V32: 2.1 | W32: 2.3 | X32: 2.6 | Y32: 2.9 | Z32: 3.3 | AA32: 3.7 | AB32: 4.2 | AC32: 4.8 | AD32: 5.4 | AE32: 6.3 | AF32: 7.6 | AG32: 8.2 | AH32: 9 | AI32: 10.3 | AJ32: 11.8 | AK32: 14 | AL32: 16.2 | AM32: 18.4 | AN32: 20.5 | AO32: 23.1 | AP32: 23.8 | AQ32: 25.9 | AR32: 27.1 | AS32: 29.5 | AT32: 31.8 | AU32: 34.1 | AV32: 36.6 | AW32: 39.1 | AX32: 42.7 | AY32: 43.2 | AZ32: 45.8 | BA32: 48 | BB32: 50.5 | BC32: 54 | BD32: 57.3 | BE32: 60.7 | BF32: 64.4 | BG32: 67.1 | BH32: 69.2 | BI32: 72.5 | BJ32: 76 | BK32: 80.1 | BL32: 89.5 | BM32: 98.1 | BN32: 100.4 | BO32: 100.3 | BP32: 103.4
A33: Less: CFCnpish | B33: T 7.12, 144 | C33: Less: CFCnpish | D33: 0.4 | E33: 0.5 | F33: 0.5 | G33: 0.6 | H33: 0.7 | I33: 0.7 | J33: 0.8 | K33: 0.8 | L33: 0.9 | M33: 1 | N33: 1.1 | O33: 1.2 | P33: 1.2 | Q33: 1.3 | R33: 1.4 | S33: 1.5 | T33: 1.6 | U33: 1.7 | V33: 1.8 | W33: 2 | X33: 2.2 | Y33: 2.4 | Z33: 2.7 | AA33: 3 | AB33: 3.3 | AC33: 3.7 | AD33: 4.3 | AE33: 5.1 | AF33: 6 | AG33: 6.6 | AH33: 7.3 | AI33: 8.2 | AJ33: 9.3 | AK33: 10.6 | AL33: 11.8 | AM33: 12.9 | AN33: 13.6 | AO33: 14.4 | AP33: 15.2 | AQ33: 16.2 | AR33: 17.3 | AS33: 18.6 | AT33: 20.2 | AU33: 22.1 | AV33: 23.8 | AW33: 25.5 | AX33: 27.2 | AY33: 28.5 | AZ33: 29.8 | BA33: 30.7 | BB33: 32.2 | BC33: 34.8 | BD33: 37.8 | BE33: 41.3 | BF33: 44.6 | BG33: 47.7 | BH33: 51.2 | BI33: 55.4 | BJ33: 60.1 | BK33: 65 | BL33: 73.5 | BM33: 81.1 | BN33: 84.2 | BO33: 85.4 | BP33: 88.2
A34: NOSnpish | C34: NOSnpish | D34: 0.1 | E34: 0.1 | F34: 0.1 | G34: 0.1 | H34: 0.1 | I34: 0.1 | J34: 0 | K34: 0.1 | L34: 0.1 | M34: 0.1 | N34: 0.1 | O34: 0 | P34: 0.1 | Q34: 0.1 | R34: 0.1 | S34: 0 | T34: 0.1 | U34: 0.2 | V34: 0.3 | W34: 0.3 | X34: 0.4 | Y34: 0.5 | Z34: 0.6 | AA34: 0.7 | AB34: 0.9 | AC34: 1.1 | AD34: 1.1 | AE34: 1.2 | AF34: 1.6 | AG34: 1.6 | AH34: 1.7 | AI34: 2.1 | AJ34: 2.5 | AK34: 3.4 | AL34: 4.4 | AM34: 5.5 | AN34: 6.9 | AO34: 8.7 | AP34: 8.6 | AQ34: 9.7 | AR34: 9.8 | AS34: 10.9 | AT34: 11.6 | AU34: 12 | AV34: 12.8 | AW34: 13.6 | AX34: 15.5 | AY34: 14.7 | AZ34: 16 | BA34: 17.3 | BB34: 18.3 | BC34: 19.2 | BD34: 19.5 | BE34: 19.4 | BF34: 19.8 | BG34: 19.4 | BH34: 18 | BI34: 17.1 | BJ34: 15.9 | BK34: 15.1 | BL34: 16 | BM34: 17 | BN34: 16.2 | BO34: 14.9 | BP34: 15.2
A35: Net Interest | B35: T 7.12, 141 | C35: Net Int | D35: 0.1 | E35: 0.1 | F35: 0.1 | G35: 0.1 | H35: 0.1 | I35: 0.1 | J35: 0.1 | K35: 0.1 | L35: 0.1 | M35: 0.1 | N35: 0.1 | O35: 0.1 | P35: 0.1 | Q35: 0.1 | R35: 0.1 | S35: 0.1 | T35: 0.1 | U35: 0.2 | V35: 0.2 | W35: 0.3 | X35: 0.4 | Y35: 0.5 | Z35: 0.6 | AA35: 0.7 | AB35: 0.8 | AC35: 0.8 | AD35: 0.9 | AE35: 1.1 | AF35: 1.4 | AG35: 1.4 | AH35: 1.5 | AI35: 1.9 | AJ35: 2.3 | AK35: 3 | AL35: 3.7 | AM35: 4.8 | AN35: 5.9 | AO35: 7.7 | AP35: 7.5 | AQ35: 8.6 | AR35: 8.7 | AS35: 9.7 | AT35: 10.4 | AU35: 10.8 | AV35: 11.4 | AW35: 11.9 | AX35: 13.8 | AY35: 12.7 | AZ35: 13.4 | BA35: 14.5 | BB35: 15.2 | BC35: 15.6 | BD35: 15.9 | BE35: 15.8 | BF35: 15.8 | BG35: 15.2 | BH35: 14.2 | BI35: 13.4 | BJ35: 12.3 | BK35: 11.2 | BL35: 11.4 | BM35: 11.8 | BN35: 9.8 | BO35: 8.2 | BP35: 7.5
A36: Transfer Payments | B36: n.a. | C36: Curr Transfers | D36: 0 | E36: 0 | F36: 0 | G36: 0 | H36: 0 | I36: 0 | J36: 0 | K36: 0 | L36: 0 | M36: 0 | N36: 0 | O36: 0 | P36: 0 | Q36: 0 | R36: 0 | S36: 0 | T36: 0 | U36: 0 | V36: 0 | W36: 0 | X36: 0 | Y36: 0 | Z36: 0 | AA36: 0 | AB36: 0 | AC36: 0 | AD36: 0 | AE36: 0 | AF36: 0 | AG36: 0 | AH36: 0 | AI36: 0 | AJ36: 0 | AK36: 0 | AL36: 0 | AM36: 0 | AN36: 0 | AO36: 0 | AP36: 0 | AQ36: 0 | AR36: 0 | AS36: 0 | AT36: 0 | AU36: 0 | AV36: 0 | AW36: 0 | AX36: 0 | AY36: 0 | AZ36: 0 | BA36: 0 | BB36: 0 | BC36: 0 | BD36: 0 | BE36: 0 | BF36: 0 | BG36: 0 | BH36: 0 | BI36: 0 | BJ36: 0 | BK36: 0 | BL36: 0 | BM36: 0 | BN36: 0 | BO36: 0 | BP36: 0
A37: Rental inc of persons for tenant-occupied housing owned by npishes | B37: T 7.9,14 | C37: Rental Inc w/ CCAdj | D37: 0 | E37: 0 | F37: 0 | G37: 0 | H37: 0 | I37: 0 | J37: 0 | K37: 0 | L37: 0 | M37: 0 | N37: 0 | O37: 0 | P37: 0 | Q37: 0 | R37: 0 | S37: 0 | T37: 0 | U37: 0 | V37: 0 | W37: 0 | X37: 0 | Y37: 0 | Z37: 0 | AA37: 0 | AB37: 0.1 | AC37: 0.2 | AD37: 0.1 | AE37: 0.1 | AF37: 0.1 | AG37: 0.1 | AH37: 0.2 | AI37: 0.2 | AJ37: 0.2 | AK37: 0.4 | AL37: 0.6 | AM37: 0.8 | AN37: 1 | AO37: 1 | AP37: 1.1 | AQ37: 1.1 | AR37: 1.1 | AS37: 1.1 | AT37: 1.1 | AU37: 1.2 | AV37: 1.3 | AW37: 1.6 | AX37: 1.7 | AY37: 2.1 | AZ37: 2.6 | BA37: 2.8 | BB37: 3.1 | BC37: 3.5 | BD37: 3.6 | BE37: 3.6 | BF37: 4 | BG37: 4.2 | BH37: 3.8 | BI37: 3.8 | BJ37: 3.6 | BK37: 3.8 | BL37: 4.6 | BM37: 5.3 | BN37: 6.3 | BO37: 6.8 | BP37: 7.6
A39: GVAgengov | B39: T 1.3.5, 8 | C39: GVAgengov | D39: 27.8 | E39: 27.2 | F39: 28.3 | G39: 28.6 | H39: 35.8 | I39: 40.4 | J39: 42.2 | K39: 43.5 | L39: 45.8 | M39: 49.1 | N39: 52.4 | O39: 55.8 | P39: 58.3 | Q39: 62 | R39: 66 | S39: 70.7 | T39: 75.5 | U39: 81.1 | V39: 86.6 | W39: 96.8 | X39: 107 | Y39: 118.8 | Z39: 130 | AA39: 143.5 | AB39: 156.4 | AC39: 169.4 | AD39: 183.2 | AE39: 201.3 | AF39: 224.5 | AG39: 243.5 | AH39: 264.6 | AI39: 287.5 | AJ39: 313 | AK39: 348.5 | AL39: 385.3 | AM39: 419 | AN39: 445.4 | AO39: 485.1 | AP39: 523.4 | AQ39: 556.3 | AR39: 591.5 | AS39: 630.6 | AT39: 672.2 | AU39: 722.7 | AV39: 767.6 | AW39: 801.9 | AX39: 831.2 | AY39: 859.9 | AZ39: 884.8 | BA39: 911.3 | BB39: 940.3 | BC39: 972.5 | BD39: 1021.6 | BE39: 1078.8 | BF39: 1139.6 | BG39: 1211.4 | BH39: 1292.2 | BI39: 1359.3 | BJ39: 1436.5 | BK39: 1512 | BL39: 1604.6 | BM39: 1698 | BN39: 1761.9 | BO39: 1811.7 | BP39: 1842.4
A40: Less: ECgengov | B40: T 6.2A-D, 77, 78, 88 + 80, 83, 93 in successive tables | C40: Less: ECgengov | D40: 17.643 | E40: 18.077 | F40: 20.121 | G40: 21.24 | H40: 27.741 | I40: 31.527 | J40: 32.409 | K40: 33.044 | L40: 34.796 | M40: 37.224 | N40: 39.783 | O40: 42.903 | P40: 44.861 | Q40: 48.074 | R40: 51.591 | S40: 55.454 | T40: 59.34 | U40: 64.408 | V40: 69.28 | W40: 78.419 | X40: 87.405 | Y40: 97.801 | Z40: 107.461 | AA40: 119.393 | AB40: 130.895 | AC40: 143.077 | AD40: 155.418 | AE40: 169.739 | AF40: 189.598 | AG40: 206.353 | AH40: 224.995 | AI40: 244.672 | AJ40: 266.104 | AK40: 295.502 | AL40: 325.184 | AM40: 352.719 | AN40: 375.28 | AO40: 410.428 | AP40: 443.689 | AQ40: 470.632 | AR40: 499.549 | AS40: 532.319 | AT40: 567.101 | AU40: 609.736 | AV40: 647.51 | AW40: 677.261 | AX40: 700.654 | AY40: 724.077 | AZ40: 743.537 | BA40: 766.762 | BB40: 792.176 | BC40: 820.664 | BD40: 863.055 | BE40: 911.96 | BF40: 967.138 | BG40: 1034.139 | BH40: 1109.423 | BI40: 1165.924 | BJ40: 1227.786 | BK40: 1287.273 | BL40: 1361.375 | BM40: 1438.386 | BN40: 1491.464 | BO40: 1533.51 | BP40: 1551.439
A41: Less: Tgengov | B41: n.a. | C41: Less: Tgengov
A42: GOSgengov | C42: GOSgengov | D42: 10.157 | E42: 9.123 | F42: 8.179 | G42: 7.36 | H42: 8.059 | I42: 8.873 | J42: 9.791 | K42: 10.456 | L42: 11.004 | M42: 11.876 | N42: 12.617 | O42: 12.897 | P42: 13.439 | Q42: 13.926 | R42: 14.409 | S42: 15.246 | T42: 16.16 | U42: 16.692 | V42: 17.32 | W42: 18.381 | X42: 19.595 | Y42: 20.999 | Z42: 22.539 | AA42: 24.107 | AB42: 25.505 | AC42: 26.323 | AD42: 27.782 | AE42: 31.561 | AF42: 34.902 | AG42: 37.147 | AH42: 39.605 | AI42: 42.828 | AJ42: 46.896 | AK42: 52.998 | AL42: 60.116 | AM42: 66.281 | AN42: 70.12 | AO42: 74.672 | AP42: 79.711 | AQ42: 85.668 | AR42: 91.951 | AS42: 98.281 | AT42: 105.099 | AU42: 112.964 | AV42: 120.09 | AW42: 124.639 | AX42: 130.546 | AY42: 135.823 | AZ42: 141.263 | BA42: 144.538 | BB42: 148.124 | BC42: 151.836 | BD42: 158.545 | BE42: 166.84 | BF42: 172.462 | BG42: 177.261 | BH42: 182.777 | BI42: 193.376 | BJ42: 208.714 | BK42: 224.727 | BL42: 243.225 | BM42: 259.614 | BN42: 270.436 | BO42: 278.19 | BP42: 290.961
A43: Less: CFCgengov | B43: T 7.5, 22 | C43: Less: CFCgengov | D43: 10.2 | E43: 9.1 | F43: 8.2 | G43: 7.4 | H43: 8 | I43: 8.9 | J43: 9.7 | K43: 10.4 | L43: 11 | M43: 11.9 | N43: 12.7 | O43: 12.9 | P43: 13.4 | Q43: 13.9 | R43: 14.4 | S43: 15.2 | T43: 16.1 | U43: 16.7 | V43: 17.4 | W43: 18.3 | X43: 19.6 | Y43: 21 | Z43: 22.5 | AA43: 24.1 | AB43: 25.5 | AC43: 26.3 | AD43: 27.8 | AE43: 31.6 | AF43: 34.9 | AG43: 37.1 | AH43: 39.6 | AI43: 42.8 | AJ43: 46.9 | AK43: 53 | AL43: 60.1 | AM43: 66.2 | AN43: 70.1 | AO43: 74.7 | AP43: 79.7 | AQ43: 85.6 | AR43: 92 | AS43: 98.3 | AT43: 105.1 | AU43: 112.9 | AV43: 120.1 | AW43: 124.7 | AX43: 130.5 | AY43: 135.8 | AZ43: 141.2 | BA43: 144.5 | BB43: 148.1 | BC43: 151.9 | BD43: 158.5 | BE43: 166.8 | BF43: 172.5 | BG43: 177.3 | BH43: 182.8 | BI43: 193.4 | BJ43: 208.7 | BK43: 224.7 | BL43: 243.2 | BM43: 259.6 | BN43: 270.4 | BO43: 278.2 | BP43: 291
A44: NOSgengov | B44: NOSgov = 0 by construction | C44: NOSgengov | D44: 0 | E44: 0 | F44: 0 | G44: 0 | H44: 0 | I44: 0 | J44: 0 | K44: 0 | L44: 0 | M44: 0 | N44: 0 | O44: 0 | P44: 0 | Q44: 0 | R44: 0 | S44: 0 | T44: 0 | U44: 0 | V44: 0 | W44: 0 | X44: 0 | Y44: 0 | Z44: 0 | AA44: 0 | AB44: 0 | AC44: 0 | AD44: 0 | AE44: 0 | AF44: 0 | AG44: 0 | AH44: 0 | AI44: 0 | AJ44: 0 | AK44: 0 | AL44: 0 | AM44: 0 | AN44: 0 | AO44: 0 | AP44: 0 | AQ44: 0 | AR44: 0 | AS44: 0 | AT44: 0 | AU44: 0 | AV44: 0 | AW44: 0 | AX44: 0 | AY44: 0 | AZ44: 0 | BA44: 0 | BB44: 0 | BC44: 0 | BD44: 0 | BE44: 0 | BF44: 0 | BG44: 0 | BH44: 0 | BI44: 0 | BJ44: 0 | BK44: 0 | BL44: 0 | BM44: 0 | BN44: 0 | BO44: 0 | BP44: 0
A45: Net Interest | B45: n.a. | C45: Net Int
A46: Transfer Payments (negative of net int paid) | B46: n.a. | C46: Curr Transfers
A47: Rental inc of persons | B47: n.a. | C47: Rental Inc w/ CCAdj
A49: GVAgoventerp | C49: GVAgoventerp | D49: 2.365 | E49: 2.767 | F49: 3.012 | G49: 3.14 | H49: 3.545 | I49: 4.032 | J49: 4.151 | K49: 4.198 | L49: 4.552 | M49: 4.834 | N49: 5.07 | O49: 5.629 | P49: 7.008 | Q49: 7.459 | R49: 7.713 | S49: 8.21 | T49: 9.28 | U49: 9.797 | V49: 10.423 | W49: 10.875 | X49: 11.533 | Y49: 13.148 | Z49: 14.176 | AA49: 15.318 | AB49: 16.644 | AC49: 18.809 | AD49: 19.867 | AE49: 22.701 | AF49: 24.124 | AG49: 27.748 | AH49: 29.237 | AI49: 32.833 | AJ49: 36.082 | AK49: 39.484 | AL49: 45.021 | AM49: 49.197 | AN49: 54.274 | AO49: 59.588 | AP49: 66.941 | AQ49: 70.271 | AR49: 73.69 | AS49: 82.222 | AT49: 88.863 | AU49: 92.993 | AV49: 101.72 | AW49: 109.783 | AX49: 112.839 | AY49: 118.783 | AZ49: 125.692 | BA49: 130.674 | BB49: 134.883 | BC49: 138.433 | BD49: 144.328 | BE49: 148.093 | BF49: 148.265 | BG49: 156.284 | BH49: 158.896 | BI49: 164.911 | BJ49: 166.467 | BK49: 173.384 | BL49: 173.962 | BM49: 176.646 | BN49: 177.444 | BO49: 175.804 | BP49: 173.568
A50: Less: ECgoventerp | B50: T 6.2A-D, 16 + 19, divided by 1000 | C50: Less: ECgoventerp | D50: 1.965 | E50: 2.267 | F50: 2.512 | G50: 2.64 | H50: 2.945 | I50: 3.432 | J50: 3.451 | K50: 3.498 | L50: 3.752 | M50: 3.934 | N50: 4.17 | O50: 4.629 | P50: 5.008 | Q50: 5.459 | R50: 5.713 | S50: 6.11 | T50: 6.58 | U50: 7.097 | V50: 7.623 | W50: 8.275 | X50: 8.833 | Y50: 9.948 | Z50: 10.976 | AA50: 12.818 | AB50: 14.044 | AC50: 15.209 | AD50: 16.767 | AE50: 19.301 | AF50: 22.224 | AG50: 24.048 | AH50: 25.937 | AI50: 28.333 | AJ50: 31.382 | AK50: 35.784 | AL50: 40.621 | AM50: 42.797 | AN50: 45.974 | AO50: 49.288 | AP50: 53.441 | AQ50: 55.571 | AR50: 58.89 | AS50: 64.022 | AT50: 67.263 | AU50: 73.493 | AV50: 77.22 | AW50: 81.783 | AX50: 83.039 | AY50: 86.783 | AZ50: 88.992 | BA50: 91.674 | BB50: 94.783 | BC50: 98.033 | BD50: 101.628 | BE50: 108.293 | BF50: 112.165 | BG50: 116.284 | BH50: 116.496 | BI50: 125.211 | BJ50: 128.067 | BK50: 132.984 | BL50: 137.662 | BM50: 141.146 | BN50: 139.944 | BO50: 140.004 | BP50: 141.668
A51: Less: Tgoventerp | C51: Less: Tgoventerp | D51: 0 | E51: 0 | F51: 0 | G51: 0 | H51: 0 | I51: 0 | J51: 0 | K51: 0 | L51: 0 | M51: 0 | N51: 0 | O51: 0 | P51: 0 | Q51: 0 | R51: 0 | S51: 0 | T51: 0 | U51: 0 | V51: 0 | W51: 0 | X51: 0 | Y51: 0 | Z51: 0 | AA51: 0 | AB51: 0 | AC51: 0 | AD51: 0 | AE51: 0 | AF51: 0 | AG51: 0 | AH51: 0 | AI51: 0 | AJ51: 0 | AK51: 0 | AL51: 0 | AM51: 0 | AN51: 0 | AO51: 0 | AP51: 0 | AQ51: 0 | AR51: 0 | AS51: 0 | AT51: 0 | AU51: 0 | AV51: 0 | AW51: 0 | AX51: 0 | AY51: 0 | AZ51: 0 | BA51: 0 | BB51: 0 | BC51: 0 | BD51: 0 | BE51: 0 | BF51: 0 | BG51: 0 | BH51: 0 | BI51: 0 | BJ51: 0 | BK51: 0 | BL51: 0 | BM51: 0 | BN51: 0 | BO51: 0 | BP51: 0
A52: GOSgoventerp | C52: GOSgoventerp | D52: 0.4 | E52: 0.5 | F52: 0.5 | G52: 0.5 | H52: 0.6 | I52: 0.6 | J52: 0.7 | K52: 0.7 | L52: 0.8 | M52: 0.9 | N52: 0.9 | O52: 1 | P52: 2 | Q52: 2 | R52: 2 | S52: 2.1 | T52: 2.7 | U52: 2.7 | V52: 2.8 | W52: 2.6 | X52: 2.7 | Y52: 3.2 | Z52: 3.2 | AA52: 2.5 | AB52: 2.6 | AC52: 3.6 | AD52: 3.1 | AE52: 3.4 | AF52: 1.9 | AG52: 3.7 | AH52: 3.3 | AI52: 4.5 | AJ52: 4.7 | AK52: 3.7 | AL52: 4.4 | AM52: 6.4 | AN52: 8.3 | AO52: 10.3 | AP52: 13.5 | AQ52: 14.7 | AR52: 14.8 | AS52: 18.2 | AT52: 21.6 | AU52: 19.5 | AV52: 24.5 | AW52: 28 | AX52: 29.8 | AY52: 32 | AZ52: 36.7 | BA52: 39 | BB52: 40.1 | BC52: 40.4 | BD52: 42.7 | BE52: 39.8 | BF52: 36.1 | BG52: 40 | BH52: 42.4 | BI52: 39.7 | BJ52: 38.4 | BK52: 40.4 | BL52: 36.3 | BM52: 35.5 | BN52: 37.5 | BO52: 35.8 | BP52: 31.9
A53: Less: CFCgoventerp | B53: T 7.5, 25 | C53: Less: CFCgoventerp | D53: 0.4 | E53: 0.5 | F53: 0.5 | G53: 0.5 | H53: 0.6 | I53: 0.6 | J53: 0.7 | K53: 0.7 | L53: 0.8 | M53: 0.9 | N53: 0.9 | O53: 1 | P53: 1 | Q53: 1.1 | R53: 1.2 | S53: 1.2 | T53: 1.3 | U53: 1.4 | V53: 1.5 | W53: 1.6 | X53: 1.8 | Y53: 2 | Z53: 2.2 | AA53: 2.5 | AB53: 2.8 | AC53: 3.1 | AD53: 3.5 | AE53: 4.3 | AF53: 5.1 | AG53: 5.5 | AH53: 6 | AI53: 6.7 | AJ53: 7.6 | AK53: 8.8 | AL53: 10 | AM53: 10.9 | AN53: 11.5 | AO53: 12.2 | AP53: 12.9 | AQ53: 13.8 | AR53: 14.6 | AS53: 15.6 | AT53: 16.7 | AU53: 17.9 | AV53: 18.8 | AW53: 19.8 | AX53: 21.1 | AY53: 22.4 | AZ53: 23.6 | BA53: 24.6 | BB53: 26 | BC53: 27.1 | BD53: 28.6 | BE53: 30.7 | BF53: 32.1 | BG53: 33.7 | BH53: 35.4 | BI53: 38.5 | BJ53: 41.9 | BK53: 44.6 | BL53: 48.1 | BM53: 51.5 | BN53: 53.1 | BO53: 55.3 | BP53: 58.4
A54: NOSgoventerp (current surplus of government enterprises) | B54: T 1.10, 22 | C54: NOSgoventerp | D54: 0 | E54: 0 | F54: 0 | G54: 0 | H54: 0 | I54: 0 | J54: 0 | K54: 0 | L54: 0 | M54: 0 | N54: 0 | O54: 0 | P54: 1 | Q54: 0.9 | R54: 0.8 | S54: 0.9 | T54: 1.4 | U54: 1.3 | V54: 1.3 | W54: 1 | X54: 0.9 | Y54: 1.2 | Z54: 1 | AA54: 0 | AB54: -0.2 | AC54: 0.5 | AD54: -0.4 | AE54: -0.9 | AF54: -3.2 | AG54: -1.8 | AH54: -2.7 | AI54: -2.2 | AJ54: -2.9 | AK54: -5.1 | AL54: -5.6 | AM54: -4.5 | AN54: -3.2 | AO54: -1.9 | AP54: 0.6 | AQ54: 0.9 | AR54: 0.2 | AS54: 2.6 | AT54: 4.9 | AU54: 1.6 | AV54: 5.7 | AW54: 8.2 | AX54: 8.7 | AY54: 9.6 | AZ54: 13.1 | BA54: 14.4 | BB54: 14.1 | BC54: 13.3 | BD54: 14.1 | BE54: 9.1 | BF54: 4 | BG54: 6.3 | BH54: 7 | BI54: 1.2 | BJ54: -3.5 | BK54: -4.2 | BL54: -11.8 | BM54: -16 | BN54: -15.6 | BO54: -19.5 | BP54: -26.5
A55: Net Interest | B55: n.a. | C55: Net Int
A56: Transfer Payments | B56: n.a. | C56: Curr Transfers
A57: Rental inc of persons | B57: n.a. | C57: Rental Inc w/ CCAdj
A59: GVAbusnipa | B59: GDP - GVAhh - GVAnpish - GVAgengov - GVAgoventerp | C59: GVAbusnipa | D59: 200.735 | E59: 224.533 | F59: 219.888 | G59: 244.16 | H59: 280.055 | I59: 291.768 | J59: 308.349 | K59: 305.902 | L59: 334.948 | M59: 351.466 | N59: 368.93 | O59: 368.271 | P59: 400.592 | Q59: 412.341 | R59: 423.687 | S59: 455.79 | T59: 478.72 | U59: 515.003 | V59: 560.277 | W59: 613.425 | X59: 642.067 | Y59: 700.352 | Z59: 754.824 | AA59: 786.882 | AB59: 851.556 | AC59: 938.391 | AD59: 1057.533 | AE59: 1141.899 | AF59: 1241.576 | AG59: 1392.852 | AH59: 1560.763 | AI59: 1776.567 | AJ59: 1992.318 | AK59: 2146.616 | AL59: 2408.979 | AM59: 2465.603 | AN59: 2686.826 | AO59: 3005.912 | AP59: 3217.059 | AQ59: 3391.229 | AR59: 3588.41 | AS59: 3857.878 | AT59: 4146.837 | AU59: 4360.907 | AV59: 4456.88 | AW59: 4719.417 | AX59: 4971.261 | AY59: 5306.517 | AZ59: 5552.108 | BA59: 5899.526 | BB59: 6308.017 | BC59: 6672.367 | BD59: 7104.672 | BE59: 7567.407 | BF59: 7765.435 | BG59: 7976.516 | BH59: 8343.804 | BI59: 8905.389 | BJ59: 9513.633 | BK59: 10088.916 | BL59: 10564.238 | BM59: 10611.154 | BN59: 10189.556 | BO59: 10660.196 | BP59: 11167.632
A60: SD | C60: SDnipa | D60: 2.3 | E60: -0.5 | F60: 1.8 | G60: 1.4 | H60: 3.6 | I60: 2.7 | J60: 4 | K60: 3.1 | L60: 2.4 | M60: -1.8 | N60: -0.1 | O60: 1 | P60: 0.5 | Q60: -1 | R60: -0.6 | S60: 0.3 | T60: -0.8 | U60: 0.8 | V60: 1.5 | W60: 6.2 | X60: 4.5 | Y60: 4.3 | Z60: 2.9 | AA60: 6.9 | AB60: 11 | AC60: 8.9 | AD60: 8 | AE60: 9.8 | AF60: 16.3 | AG60: 23.5 | AH60: 21.2 | AI60: 26.1 | AJ60: 47 | AK60: 45.3 | AL60: 36.6 | AM60: 4.8 | AN60: 49.7 | AO60: 31.5 | AP60: 42.3 | AQ60: 67.7 | AR60: 32.9 | AS60: -9.5 | AT60: 56.1 | AU60: 84.2 | AV60: 79.7 | AW60: 110 | AX60: 135.8 | AY60: 108.8 | AZ60: 52.5 | BA60: 25.9 | BB60: -14 | BC60: -85.3 | BD60: -71.1 | BE60: -134 | BF60: -103.4 | BG60: -22.1 | BH60: 16.6 | BI60: -22.3 | BJ60: -95.1 | BK60: -242.3 | BL60: -12 | BM60: -2.4 | BN60: 118.3 | BO60: 23.3 | BP60: 31.9
A61: Less: ECbusnipa | B61: EC - EChh - ECnpish - ECgengov - ECgoventerp | C61: ECbusnipa | D61: 105.092 | E61: 115.956 | F61: 113.067 | G61: 124.72 | H61: 143.714 | I61: 153.941 | J61: 166.34 | K61: 164.358 | L61: 178.052 | M61: 193.342 | N61: 202.747 | O61: 200.468 | P61: 218.631 | Q61: 228.967 | R61: 233.396 | S61: 249.736 | T61: 262.48 | U61: 281.095 | V61: 303.097 | W61: 334.306 | X61: 355.162 | Y61: 390.051 | Z61: 429.363 | AA61: 452.189 | AB61: 477.861 | AC61: 527.514 | AD61: 595.415 | AE61: 653.46 | AF61: 684.678 | AG61: 771.199 | AH61: 866.468 | AI61: 992.095 | AJ61: 1122.814 | AK61: 1228.714 | AL61: 1355.895 | AM61: 1415.384 | AN61: 1494.946 | AO61: 1654.484 | AP61: 1773.57 | AQ61: 1879.197 | AR61: 2005.661 | AS61: 2165.759 | AT61: 2286.936 | AU61: 2412.671 | AV61: 2464.97 | AW61: 2601.856 | AX61: 2728.307 | AY61: 2888.74 | AZ61: 3044.471 | BA61: 3199.664 | BB61: 3427.341 | BC61: 3727.003 | BD61: 3989.117 | BE61: 4341.347 | BF61: 4448.297 | BG61: 4473.777 | BH61: 4638.681 | BI61: 4854.465 | BJ61: 5140.847 | BK61: 5455.943 | BL61: 5725.363 | BM61: 5823.868 | BN61: 5470.992 | BO61: 5584.786 | BP61: 5869.093
A62: Less: Tbusnipa | B62: T - Thh - Tnpish - Tgengov -Tgoventerp | C62: Tbusnipa | D62: 16.5 | E62: 17.9 | F62: 18.9 | G62: 20.5 | H62: 21.9 | I62: 24.3 | J62: 26.3 | K62: 26.1 | L62: 28.4 | M62: 30 | N62: 31.7 | O62: 32 | P62: 34.9 | Q62: 37.8 | R62: 38.8 | S62: 41.3 | T62: 43.8 | U62: 46.5 | V62: 48.9 | W62: 49.8 | X62: 53.4 | Y62: 60.2 | Z62: 66 | AA62: 71.4 | AB62: 79.1 | AC62: 83.2 | AD62: 92.5 | AE62: 100.7 | AF62: 107.9 | AG62: 116 | AH62: 124.8 | AI62: 133.6 | AJ62: 142.3 | AK62: 158.7 | AL62: 188.9 | AM62: 187.5 | AN62: 201 | AO62: 224.5 | AP62: 239.7 | AQ62: 248.6 | AR62: 262.5 | AS62: 286.8 | AT62: 308.5 | AU62: 331.1 | AV62: 357.8 | AW62: 379.1 | AX62: 392.2 | AY62: 435 | AZ62: 445.1 | BA62: 465.1 | BB62: 494.3 | BC62: 517.9 | BD62: 540.3 | BE62: 571.7 | BF62: 572.9 | BG62: 617.4 | BH62: 647.7 | BI62: 700.5 | BJ62: 748 | BK62: 804.4 | BL62: 838.7 | BM62: 843.7 | BN62: 812.4 | BO62: 845.6 | BP62: 881
A63: GOSbusnipa | B63: GVAbus - ECbus - Tbus - SD | C63: GOSbusnipa | D63: 76.843 | E63: 91.177 | F63: 86.121 | G63: 97.54 | H63: 110.841 | I63: 110.827 | J63: 111.709 | K63: 112.344 | L63: 126.096 | M63: 129.924 | N63: 134.583 | O63: 134.803 | P63: 146.561 | Q63: 146.574 | R63: 152.091 | S63: 164.454 | T63: 173.24 | U63: 186.608 | V63: 206.78 | W63: 223.119 | X63: 229.005 | Y63: 245.801 | Z63: 256.561 | AA63: 256.393 | AB63: 283.595 | AC63: 318.777 | AD63: 361.618 | AE63: 377.939 | AF63: 432.698 | AG63: 482.153 | AH63: 548.295 | AI63: 624.772 | AJ63: 680.204 | AK63: 713.902 | AL63: 827.584 | AM63: 857.919 | AN63: 941.18 | AO63: 1095.428 | AP63: 1161.489 | AQ63: 1195.732 | AR63: 1287.349 | AS63: 1414.819 | AT63: 1495.301 | AU63: 1532.936 | AV63: 1554.41 | AW63: 1628.461 | AX63: 1714.954 | AY63: 1873.977 | AZ63: 2010.037 | BA63: 2208.862 | BB63: 2400.376 | BC63: 2512.764 | BD63: 2646.355 | BE63: 2788.36 | BF63: 2847.638 | BG63: 2907.439 | BH63: 3040.823 | BI63: 3372.724 | BJ63: 3719.886 | BK63: 4070.873 | BL63: 4012.175 | BM63: 3945.986 | BN63: 3787.864 | BO63: 4206.51 | BP63: 4385.639
A64: Less: CFCbusnipa | B64: CFC - CFChh - CFCnpish - CFCgengov - CFCgoventerp | C64: CFCbusnipa | D64: 13.6 | E64: 16.1 | F64: 17.5 | G64: 18.6 | H64: 21.3 | I64: 22.7 | J64: 23.7 | K64: 24.8 | L64: 25.9 | M64: 28.8 | N64: 31.3 | O64: 33.2 | P64: 34.6 | Q64: 34.8 | R64: 35.6 | S64: 36.9 | T64: 38.3 | U64: 40.3 | V64: 43.2 | W64: 47.3 | X64: 51.5 | Y64: 56.5 | Z64: 62.3 | AA64: 68.6 | AB64: 75.1 | AC64: 81.8 | AD64: 91.3 | AE64: 106.7 | AF64: 126.5 | AG64: 139.3 | AH64: 156.4 | AI64: 177.4 | AJ64: 204.6 | AK64: 236.7 | AL64: 272.6 | AM64: 302.1 | AN64: 312.9 | AO64: 327.5 | AP64: 349.7 | AQ64: 371.7 | AR64: 392.3 | AS64: 419.6 | AT64: 446.6 | AU64: 471.9 | AV64: 492.8 | AW64: 503.1 | AX64: 523.4 | AY64: 551.6 | AZ64: 588.3 | BA64: 621.5 | BB64: 660.9 | BC64: 704.4 | BD64: 759.5 | BE64: 827 | BF64: 879.3 | BG64: 911.3 | BH64: 938.5 | BI64: 982 | BJ64: 1049.3 | BK64: 1127.2 | BL64: 1194.7 | BM64: 1252.4 | BN64: 1254.1 | BO64: 1249 | BP64: 1289.7
A65: NOSbusnipa | B65: GOSbus - CFCbus | C65: NOSbusnipa | D65: 63.2 | E65: 75.1 | F65: 68.6 | G65: 78.9 | H65: 89.6 | I65: 88.1 | J65: 88.1 | K65: 87.6 | L65: 100.2 | M65: 101.1 | N65: 103.2 | O65: 101.6 | P65: 112 | Q65: 111.8 | R65: 116.5 | S65: 127.6 | T65: 135 | U65: 146.3 | V65: 163.5 | W65: 175.9 | X65: 177.5 | Y65: 189.3 | Z65: 194.3 | AA65: 187.8 | AB65: 208.5 | AC65: 237 | AD65: 270.3 | AE65: 271.2 | AF65: 306.2 | AG65: 342.9 | AH65: 391.9 | AI65: 447.4 | AJ65: 475.6 | AK65: 477.2 | AL65: 555 | AM65: 555.9 | AN65: 628.3 | AO65: 767.9 | AP65: 811.8 | AQ65: 824.1 | AR65: 895 | AS65: 995.2 | AT65: 1048.7 | AU65: 1061.1 | AV65: 1061.6 | AW65: 1125.3 | AX65: 1191.6 | AY65: 1322.4 | AZ65: 1421.8 | BA65: 1587.4 | BB65: 1739.5 | BC65: 1808.3 | BD65: 1886.9 | BE65: 1961.4 | BF65: 1968.3 | BG65: 1996.1 | BH65: 2102.3 | BI65: 2390.7 | BJ65: 2670.6 | BK65: 2943.7 | BL65: 2817.5 | BM65: 2693.6 | BN65: 2533.8 | BO65: 2957.5 | BP65: 3095.9
A66: Net interest and miscellaneous payments (NIbus) | B66: NI - NIhh - NInpish - NIgengov - NIgoventerp | C66: Net Int | D66: 1.2 | E66: 1.1 | F66: 1.3 | G66: 1.4 | H66: 1.5 | I66: 1.7 | J66: 2 | K66: 2.4 | L66: 2.7 | M66: 2.8 | N66: 3.3 | O66: 4.1 | P66: 3.5 | Q66: 3.7 | R66: 4.8 | S66: 5.6 | T66: 5.8 | U66: 6.9 | V66: 8.2 | W66: 10.1 | X66: 12.3 | Y66: 13.1 | Z66: 18.1 | AA66: 23.3 | AB66: 25.2 | AC66: 27.1 | AD66: 32.6 | AE66: 44.1 | AF66: 49.7 | AG66: 47.7 | AH66: 55.7 | AI66: 64 | AJ66: 79 | AK66: 108.5 | AL66: 141.9 | AM66: 162.9 | AN66: 164.5 | AO66: 193.8 | AP66: 203.1 | AQ66: 222 | AR66: 221.1 | AS66: 232.2 | AT66: 273.4 | AU66: 267.8 | AV66: 238.7 | AW66: 203.2 | AX66: 188.5 | AY66: 194.5 | AZ66: 182.2 | BA66: 191.4 | BB66: 225.9 | BC66: 286.9 | BD66: 277.9 | BE66: 323.5 | BF66: 316.2 | BG66: 253.2 | BH66: 233.1 | BI66: 184 | BJ66: 242.7 | BK66: 327.7 | BL66: 401.8 | BM66: 537.8 | BN66: 343.3 | BO66: 310.8 | BP66: 297.8
A67: Current transfer payments (net) (CTbus) | B67: CT - CThh - CTnpish - CTgengov - CTgoventerp | C67: Curr Transfers | D67: 0.7 | E67: 0.7 | F67: 0.7 | G67: 0.9 | H67: 1.2 | I67: 1.3 | J67: 1.2 | K67: 1 | L67: 1.4 | M67: 1.7 | N67: 1.9 | O67: 1.8 | P67: 1.8 | Q67: 1.9 | R67: 2.1 | S67: 2.3 | T67: 2.8 | U67: 3.2 | V67: 3.7 | W67: 3.5 | X67: 3.8 | Y67: 4.3 | Z67: 4.9 | AA67: 4.5 | AB67: 4.2 | AC67: 4.7 | AD67: 5.9 | AE67: 7.4 | AF67: 9.6 | AG67: 9.4 | AH67: 8.1 | AI67: 10.3 | AJ67: 13.4 | AK67: 15 | AL67: 17.7 | AM67: 20.6 | AN67: 22.7 | AO67: 30.4 | AP67: 35.5 | AQ67: 35.9 | AR67: 32.5 | AS67: 32.9 | AT67: 40.1 | AU67: 40.9 | AV67: 40.5 | AW67: 42.1 | AX67: 39 | AY67: 40.1 | AZ67: 44.1 | BA67: 54.5 | BB67: 46.7 | BC67: 63.4 | BD67: 67 | BE67: 86.2 | BF67: 102.3 | BG67: 79.8 | BH67: 71.7 | BI67: 75.9 | BJ67: 84.6 | BK67: 72.3 | BL67: 94.4 | BM67: 119.8 | BN67: 127.7 | BO67: 136.1 | BP67: 134.6
A68: Proprietors' income with inventory valuation and capital consumption adjustments (PIbus) | C68: Prop Inc w/IVA and CCAdj | D68: 34.5 | E68: 39.2 | F68: 34.6 | G68: 37.5 | H68: 42.7 | I68: 43.1 | J68: 42 | K68: 42.3 | L68: 44.3 | M68: 45.9 | N68: 47.8 | O68: 50.2 | P68: 50.3 | Q68: 50.7 | R68: 53.2 | S68: 55.3 | T68: 56.5 | U68: 59.4 | V68: 63.9 | W68: 68.2 | X68: 69.8 | Y68: 74.2 | Z68: 77.5 | AA68: 78.5 | AB68: 84.7 | AC68: 96 | AD68: 113.6 | AE68: 113.5 | AF68: 119.6 | AG68: 132.2 | AH68: 146 | AI68: 167.5 | AJ68: 181.1 | AK68: 173.5 | AL68: 181.6 | AM68: 174.8 | AN68: 190.7 | AO68: 233.1 | AP68: 246.1 | AQ68: 262.6 | AR68: 294.2 | AS68: 334.8 | AT68: 351.6 | AU68: 365.1 | AV68: 367.3 | AW68: 414.9 | AX68: 449.6 | AY68: 485.1 | AZ68: 516 | BA68: 583.7 | BB68: 628.2 | BC68: 687.5 | BD68: 746.8 | BE68: 817.5 | BF68: 870.7 | BG68: 890.3 | BH68: 930.6 | BI68: 1033.8 | BJ68: 1069.8 | BK68: 1133 | BL68: 1090.4 | BM68: 1097.9 | BN68: 979.4 | BO68: 1103.4 | BP68: 1157.3
A69: Rental income of persons with capital consumption adjustment (RIbus) | B69: RI - RIhh - RInpish - RIgengov - RIgoventerp | C69: Rental Inc w/ CCAdj | D69: 4.2 | E69: 4.6 | F69: 4.5 | G69: 4.8 | H69: 5.1 | I69: 5.3 | J69: 5.4 | K69: 5.4 | L69: 5.4 | M69: 5.5 | N69: 5.4 | O69: 5.6 | P69: 5.5 | Q69: 5.5 | R69: 5.5 | S69: 5.6 | T69: 5.8 | U69: 5.8 | V69: 6 | W69: 6.1 | X69: 6 | Y69: 6.1 | Z69: 6 | AA69: 6.3 | AB69: 6.3 | AC69: 7.2 | AD69: 8.7 | AE69: 8.4 | AF69: 8.7 | AG69: 8.7 | AH69: 9.5 | AI69: 10.2 | AJ69: 11.4 | AK69: 14.3 | AL69: 20.2 | AM69: 24.3 | AN69: 25.8 | AO69: 28.4 | AP69: 32.6 | AQ69: 29 | AR69: 27.4 | AS69: 25.7 | AT69: 25.3 | AU69: 29.2 | AV69: 34.4 | AW69: 42.1 | AX69: 47.6 | AY69: 52 | AZ69: 56.1 | BA69: 58.4 | BB69: 61.3 | BC69: 60.7 | BD69: 60.6 | BE69: 60.7 | BF69: 64.5 | BG69: 58.5 | BH69: 54.9 | BI69: 55.1 | BJ69: 56.7 | BK69: 59.3 | BL69: 71 | BM69: 96.3 | BN69: 93.9 | BO69: 106.2 | BP69: 118.2
A70: Corp Profit with inventory valuation and capital consumption adjustments, domestic industries | C70: Corp Profit w/IVA and CCAdj | D70: 22.5 | E70: 29.6 | F70: 27.6 | G70: 34.4 | H70: 39.1 | I70: 37 | J70: 37.3 | K70: 36.4 | L70: 46.6 | M70: 45.2 | N70: 44.5 | O70: 39.9 | P70: 51.1 | Q70: 50 | R70: 50.9 | S70: 58.6 | T70: 64.3 | U70: 71.1 | V70: 81.8 | W70: 88 | X70: 85.4 | Y70: 91.6 | Z70: 87.9 | AA70: 75.4 | AB70: 88.2 | AC70: 101.9 | AD70: 109.6 | AE70: 97.7 | AF70: 118.7 | AG70: 145.1 | AH70: 172.7 | AI70: 195.6 | AJ70: 190.7 | AK70: 166 | AL70: 193.6 | AM70: 173.1 | AN70: 224.8 | AO70: 282 | AP70: 294.4 | AQ70: 274.7 | AR70: 319.8 | AS70: 369.6 | AT70: 358.4 | AU70: 358.4 | AV70: 380.8 | AW70: 423.1 | AX70: 466.8 | AY70: 550.3 | AZ70: 623.2 | BA70: 699.5 | BB70: 777.3 | BC70: 709.7 | BD70: 734.8 | BE70: 673.6 | BF70: 614.5 | BG70: 714.3 | BH70: 812 | BI70: 1041.9 | BJ70: 1216.6 | BK70: 1351.5 | BL70: 1159.8 | BM70: 841.8 | BN70: 989.5 | BO70: 1300.9 | BP70: 1388.1
A72: Appendix Table 6.8.I.2: Measures of Aggregate Profits
A73: All Tables from NIPA , and all sums in Bills-$, unless indicated otherwise
A74: Description | B74: Source | C74: Variable | D74: 1947 | E74: 1948 | F74: 1949 | G74: 1950 | H74: 1951 | I74: 1952 | J74: 1953 | K74: 1954 | L74: 1955 | M74: 1956 | N74: 1957 | O74: 1958 | P74: 1959 | Q74: 1960 | R74: 1961 | S74: 1962 | T74: 1963 | U74: 1964 | V74: 1965 | W74: 1966 | X74: 1967 | Y74: 1968 | Z74: 1969 | AA74: 1970 | AB74: 1971 | AC74: 1972 | AD74: 1973 | AE74: 1974 | AF74: 1975 | AG74: 1976 | AH74: 1977 | AI74: 1978 | AJ74: 1979 | AK74: 1980 | AL74: 1981 | AM74: 1982 | AN74: 1983 | AO74: 1984 | AP74: 1985 | AQ74: 1986 | AR74: 1987 | AS74: 1988 | AT74: 1989 | AU74: 1990 | AV74: 1991 | AW74: 1992 | AX74: 1993 | AY74: 1994 | AZ74: 1995 | BA74: 1996 | BB74: 1997 | BC74: 1998 | BD74: 1999 | BE74: 2000 | BF74: 2001 | BG74: 2002 | BH74: 2003 | BI74: 2004 | BJ74: 2005 | BK74: 2006 | BL74: 2007 | BM74: 2008 | BN74: 2009 | BO74: 2010 | BP74: 2011
A75: Noncorporate Sector
A76: Proprietorships and Partnerships Income w/IVA and CCAdj | B76: T 1.13, line 23 | C76: PropInc | D76: 34.5 | E76: 39.2 | F76: 34.6 | G76: 37.5 | H76: 42.7 | I76: 43.1 | J76: 42 | K76: 42.3 | L76: 44.3 | M76: 45.9 | N76: 47.8 | O76: 50.2 | P76: 50.3 | Q76: 50.7 | R76: 53.2 | S76: 55.3 | T76: 56.5 | U76: 59.4 | V76: 63.9 | W76: 68.2 | X76: 69.8 | Y76: 74.2 | Z76: 77.5 | AA76: 78.5 | AB76: 84.7 | AC76: 96 | AD76: 113.6 | AE76: 113.5 | AF76: 119.6 | AG76: 132.2 | AH76: 146 | AI76: 167.5 | AJ76: 181.1 | AK76: 173.5 | AL76: 181.6 | AM76: 174.8 | AN76: 190.7 | AO76: 233.1 | AP76: 246.1 | AQ76: 262.6 | AR76: 294.2 | AS76: 334.8 | AT76: 351.6 | AU76: 365.1 | AV76: 367.3 | AW76: 414.9 | AX76: 449.6 | AY76: 485.1 | AZ76: 516 | BA76: 583.7 | BB76: 628.2 | BC76: 687.5 | BD76: 746.8 | BE76: 817.5 | BF76: 870.7 | BG76: 890.3 | BH76: 930.6 | BI76: 1033.8 | BJ76: 1069.8 | BK76: 1133 | BL76: 1090.4 | BM76: 1097.9 | BN76: 979.4 | BO76: 1103.4 | BP76: 1157.3
A77: Employee Compensation, Proprietorships and Partnerships | B77: ECbusnipa (Appendix Table 6.8.1) - ECcorpnipa (T 1.14, line 4) | C77: ECprop | D77: 22.992 | E77: 24.856 | F77: 24.267 | G77: 26.02 | H77: 29.114 | I77: 30.941 | J77: 32.34 | K77: 32.158 | L77: 33.452 | M77: 35.142 | N77: 36.247 | O77: 36.468 | P77: 38.331 | Q77: 38.267 | R77: 37.796 | S77: 38.736 | T77: 39.78 | U77: 41.895 | V77: 43.197 | W77: 45.806 | X77: 46.762 | Y77: 48.751 | Z77: 50.763 | AA77: 51.989 | AB77: 52.561 | AC77: 55.014 | AD77: 61.515 | AE77: 66.06 | AF77: 69.778 | AG77: 75.999 | AH77: 81.668 | AI77: 90.295 | AJ77: 100.814 | AK77: 108.614 | AL77: 115.895 | AM77: 121.584 | AN77: 127.846 | AO77: 140.584 | AP77: 151.17 | AQ77: 158.797 | AR77: 165.661 | AS77: 185.359 | AT77: 198.636 | AU77: 212.071 | AV77: 215.57 | AW77: 226.356 | AX77: 240.107 | AY77: 253.94 | AZ77: 268.471 | BA77: 284.764 | BB77: 303.441 | BC77: 330.203 | BD77: 360.517 | BE77: 390.647 | BF77: 462.097 | BG77: 493.077 | BH77: 533.181 | BI77: 588.565 | BJ77: 642.347 | BK77: 712.543 | BL77: 781.263 | BM77: 797.968 | BN77: 761.392 | BO77: 776.886 | BP77: 811.293
A78: No. of Proprietors and Partners (Self-Employed Persons) | B78: T 6.7, line 1 (Thousands-$) | C78: SEP | D78: 10199 | E78: 10211 | F78: 10064 | G78: 9996 | H78: 9699 | I78: 9637 | J78: 9475 | K78: 9329 | L78: 9149 | M78: 8981 | N78: 8821 | O78: 8611 | P78: 8428 | Q78: 8305 | R78: 8177 | S78: 8009 | T78: 7722 | U78: 7652 | V78: 7526 | W78: 7271 | X78: 7188 | Y78: 7115 | Z78: 7199 | AA78: 7097 | AB78: 7142 | AC78: 7234 | AD78: 7316 | AE78: 7527 | AF78: 7506 | AG78: 7495 | AH78: 7758 | AI78: 8118 | AJ78: 8416 | AK78: 8658 | AL78: 8753 | AM78: 8923 | AN78: 9213 | AO78: 9412 | AP78: 9327 | AQ78: 9369 | AR78: 9665 | AS78: 9956 | AT78: 10070 | AU78: 10132 | AV78: 10373 | AW78: 10040 | AX78: 10505 | AY78: 10564 | AZ78: 10514 | BA78: 10524 | BB78: 10544 | BC78: 10341 | BD78: 10121 | BE78: 10233 | BF78: 10133 | BG78: 9963 | BH78: 10297 | BI78: 10429 | BJ78: 10453 | BK78: 10589 | BL78: 10419 | BM78: 10063 | BN78: 9829 | BO78: 9681 | BP78: 9449
A79: Private Sector Employee Compensation per Full Time Equivalent Employee (FEE) | B79: T 6.2, line 3/Table 6.3, line 3 ($) | C79: ecprop | D79: 2734.8132 | E79: 2944.1591 | F79: 3011.067 | G79: 3195.1629 | H79: 3478.9613 | I79: 3688.9789 | J79: 3902.7911 | K79: 4010.5681 | L79: 4218.4043 | M79: 4460.3662 | N79: 4662.8694 | O79: 4823.4478 | P79: 5096.462 | Q79: 5271.4791 | R79: 5439.2275 | S79: 5684.8333 | T79: 5896.1587 | U79: 6190.9087 | V79: 6408.6177 | W79: 6742.1249 | X79: 7016.0738 | Y79: 7516.4294 | Z79: 8051.908 | AA79: 8575.5915 | AB79: 9144.0238 | AC79: 9770.2782 | AD79: 10446.789 | AE79: 11309.265 | AF79: 12302.351 | AG79: 13328.692 | AH79: 14353.173 | AI79: 15504.677 | AJ79: 16870.947 | AK79: 18551.566 | AL79: 20228.071 | AM79: 21865.393 | AN79: 22943.666 | AO79: 23992.96 | AP79: 25051.455 | AQ79: 26145.203 | AR79: 27187.431 | AS79: 28566.181 | AT79: 29462.798 | AU79: 30902.724 | AV79: 32313.301 | AW79: 34127.187 | AX79: 35033.353 | AY79: 35902.417 | AZ79: 36687.894 | BA79: 37681.549 | BB79: 39164.191 | BC79: 41314.997 | BD79: 43114.702 | BE79: 45772.437 | BF79: 47025.971 | BG79: 48345.155 | BH79: 50538.675 | BI79: 52347.316 | BJ79: 54139.365 | BK79: 56256.745 | BL79: 58413.32 | BM79: 60165.866 | BN79: 60920.857 | BO79: 62664.344 | BP79: 64560.325
A80: Estimated Wage Equivalent of Prop & Partner's Income using SEP times Average Private Sector EC per FTE | B80: ecpriv*SEP | C80: WEQ1 | D80: 27.89236 | E80: 30.062809 | F80: 30.303379 | G80: 31.938848 | H80: 33.742446 | I80: 35.55069 | J80: 36.978946 | K80: 37.41459 | L80: 38.594181 | M80: 40.058549 | N80: 41.131171 | O80: 41.534709 | P80: 42.952982 | Q80: 43.779634 | R80: 44.476564 | S80: 45.52983 | T80: 45.530138 | U80: 47.372833 | V80: 48.231257 | W80: 49.02199 | X80: 50.431538 | Y80: 53.479395 | Z80: 57.965685 | AA80: 60.860973 | AB80: 65.306618 | AC80: 70.678192 | AD80: 76.428711 | AE80: 85.124841 | AF80: 92.341445 | AG80: 99.898547 | AH80: 111.35191 | AI80: 125.86697 | AJ80: 141.98589 | AK80: 160.61946 | AL80: 177.05631 | AM80: 195.1049 | AN80: 211.37999 | AO80: 225.82174 | AP80: 233.65492 | AQ80: 244.95441 | AR80: 262.76652 | AS80: 284.4049 | AT80: 296.69037 | AU80: 313.1064 | AV80: 335.18587 | AW80: 342.63696 | AX80: 368.02537 | AY80: 379.27314 | AZ80: 385.73652 | BA80: 396.56063 | BB80: 412.94723 | BC80: 427.23839 | BD80: 436.3639 | BE80: 468.38934 | BF80: 476.51416 | BG80: 481.66278 | BH80: 520.39673 | BI80: 545.93016 | BJ80: 565.91878 | BK80: 595.70268 | BL80: 608.60838 | BM80: 605.44911 | BN80: 598.79111 | BO80: 606.65351 | BP80: 610.03051
A81: Noncorporate Profit Estimate 1 | B81: PropInc - WEQ1 | C81: Pnoncorp1 | D81: 6.6076402 | E81: 9.1371913 | F81: 4.2966214 | G81: 5.5611517 | H81: 8.957554 | I81: 7.5493103 | J81: 5.0210539 | K81: 4.88541 | L81: 5.7058193 | M81: 5.8414513 | N81: 6.6688293 | O81: 8.6652909 | P81: 7.347018 | Q81: 6.9203662 | R81: 8.7234363 | S81: 9.77017 | T81: 10.969862 | U81: 12.027167 | V81: 15.668743 | W81: 19.17801 | X81: 19.368462 | Y81: 20.720605 | Z81: 19.534315 | AA81: 17.639027 | AB81: 19.393382 | AC81: 25.321808 | AD81: 37.171289 | AE81: 28.375159 | AF81: 27.258555 | AG81: 32.301453 | AH81: 34.648086 | AI81: 41.633034 | AJ81: 39.114111 | AK81: 12.880544 | AL81: 4.5436911 | AM81: -20.304901 | AN81: -20.679995 | AO81: 7.2782568 | AP81: 12.445081 | AQ81: 17.645593 | AR81: 31.433483 | AS81: 50.395102 | AT81: 54.909628 | AU81: 51.993598 | AV81: 32.114131 | AW81: 72.263044 | AX81: 81.57463 | AY81: 105.82686 | AZ81: 130.26348 | BA81: 187.13937 | BB81: 215.25277 | BC81: 260.26161 | BD81: 310.4361 | BE81: 349.11066 | BF81: 394.18584 | BG81: 408.63722 | BH81: 410.20327 | BI81: 487.86984 | BJ81: 503.88122 | BK81: 537.29732 | BL81: 481.79162 | BM81: 492.45089 | BN81: 380.60889 | BO81: 496.74649 | BP81: 547.26949
A82: Corporate Wage-Profit Ratio | B82: T1.14, line 4 ÷ line 11 | C82: s | D82: 3.6488889 | E82: 3.0777027 | F82: 3.2173913 | G82: 2.869186 | H82: 2.9309463 | I82: 3.3243243 | J82: 3.5924933 | K82: 3.6318681 | L82: 3.1030043 | M82: 3.5 | N82: 3.741573 | O82: 4.1102757 | P82: 3.5283757 | Q82: 3.814 | R82: 3.8428291 | S82: 3.6006826 | T82: 3.4634526 | U82: 3.3642757 | V82: 3.1772616 | W82: 3.2784091 | X82: 3.6112412 | Y82: 3.7259825 | Z82: 4.3071672 | AA82: 5.3076923 | AB82: 4.8219955 | AC82: 4.6368989 | AD82: 4.8713504 | AE82: 6.0122825 | AF82: 5.1802864 | AG82: 4.7911785 | AH82: 4.5442965 | AI82: 4.6104294 | AJ82: 5.3592029 | AK82: 6.7475904 | AL82: 6.4049587 | AM82: 7.4742923 | AN82: 6.0814057 | AO82: 5.3684397 | AP82: 5.5108696 | AQ82: 6.2628322 | AR82: 5.753596 | AS82: 5.3582251 | AT82: 5.8267299 | AU82: 6.140067 | AV82: 5.9070378 | AW82: 5.6145119 | AX82: 5.3303342 | AY82: 4.7879339 | AZ82: 4.4544288 | BA82: 4.1671194 | BB82: 4.0189116 | BC82: 4.7862477 | BD82: 4.9382145 | BE82: 5.8650534 | BF82: 6.4868999 | BG82: 5.5728685 | BH82: 5.0560345 | BI82: 4.0943469 | BJ82: 3.6975999 | BK82: 3.5097299 | BL82: 4.2628902 | BM82: 5.9704205 | BN82: 4.7595755 | BO82: 3.695826 | BP82: 3.6436856
A83: Employee Compensation, Proprietorships and Partnerships | B83: Ecbusnipa -Eccorpnipa (NIPA Table 1.14, 4) | C83: ECprop | D83: =D61-D124 -> 22.992 | E83: =E61-E124 -> 24.856 | F83: =F61-F124 -> 24.267 | G83: =G61-G124 -> 26.02 | H83: =H61-H124 -> 29.114 | I83: =I61-I124 -> 30.941 | J83: =J61-J124 -> 32.34 | K83: =K61-K124 -> 32.158 | ... BP83: =BP61-BP124 -> 811.293
A84: Estimated Wage Equivalent of Prop & Partner's Income using Corp Wage/Profit ratio | B84: (σ∙PropInc - ECprop)/(1+σ) | C84: WEQ2 | D84: 22.133174 | E84: 23.491155 | F84: 20.641845 | G84: 21.08311 | H84: 24.431116 | I84: 25.978019 | J84: 25.812715 | K84: 26.224845 | L84: 25.349983 | M84: 27.890667 | N84: 30.074448 | O84: 33.240445 | P84: 30.72764 | Q84: 32.219111 | R84: 34.410157 | S84: 34.860424 | T84: 34.929254 | U84: 36.189963 | V84: 38.261912 | W84: 41.553179 | X84: 44.522207 | Y84: 48.184034 | Z84: 53.332116 | AA84: 57.81272 | AB84: 61.123719 | AC84: 69.209738 | AD84: 83.774664 | AE84: 87.893502 | AF84: 88.957731 | AG84: 96.248941 | AH84: 104.93654 | AI84: 121.55075 | AJ84: 136.76834 | AK84: 137.08687 | AL84: 141.42489 | AM84: 139.82552 | AN84: 145.71656 | AO84: 174.42252 | AP84: 185.08357 | AQ84: 204.57897 | AR84: 226.10872 | AS84: 252.99116 | AT84: 270.99977 | AU84: 284.26448 | AV84: 282.91216 | AW84: 317.95316 | AX84: 340.6473 | AY84: 357.41368 | AZ84: 372.17724 | BA84: 415.62492 | BB84: 442.5739 | BC84: 511.61693 | BD84: 560.32694 | BE84: 641.51492 | BF84: 692.68279 | BG84: 679.83223 | BH84: 688.89381 | BI84: 715.33621 | BJ84: 705.32728 | BK84: 723.76419 | BL84: 734.76594 | BM84: 825.91239 | BN84: 677.15689 | BO84: 702.98354 | BP84: 733.371
A85: Noncorporate Profit Estimate 2 | B85: PropInc - WEQ2 | C85: Pnoncorp | D85: 12.366826 | E85: 15.708845 | F85: 13.958155 | G85: 16.41689 | H85: 18.268884 | I85: 17.121981 | J85: 16.187285 | K85: 16.075155 | L85: 18.950017 | M85: 18.009333 | N85: 17.725552 | O85: 16.959555 | P85: 19.57236 | Q85: 18.480889 | R85: 18.789843 | S85: 20.439576 | T85: 21.570746 | U85: 23.210037 | V85: 25.638088 | W85: 26.646821 | X85: 25.277793 | Y85: 26.015966 | Z85: 24.167884 | AA85: 20.68728 | AB85: 23.576281 | AC85: 26.790262 | AD85: 29.825336 | AE85: 25.606498 | AF85: 30.642269 | AG85: 35.951059 | AH85: 41.063461 | AI85: 45.949245 | AJ85: 44.331656 | AK85: 36.413128 | AL85: 40.175106 | AM85: 34.974484 | AN85: 44.983442 | AO85: 58.677481 | AP85: 61.016427 | AQ85: 58.021029 | AR85: 68.091281 | AS85: 81.808837 | AT85: 80.60023 | AU85: 80.835516 | AV85: 84.38784 | AW85: 96.946835 | AX85: 108.9527 | AY85: 127.68632 | AZ85: 143.82276 | BA85: 168.07508 | BB85: 185.6261 | BC85: 175.88307 | BD85: 186.47306 | BE85: 175.98508 | BF85: 178.01721 | BG85: 210.46777 | BH85: 241.70619 | BI85: 318.46379 | BJ85: 364.47272 | BK85: 409.23581 | BL85: 355.63406 | BM85: 271.98761 | BN85: 302.24311 | BO85: 400.41646 | BP85: 423.929
A87: Corporate Sector
A88: NIPA Corporate GVA | B88: T 1.14, line 1 | C88: GVAcorpnipa | D88: 126 | E88: 144.5 | F88: 141.5 | G88: 160.4 | H88: 183.9 | I88: 192.6 | J88: 206.2 | K88: 203.6 | L88: 229.5 | M88: 245.6 | N88: 256.9 | O88: 251.8 | P88: 281.9 | Q88: 293.9 | R88: 302.1 | S88: 329 | T88: 349.5 | U88: 377.7 | V88: 414.4 | W88: 454.1 | X88: 479.3 | Y88: 529.1 | Z88: 576.7 | AA88: 597.8 | AB88: 646.1 | AC88: 716.7 | AD88: 802.6 | AE88: 869.9 | AF88: 944.4 | AG88: 1062.9 | AH88: 1205.1 | AI88: 1376.1 | AJ88: 1529 | AK88: 1663 | AL88: 1889 | AM88: 1967.3 | AN88: 2116.7 | AO88: 2371.3 | AP88: 2526.5 | AQ88: 2640.6 | AR88: 2832.6 | AS88: 3065.5 | AT88: 3229.5 | AU88: 3377 | AV88: 3467.4 | AW88: 3642.2 | AX88: 3823.2 | AY88: 4110.5 | AZ88: 4357.5 | BA88: 4625 | BB88: 4978.9 | BC88: 5299.3 | BD88: 5624.5 | BE88: 6016.4 | BF88: 6034.7 | BG88: 6122.7 | BH88: 6360.7 | BI88: 6774.2 | BJ88: 7297.9 | BK88: 7823.3 | BL88: 7965.6 | BM88: 7999 | BN88: 7659.9 | BO88: 8086.7 | BP88: 8493.4
A89: NIPA Corporate VA | B89: T 1.14, line 3 | C89: VAcorpnipa | D89: 117.1 | E89: 134.1 | F89: 130.3 | G89: 148.4 | H89: 170.3 | I89: 178.1 | J89: 190.8 | K89: 187.4 | L89: 212.4 | M89: 226.4 | N89: 235.6 | O89: 229.1 | P89: 258.2 | Q89: 269.9 | R89: 277.5 | S89: 303.5 | T89: 322.8 | U89: 349.5 | V89: 384 | W89: 420.7 | X89: 442.5 | Y89: 488.5 | Z89: 531.6 | AA89: 547.8 | AB89: 591.3 | AC89: 657 | AD89: 735.7 | AE89: 791.1 | AF89: 850 | AG89: 958.4 | AH89: 1087.1 | AI89: 1241.9 | AJ89: 1373.9 | AK89: 1483.2 | AL89: 1680.9 | AM89: 1735.9 | AN89: 1876.3 | AO89: 2118.4 | AP89: 2254.8 | AQ89: 2350.8 | AR89: 2526.1 | AS89: 2736.7 | AT89: 2878.7 | AU89: 3004 | AV89: 3075.3 | AW89: 3240.2 | AX89: 3403.1 | AY89: 3665.6 | AZ89: 3880.7 | BA89: 4119 | BB89: 4438 | BC89: 4721 | BD89: 4998.7 | BE89: 5331.3 | BF89: 5304.4 | BG89: 5366.8 | BH89: 5585.2 | BI89: 5965 | BJ89: 6435 | BK89: 6897.4 | BL89: 6992.2 | BM89: 6970.5 | BN89: 6629.5 | BO89: 7060.2 | BP89: 7431.5
A90: NIPA Corporate GOS | B90: T 1.14, line 2 + line 8 | C90: GOScorpnipa | D90: 32.3 | E90: 40.6 | F90: 39.3 | G90: 47 | H90: 53.5 | I90: 52.3 | J90: 53.7 | K90: 53.5 | L90: 65.1 | M90: 65.9 | N90: 67.7 | O90: 64.7 | P90: 76.1 | Q90: 75.3 | R90: 77.6 | S90: 86.8 | T90: 93.7 | U90: 102.9 | V90: 116.7 | W90: 126.7 | X90: 129.5 | Y90: 140 | Z90: 145.1 | AA90: 140.6 | AB90: 158 | AC90: 176.9 | AD90: 194.5 | AE90: 203.8 | AF90: 245.1 | AG90: 276.2 | AH90: 320.3 | AI90: 365.5 | AJ90: 392 | AK90: 414.3 | AL90: 494.5 | AM90: 512.2 | AN90: 572.1 | AO90: 661.8 | AP90: 695 | AQ90: 700.6 | AR90: 759.2 | AS90: 833.1 | AT90: 873.6 | AU90: 891.9 | AV90: 910.1 | AW90: 940.8 | AX90: 993 | AY90: 1103.4 | AZ90: 1202.4 | BA90: 1319.4 | BB90: 1448.2 | BC90: 1484 | BD90: 1554.4 | BE90: 1599.2 | BF90: 1586 | BG90: 1649.8 | BH90: 1737.9 | BI90: 1954.6 | BJ90: 2202.7 | BK90: 2446.2 | BL90: 2369.9 | BM90: 2312.2 | BN90: 2313.8 | BO90: 2619.8 | BP90: 2741.5
A91: NIPA Corporate NOS | B91: T 1.14, line 8 | C91: NOScorpnipa | D91: 23.4 | E91: 30.2 | F91: 28.1 | G91: 35 | H91: 39.9 | I91: 37.8 | J91: 38.3 | K91: 37.3 | L91: 48 | M91: 46.7 | N91: 46.4 | O91: 42 | P91: 52.4 | Q91: 51.3 | R91: 53 | S91: 61.3 | T91: 67 | U91: 74.7 | V91: 86.3 | W91: 93.3 | X91: 92.7 | Y91: 99.4 | Z91: 100 | AA91: 90.6 | AB91: 103.2 | AC91: 117.2 | AD91: 127.6 | AE91: 125 | AF91: 150.7 | AG91: 171.7 | AH91: 202.3 | AI91: 231.3 | AJ91: 236.9 | AK91: 234.5 | AL91: 286.4 | AM91: 280.8 | AN91: 331.7 | AO91: 408.9 | AP91: 423.3 | AQ91: 410.8 | AR91: 452.7 | AS91: 504.3 | AT91: 522.8 | AU91: 518.9 | AV91: 518 | AW91: 538.8 | AX91: 572.9 | AY91: 658.5 | AZ91: 725.6 | BA91: 813.4 | BB91: 907.3 | BC91: 905.7 | BD91: 928.6 | BE91: 914.1 | BF91: 855.7 | BG91: 893.9 | BH91: 962.4 | BI91: 1145.4 | BJ91: 1339.8 | BK91: 1520.3 | BL91: 1396.5 | BM91: 1283.7 | BN91: 1283.4 | BO91: 1593.3 | BP91: 1679.6
A92: Corp Net interest | C92: Corpnetintnipa | D92: 0.3 | E92: 0 | F92: 0 | G92: -0.1 | H92: -0.2 | I92: -0.2 | J92: 0 | K92: 0.2 | L92: 0.2 | M92: 0 | N92: 0.2 | O92: 0.6 | P92: -0.2 | Q92: -0.2 | R92: 0.4 | S92: 0.7 | T92: 0.4 | U92: 0.8 | V92: 1.2 | W92: 2.3 | X92: 4 | Y92: 3.9 | Z92: 7.8 | AA92: 11.3 | AB92: 11.5 | AC92: 11.3 | AD92: 13 | AE92: 20.7 | AF92: 23.4 | AG92: 18.8 | AH92: 23.3 | AI92: 27.5 | AJ92: 34.9 | AK92: 55.9 | AL92: 77.7 | AM92: 90 | AN92: 86.6 | AO92: 98.8 | AP92: 96.9 | AQ92: 106.3 | AR92: 107.6 | AS92: 107.8 | AT92: 130 | AU92: 125.8 | AV92: 102.6 | AW92: 80.6 | AX92: 73.5 | AY92: 75 | AZ92: 64.7 | BA92: 69.3 | BB92: 94.8 | BC92: 142.2 | BD92: 139 | BE92: 166.6 | BF92: 154.2 | BG92: 116.2 | BH92: 99.4 | BI92: 48.6 | BJ92: 61.6 | BK92: 120.4 | BL92: 164.2 | BM92: 338.7 | BN92: 189.8 | BO92: 182.6 | BP92: 183.4
A93: Business net transfer payments | C93: Corptrnsfrsnipa | D93: 0.6 | E93: 0.6 | F93: 0.6 | G93: 0.7 | H93: 1.1 | I93: 1.1 | J93: 1 | K93: 0.8 | L93: 1.2 | M93: 1.5 | N93: 1.7 | O93: 1.5 | P93: 1.5 | Q93: 1.6 | R93: 1.8 | S93: 2 | T93: 2.4 | U93: 2.9 | V93: 3.3 | W93: 3 | X93: 3.3 | Y93: 3.8 | Z93: 4.4 | AA93: 3.9 | AB93: 3.5 | AC93: 4 | AD93: 5 | AE93: 6.6 | AF93: 8.6 | AG93: 7.9 | AH93: 6.3 | AI93: 8.2 | AJ93: 11.3 | AK93: 12.6 | AL93: 15.1 | AM93: 17.7 | AN93: 20.3 | AO93: 28 | AP93: 31.9 | AQ93: 29.9 | AR93: 25.3 | AS93: 26.9 | AT93: 34.4 | AU93: 34.8 | AV93: 34.6 | AW93: 35.1 | AX93: 32.7 | AY93: 33.2 | AZ93: 37.7 | BA93: 44.6 | BB93: 35.2 | BC93: 53.8 | BD93: 54.9 | BE93: 73.8 | BF93: 87 | BG93: 63.5 | BH93: 50.9 | BI93: 54.9 | BJ93: 61.6 | BK93: 48.4 | BL93: 72.6 | BM93: 103.2 | BN93: 104 | BO93: 109.8 | BP93: 108.1
A94: NIPA Corp Profits w/IVA & CCAdj | B94: T 1.14, line 11 | C94: Pcorpnipa | D94: 22.5 | E94: 29.6 | F94: 27.6 | G94: 34.4 | H94: 39.1 | I94: 37 | J94: 37.3 | K94: 36.4 | L94: 46.6 | M94: 45.2 | N94: 44.5 | O94: 39.9 | P94: 51.1 | Q94: 50 | R94: 50.9 | S94: 58.6 | T94: 64.3 | U94: 71.1 | V94: 81.8 | W94: 88 | X94: 85.4 | Y94: 91.6 | Z94: 87.9 | AA94: 75.4 | AB94: 88.2 | AC94: 101.9 | AD94: 109.6 | AE94: 97.7 | AF94: 118.7 | AG94: 145.1 | AH94: 172.7 | AI94: 195.6 | AJ94: 190.7 | AK94: 166 | AL94: 193.6 | AM94: 173.1 | AN94: 224.8 | AO94: 282 | AP94: 294.4 | AQ94: 274.7 | AR94: 319.8 | AS94: 369.6 | AT94: 358.4 | AU94: 358.4 | AV94: 380.8 | AW94: 423.1 | AX94: 466.8 | AY94: 550.3 | AZ94: 623.2 | BA94: 699.5 | BB94: 777.3 | BC94: 709.7 | BD94: 734.8 | BE94: 673.6 | BF94: 614.5 | BG94: 714.3 | BH94: 812 | BI94: 1041.9 | BJ94: 1216.6 | BK94: 1351.5 | BL94: 1159.8 | BM94: 841.8 | BN94: 989.5 | BO94: 1300.9 | BP94: 1388.1
A96: Appendix Table 6.8.I.3: Business Accounts Corrected for WEQ2 and Imputed Interest Adjustments
A97: GVAbusnipa and its components are from Appendix 6.8A.1; Corporate GVA and components are from Appendix Table 6.8A.2
A98: Description | B98: Source | C98: Variable | D98: 1947 | E98: 1948 | F98: 1949 | G98: 1950 | H98: 1951 | I98: 1952 | J98: 1953 | K98: 1954 | L98: 1955 | M98: 1956 | N98: 1957 | O98: 1958 | P98: 1959 | Q98: 1960 | R98: 1961 | S98: 1962 | T98: 1963 | U98: 1964 | V98: 1965 | W98: 1966 | X98: 1967 | Y98: 1968 | Z98: 1969 | AA98: 1970 | AB98: 1971 | AC98: 1972 | AD98: 1973 | AE98: 1974 | AF98: 1975 | AG98: 1976 | AH98: 1977 | AI98: 1978 | AJ98: 1979 | AK98: 1980 | AL98: 1981 | AM98: 1982 | AN98: 1983 | AO98: 1984 | AP98: 1985 | AQ98: 1986 | AR98: 1987 | AS98: 1988 | AT98: 1989 | AU98: 1990 | AV98: 1991 | AW98: 1992 | AX98: 1993 | AY98: 1994 | AZ98: 1995 | BA98: 1996 | BB98: 1997 | BC98: 1998 | BD98: 1999 | BE98: 2000 | BF98: 2001 | BG98: 2002 | BH98: 2003 | BI98: 2004 | BJ98: 2005 | BK98: 2006 | BL98: 2007 | BM98: 2008 | BN98: 2009 | BO98: 2010 | BP98: 2011
A99: Bank (Fin Corp) Monetary Int Paid | B99: T 7.11, line 4 | C99: BankMonIntPaid | D99: -0.6 | E99: -0.9 | F99: -1.1 | G99: -1 | H99: -1.3 | I99: -1.4 | J99: -1.2 | K99: -1.4 | L99: -1.6 | M99: -1.6 | N99: -1.9 | O99: -2.2 | P99: -3 | Q99: -3.4 | R99: -3.3 | S99: -3.6 | T99: -4.3 | U99: -4.3 | V99: -4.7 | W99: -4.8 | X99: -4.4 | Y99: -5.8 | Z99: -5 | AA99: -5.4 | AB99: -6.1 | AC99: -7.3 | AD99: -8.7 | AE99: -6.8 | AF99: -5 | AG99: -7.2 | AH99: -5.1 | AI99: -5.8 | AJ99: -7 | AK99: 1.8 | AL99: 10.5 | AM99: 12.5 | AN99: 9.7 | AO99: 12.8 | AP99: 5.3 | AQ99: 7.9 | AR99: 11.9 | AS99: -0.2 | AT99: -3.8 | AU99: -17.3 | AV99: -37 | AW99: -33.7 | AX99: -26.4 | AY99: -23.8 | AZ99: -48.1 | BA99: -42.8 | BB99: -29.9 | BC99: -4.6 | BD99: -25.6 | BE99: -26.2 | BF99: -43.4 | BG99: -47.6 | BH99: -48.4 | BI99: -85.9 | BJ99: -86.6 | BK99: -43.7 | BL99: -68.2 | BM99: 81 | BN99: -37.6 | BO99: -39.2 | BP99: -72.4
A100: NonFin Bus Net Imputed Int Paid | B100: T 7.11, lines (74+75) – lines (53+54) | C100: NFNetImpIntPaid | D100: -1.3 | E100: -1.4 | F100: -1.4 | G100: -1.6 | H100: -1.7 | I100: -1.9 | J100: -2.1 | K100: -2.1 | L100: -2.2 | M100: -2.6 | N100: -2.9 | O100: -2.9 | P100: -3.1 | Q100: -3.5 | R100: -3.6 | S100: -3.8 | T100: -3.9 | U100: -4.1 | V100: -4.4 | W100: -5.1 | X100: -5.6 | Y100: -6.5 | Z100: -7.7 | AA100: -8.5 | AB100: -8.7 | AC100: -9.5 | AD100: -11.3 | AE100: -13.7 | AF100: -13.7 | AG100: -15.3 | AH100: -17.1 | AI100: -21.2 | AJ100: -26.2 | AK100: -31.7 | AL100: -37.7 | AM100: -40.7 | AN100: -34.5 | AO100: -39.9 | AP100: -38.5 | AQ100: -40.8 | AR100: -49.9 | AS100: -56.2 | AT100: -61 | AU100: -56.3 | AV100: -49.2 | AW100: -48.7 | AX100: -55.4 | AY100: -62 | AZ100: -66.2 | BA100: -66.4 | BB100: -70.8 | BC100: -74.7 | BD100: -79.4 | BE100: -91.8 | BF100: -94 | BG100: -96.7 | BH100: -103.1 | BI100: -107.2 | BJ100: -118.7 | BK100: -129.8 | BL100: -127.4 | BM100: -126.1 | BN100: -136.1 | BO100: -148.6 | BP100: -153.2
A101: Imputed Bus Int Adjustment | B101: -BankMonIntPaid - NFNetImpIntPaid | C101: BusImpIntAdj | D101: =-D99-D100 -> 1.9 | E101: =-E99-E100 -> 2.3 | F101: =-F99-F100 -> 2.5 | G101: =-G99-G100 -> 2.6 | H101: =-H99-H100 -> 3 | I101: =-I99-I100 -> 3.3 | J101: =-J99-J100 -> 3.3 | K101: =-K99-K100 -> 3.5 | ... BP101: =-BP99-BP100 -> 225.6
A102: Business Sector
A103: GVA Business Sector | B103: GVAbusnipa + BusImpAdj | C103: GVAbus | D103: =D59+D101 -> 202.635 | E103: =E59+E101 -> 226.833 | F103: =F59+F101 -> 222.388 | G103: =G59+G101 -> 246.76 | H103: =H59+H101 -> 283.055 | I103: =I59+I101 -> 295.068 | J103: =J59+J101 -> 311.649 | K103: =K59+K101 -> 309.402 | ... BP103: =BP59+BP101 -> 11393.232
A104: SDbus | B104: SDbusnipa | C104: SDbus | D104: 2.3 | E104: -0.5 | F104: 1.8 | G104: 1.4 | H104: 3.6 | I104: 2.7 | J104: 4 | K104: 3.1 | L104: 2.4 | M104: -1.8 | N104: -0.1 | O104: 1 | P104: 0.5 | Q104: -1 | R104: -0.6 | S104: 0.3 | T104: -0.8 | U104: 0.8 | V104: 1.5 | W104: 6.2 | X104: 4.5 | Y104: 4.3 | Z104: 2.9 | AA104: 6.9 | AB104: 11 | AC104: 8.9 | AD104: 8 | AE104: 9.8 | AF104: 16.3 | AG104: 23.5 | AH104: 21.2 | AI104: 26.1 | AJ104: 47 | AK104: 45.3 | AL104: 36.6 | AM104: 4.8 | AN104: 49.7 | AO104: 31.5 | AP104: 42.3 | AQ104: 67.7 | AR104: 32.9 | AS104: -9.5 | AT104: 56.1 | AU104: 84.2 | AV104: 79.7 | AW104: 110 | AX104: 135.8 | AY104: 108.8 | AZ104: 52.5 | BA104: 25.9 | BB104: -14 | BC104: -85.3 | BD104: -71.1 | BE104: -134 | BF104: -103.4 | BG104: -22.1 | BH104: 16.6 | BI104: -22.3 | BJ104: -95.1 | BK104: -242.3 | BL104: -12 | BM104: -2.4 | BN104: 118.3 | BO104: 23.3 | BP104: 31.9
A105: ECbus (EC including WEQ2) | B105: ECbusnipa + WEQ2 | C105: ECbus | D105: =D61+D84 -> 127.22517 | E105: =E61+E84 -> 139.44715 | F105: =F61+F84 -> 133.70885 | G105: =G61+G84 -> 145.80311 | H105: =H61+H84 -> 168.14512 | I105: =I61+I84 -> 179.91902 | J105: =J61+J84 -> 192.15271 | K105: =K61+K84 -> 190.58284 | ... BP105: =BP61+BP84 -> 6602.464
A106: Tbus | B106: Tbusnipa | C106: Tbus | D106: 16.5 | E106: 17.9 | F106: 18.9 | G106: 20.5 | H106: 21.9 | I106: 24.3 | J106: 26.3 | K106: 26.1 | L106: 28.4 | M106: 30 | N106: 31.7 | O106: 32 | P106: 34.9 | Q106: 37.8 | R106: 38.8 | S106: 41.3 | T106: 43.8 | U106: 46.5 | V106: 48.9 | W106: 49.8 | X106: 53.4 | Y106: 60.2 | Z106: 66 | AA106: 71.4 | AB106: 79.1 | AC106: 83.2 | AD106: 92.5 | AE106: 100.7 | AF106: 107.9 | AG106: 116 | AH106: 124.8 | AI106: 133.6 | AJ106: 142.3 | AK106: 158.7 | AL106: 188.9 | AM106: 187.5 | AN106: 201 | AO106: 224.5 | AP106: 239.7 | AQ106: 248.6 | AR106: 262.5 | AS106: 286.8 | AT106: 308.5 | AU106: 331.1 | AV106: 357.8 | AW106: 379.1 | AX106: 392.2 | AY106: 435 | AZ106: 445.1 | BA106: 465.1 | BB106: 494.3 | BC106: 517.9 | BD106: 540.3 | BE106: 571.7 | BF106: 572.9 | BG106: 617.4 | BH106: 647.7 | BI106: 700.5 | BJ106: 748 | BK106: 804.4 | BL106: 838.7 | BM106: 843.7 | BN106: 812.4 | BO106: 845.6 | BP106: 881
A107: GOSbus | B107: GOSbusnipa - WEQ2 + BusImpIntAdj | C107: GOSbus | D107: =D63-D84+D101 -> 56.609826 | E107: =E63-E84+E101 -> 69.985845 | F107: =F63-F84+F101 -> 67.979155 | G107: =G63-G84+G101 -> 79.05689 | H107: =H63-H84+H101 -> 89.409884 | I107: =I63-I84+I101 -> 88.148981 | J107: =J63-J84+J101 -> 89.196285 | K107: =K63-K84+K101 -> 89.619155 | ... BP107: =BP63-BP84+BP101 -> 3877.868
A108: CFCbus | B108: CFCbusnipa | C108: CFCbus | D108: 13.6 | E108: 16.1 | F108: 17.5 | G108: 18.6 | H108: 21.3 | I108: 22.7 | J108: 23.7 | K108: 24.8 | L108: 25.9 | M108: 28.8 | N108: 31.3 | O108: 33.2 | P108: 34.6 | Q108: 34.8 | R108: 35.6 | S108: 36.9 | T108: 38.3 | U108: 40.3 | V108: 43.2 | W108: 47.3 | X108: 51.5 | Y108: 56.5 | Z108: 62.3 | AA108: 68.6 | AB108: 75.1 | AC108: 81.8 | AD108: 91.3 | AE108: 106.7 | AF108: 126.5 | AG108: 139.3 | AH108: 156.4 | AI108: 177.4 | AJ108: 204.6 | AK108: 236.7 | AL108: 272.6 | AM108: 302.1 | AN108: 312.9 | AO108: 327.5 | AP108: 349.7 | AQ108: 371.7 | AR108: 392.3 | AS108: 419.6 | AT108: 446.6 | AU108: 471.9 | AV108: 492.8 | AW108: 503.1 | AX108: 523.4 | AY108: 551.6 | AZ108: 588.3 | BA108: 621.5 | BB108: 660.9 | BC108: 704.4 | BD108: 759.5 | BE108: 827 | BF108: 879.3 | BG108: 911.3 | BH108: 938.5 | BI108: 982 | BJ108: 1049.3 | BK108: 1127.2 | BL108: 1194.7 | BM108: 1252.4 | BN108: 1254.1 | BO108: 1249 | BP108: 1289.7
...

Sheet Appndx 6.8.II.1
A18: Description | B18: Source | C18: Variable | D18: 1925 | E18: 1926 | F18: 1927 | G18: 1928 | H18: 1929 | I18: 1930 | J18: 1931 | K18: 1932 | L18: 1933 | M18: 1934 | N18: 1935 | O18: 1936 | P18: 1937 | Q18: 1938 | R18: 1939 | S18: 1940 | T18: 1941 | U18: 1942 | V18: 1943 | W18: 1944 | X18: 1945 | Y18: 1946 | Z18: 1947 | AA18: 1948 | AB18: 1949 | AC18: 1950 | AD18: 1951 | AE18: 1952 | AF18: 1953 | AG18: 1954 | AH18: 1955 | AI18: 1956 | AJ18: 1957 | AK18: 1958 | AL18: 1959 | AM18: 1960 | AN18: 1961 | AO18: 1962 | AP18: 1963 | AQ18: 1964 | AR18: 1965 | AS18: 1966 | AT18: 1967 | AU18: 1968 | AV18: 1969 | AW18: 1970 | AX18: 1971 | AY18: 1972 | AZ18: 1973 | BA18: 1974 | BB18: 1975 | BC18: 1976 | BD18: 1977 | BE18: 1978 | BF18: 1979 | BG18: 1980 | BH18: 1981 | BI18: 1982 | BJ18: 1983 | BK18: 1984 | BL18: 1985 | BM18: 1986 | BN18: 1987 | BO18: 1988 | BP18: 1989 | BQ18: 1990 | BR18: 1991 | BS18: 1992 | BT18: 1993 | BU18: 1994 | BV18: 1995 | BW18: 1996 | BX18: 1997 | BY18: 1998 | BZ18: 1999 | CA18: 2000 | CB18: 2001 | CC18: 2002 | CD18: 2003 | CE18: 2004 | CF18: 2005 | CG18: 2006 | CH18: 2007 | CI18: 2008 | CJ18: 2009 | CK18: 2010 | CL18: 2011 | CM18: 2012 | CN18: 2013
A19: BEA Current-Cost Corporate Net Stock | B19: FA Table 6.1, line 2: Bill-$ | C19: KNCcorpbea | D19: 98.1 | E19: 101 | F19: 102.4 | G19: 104.7 | H19: 103.6 | I19: 98.5 | J19: 88.4 | K19: 82.4 | L19: 83.2 | M19: 84.2 | N19: 83.7 | O19: 92 | P19: 95.2 | Q19: 93.9 | R19: 94.4 | S19: 100.1 | T19: 112.1 | U19: 118.9 | V19: 119.3 | W19: 120.2 | X19: 131.2 | Y19: 159.4 | Z19: 190.1 | AA19: 208.1 | AB19: 212.2 | AC19: 238.1 | AD19: 258.5 | AE19: 273.5 | AF19: 287 | AG19: 295.3 | AH19: 325 | AI19: 360.7 | AJ19: 386.9 | AK19: 394.4 | AL19: 411.6 | AM19: 419.9 | AN19: 430.3 | AO19: 444.2 | AP19: 458.3 | AQ19: 483.9 | AR19: 517.4 | AS19: 563.4 | AT19: 610.8 | AU19: 672.6 | AV19: 741.1 | AW19: 815.7 | AX19: 895.2 | AY19: 972.2 | AZ19: 1097.4 | BA19: 1346.4 | BB19: 1495.4 | BC19: 1643.8 | BD19: 1829.9 | BE19: 2081.5 | BF19: 2399.7 | BG19: 2761.2 | BH19: 3125.3 | BI19: 3318.6 | BJ19: 3415.3 | BK19: 3618.4 | BL19: 3819.3 | BM19: 3989.7 | BN19: 4197.6 | BO19: 4462.9 | BP19: 4728.2 | BQ19: 4993.1 | BR19: 5105.1 | BS19: 5275.6 | BT19: 5523.9 | BU19: 5823.9 | BV19: 6154.2 | BW19: 6469.9 | BX19: 6830.5 | BY19: 7217.6 | BZ19: 7641.6 | CA19: 8175.4 | CB19: 8595.6 | CC19: 8907.7 | CD19: 9185.8 | CE19: 9909.5 | CF19: 10768.3 | CG19: 11679.9 | CH19: 12317.8 | CI19: 13138 | CJ19: 12701.7 | CK19: 12994.6 | CL19: 13530.8
A20: BEA Chain-Index Real Corporate Net Stock | B20: FA Table 6.2, line 2: 2005 = 100 | C20: KNRIndxcorpbea | D20: 13.038 | E20: 13.38 | F20: 13.649 | G20: 13.929 | H20: 14.298 | I20: 14.519 | J20: 14.442 | K20: 14.169 | L20: 13.891 | M20: 13.703 | N20: 13.579 | O20: 13.607 | P20: 13.752 | Q20: 13.695 | R20: 13.694 | S20: 13.827 | T20: 14.044 | U20: 13.978 | V20: 13.817 | W20: 13.797 | X20: 14.013 | Y20: 14.532 | Z20: 15.105 | AA20: 15.675 | AB20: 16.051 | AC20: 16.481 | AD20: 17.015 | AE20: 17.551 | AF20: 18.15 | AG20: 18.649 | AH20: 19.238 | AI20: 19.98 | AJ20: 20.719 | AK20: 21.123 | AL20: 21.598 | AM20: 22.218 | AN20: 22.777 | AO20: 23.452 | AP20: 24.158 | AQ20: 25.076 | AR20: 26.327 | AS20: 27.856 | AT20: 29.223 | AU20: 30.643 | AV20: 32.161 | AW20: 33.48 | AX20: 34.66 | AY20: 36.02 | AZ20: 37.719 | BA20: 39.393 | BB20: 40.499 | BC20: 41.65 | BD20: 43.089 | BE20: 44.985 | BF20: 47.115 | BG20: 49.079 | BH20: 51.06 | BI20: 52.574 | BJ20: 53.889 | BK20: 55.932 | BL20: 58.089 | BM20: 59.785 | BN20: 61.217 | BO20: 62.708 | BP20: 64.332 | BQ20: 66.06 | BR20: 67.245 | BS20: 68.413 | BT20: 69.996 | BU20: 71.864 | BV20: 74.257 | BW20: 77.004 | BX20: 80.052 | BY20: 83.471 | BZ20: 87.15 | CA20: 91.139 | CB20: 93.913 | CC20: 95.374 | CD20: 96.682 | CE20: 98.214 | CF20: 100 | CG20: 102.48 | CH20: 105.241 | CI20: 107.527 | CJ20: 107.696 | CK20: 108.012 | CL20: 108.992
A21: BEA Constant-Cost Corporate Net Stock | B21: KNRIndex(t)*KNC(2005)/100: Bills-2005$ | C21: KNRcorpbea | D21: =D20*$CF$19/100 -> 1403.971 | E21: =E20*$CF$19/100 -> 1440.7985 | F21: =F20*$CF$19/100 -> 1469.7653 | G21: =G20*$CF$19/100 -> 1499.9165 | H21: =H20*$CF$19/100 -> 1539.6515 | I21: =I20*$CF$19/100 -> 1563.4495 | J21: =J20*$CF$19/100 -> 1555.1579 | K21: =K20*$CF$19/100 -> 1525.7604 | ... CL21: =CL20*$CF$19/100 -> 11736.586
A22: Implicit Price Deflator, Net Corporate Capital Stock | B22: (KNCcorp/KNRcorp)*100 | C22: pKN | D22: =(D19/D21)*100 -> 6.987324 | E22: =(E19/E21)*100 -> 7.0100016 | F22: =(F19/F21)*100 -> 6.9670989 | G22: =(G19/G21)*100 -> 6.9803885 | H22: =(H19/H21)*100 -> 6.7287953 | I22: =(I19/I21)*100 -> 6.3001716 | J22: =(J19/J21)*100 -> 5.6843103 | K22: =(K19/K21)*100 -> 5.4005857 | ... CL22: =(CL19/CL21)*100 -> 115.28736
A23: BEA Historical-Cost Corporate Net Stock | B23: FA Table 6.3, line 2: Bill-$ | C23: KNHcorpbea | D23: 69.2 | E23: 72.3 | F23: 74.9 | G23: 77.5 | H23: 80.9 | I23: 82.7 | J23: 82.3 | K23: 80.4 | L23: 78.6 | M23: 77.4 | N23: 76.7 | O23: 77 | P23: 78.5 | Q23: 78.6 | R23: 79 | S23: 80.5 | T23: 83 | U23: 83.7 | V23: 83.8 | W23: 85.1 | X23: 88.5 | Y23: 95.3 | Z23: 105 | AA23: 115.9 | AB23: 124.4 | AC23: 133.7 | AD23: 146 | AE23: 158.6 | AF23: 172.3 | AG23: 184.4 | AH23: 197.9 | AI23: 216 | AJ23: 235.4 | AK23: 248.7 | AL23: 263.6 | AM23: 280.9 | AN23: 296.5 | AO23: 313.9 | AP23: 331.7 | AQ23: 353.5 | AR23: 382.1 | AS23: 417.3 | AT23: 450.7 | AU23: 487.4 | AV23: 529 | AW23: 569.4 | AX23: 609.7 | AY23: 657.3 | AZ23: 718.2 | BA23: 790.1 | BB23: 858.5 | BC23: 934.6 | BD23: 1030.7 | BE23: 1156.7 | BF23: 1310.3 | BG23: 1474.4 | BH23: 1662.3 | BI23: 1834.5 | BJ23: 1987.1 | BK23: 2181.8 | BL23: 2383.8 | BM23: 2556.7 | BN23: 2712.7 | BO23: 2881.4 | BP23: 3067.8 | BQ23: 3267.3 | BR23: 3430.2 | BS23: 3587.9 | BT23: 3777.9 | BU23: 3995.7 | BV23: 4261.1 | BW23: 4553.3 | BX23: 4871 | BY23: 5215.3 | BZ23: 5585.3 | CA23: 5995.7 | CB23: 6306.5 | CC23: 6499.8 | CD23: 6684.5 | CE23: 6906.9 | CF23: 7201.1 | CG23: 7605.3 | CH23: 8068.8 | CI23: 8508.3 | CJ23: 8673.5 | CK23: 8848.6 | CL23: 9122.4
A25: Current-Cost Corporate Depreciation | B25: FA Table 6.4, line 2: Bill-$ | C25: DEPCcorp | D25: 4.5 | E25: 4.7 | F25: 4.8 | G25: 4.9 | H25: 5 | I25: 4.8 | J25: 4.5 | K25: 4 | L25: 3.8 | M25: 3.9 | N25: 3.9 | O25: 4 | P25: 4.4 | Q25: 4.5 | R25: 4.5 | S25: 4.6 | T25: 5.1 | U25: 5.8 | V25: 5.8 | W25: 6 | X25: 6.1 | Y25: 6.9 | Z25: 8.9 | AA25: 10.4 | AB25: 11.2 | AC25: 12 | AD25: 13.6 | AE25: 14.5 | AF25: 15.4 | AG25: 16.2 | AH25: 17.1 | AI25: 19.2 | AJ25: 21.3 | AK25: 22.7 | AL25: 23.7 | AM25: 24 | AN25: 24.7 | AO25: 25.6 | AP25: 26.7 | AQ25: 28.2 | AR25: 30.5 | AS25: 33.5 | AT25: 36.9 | AU25: 40.7 | AV25: 45.2 | AW25: 50.1 | AX25: 54.9 | AY25: 59.8 | AZ25: 67 | BA25: 78.9 | BB25: 94.5 | BC25: 104.7 | BD25: 118.1 | BE25: 134.4 | BF25: 155.3 | BG25: 180 | BH25: 208.3 | BI25: 231.6 | BJ25: 240.7 | BK25: 253.2 | BL25: 272 | BM25: 290.1 | BN25: 306.7 | BO25: 329.1 | BP25: 351.1 | BQ25: 373.4 | BR25: 392.4 | BS25: 402.3 | BT25: 420.4 | BU25: 445.2 | BV25: 477.2 | BW25: 506.3 | BX25: 541.2 | BY25: 578.6 | BZ25: 624.9 | CA25: 682.1 | CB25: 725.1 | CC25: 749.3 | CD25: 768.3 | CE25: 803.1 | CF25: 855.8 | CG25: 918.4 | CH25: 976.4 | CI25: 1028.5 | CJ25: 1030.4 | CK25: 1026.5 | CL25: 1061.9
A26: Correct Depreciation Rate | B26: DEPcorp/[(pKN/100)*KNR(-1)] | C26: dcorpstar | E26: =(E25/(E22*D21/100)) -> 0.047755305 | F26: =(F25/(F22*E21/100)) -> 0.047817405 | G26: =(G25/(G22*F21/100)) -> 0.04776046 | H26: =(H25/(H22*G21/100)) -> 0.049541095 | I26: =(I25/(I22*H21/100)) -> 0.049484185 | J26: =(J25/(J22*I21/100)) -> 0.050635008 | K26: =(K25/(K22*J21/100)) -> 0.047626058 | L26: =(L25/(L22*K21/100)) -> 0.044776958 | ... CL26: =(CL25/(CL22*CK21/100)) -> 0.079192264
A27: Historical-Cost Corporate Depreciation | B27: FA Table 6.6, line 2: Bill-$ | C27: DEPHcorpbea | D27: 4 | E27: 4.2 | F27: 4.3 | G27: 4.3 | H27: 4.4 | I27: 4.5 | J27: 4.4 | K27: 4.2 | L27: 4 | M27: 3.9 | N27: 3.8 | O27: 3.8 | P27: 4 | Q27: 4 | R27: 4 | S27: 4.1 | T27: 4.3 | U27: 4.4 | V27: 4.4 | W27: 4.5 | X27: 4.7 | Y27: 5.2 | Z27: 6 | AA27: 6.9 | AB27: 7.7 | AC27: 8.5 | AD27: 9.3 | AE27: 10.1 | AF27: 11.1 | AG27: 12.1 | AH27: 13 | AI27: 14.2 | AJ27: 15.5 | AK27: 17 | AL27: 17.8 | AM27: 18.5 | AN27: 19.6 | AO27: 20.8 | AP27: 22.2 | AQ27: 23.8 | AR27: 26 | AS27: 28.7 | AT27: 31.5 | AU27: 34.4 | AV27: 37.7 | AW27: 41.1 | AX27: 44.3 | AY27: 48.3 | AZ27: 53.8 | BA27: 59.7 | BB27: 65.7 | BC27: 72.4 | BD27: 81.2 | BE27: 92.3 | BF27: 105.8 | BG27: 120.5 | BH27: 136.6 | BI27: 154.8 | BJ27: 171 | BK27: 188.9 | BL27: 210.6 | BM27: 229.4 | BN27: 247.3 | BO27: 264.5 | BP27: 283.3 | BQ27: 302.6 | BR27: 319.5 | BS27: 334.8 | BT27: 354.2 | BU27: 379.1 | BV27: 408.8 | BW27: 443 | BX27: 482.4 | BY27: 526.7 | BZ27: 575.3 | CA27: 627.4 | CB27: 668.7 | CC27: 691.8 | CD27: 707.1 | CE27: 727.9 | CF27: 754.4 | CG27: 788.7 | CH27: 831.9 | CI27: 868.3 | CJ27: 884.7 | CK27: 888.7 | CL27: 908.6
A28: Current-Cost Gross Investment | B28: FA Table 6.7, line 2: Bill-$ | C28: IGCcorpbea | D28: 7.3 | E28: 7.3 | F28: 6.9 | G28: 7 | H28: 7.7 | I28: 6.4 | J28: 4 | K28: 2.4 | L28: 2.2 | M28: 2.7 | N28: 3.2 | O28: 4.1 | P28: 5.4 | Q28: 4.1 | R28: 4.4 | S28: 5.6 | T28: 6.8 | U28: 5.2 | V28: 4.5 | W28: 5.8 | X28: 8.1 | Y28: 12 | Z28: 15.7 | AA28: 17.8 | AB28: 16.2 | AC28: 17.8 | AD28: 21.7 | AE28: 22.7 | AF28: 24.8 | AG28: 24.1 | AH28: 26.6 | AI28: 32.2 | AJ28: 34.9 | AK28: 30.2 | AL28: 32.7 | AM28: 35.6 | AN28: 35.2 | AO28: 38.3 | AP28: 40.4 | AQ28: 46.1 | AR28: 55.1 | AS28: 63.8 | AT28: 64.9 | AU28: 71 | AV28: 79.2 | AW28: 81.4 | AX28: 84.6 | AY28: 96.2 | AZ28: 114.8 | BA28: 131.2 | BB28: 134 | BC28: 148.6 | BD28: 177.4 | BE28: 218.2 | BF28: 259.5 | BG28: 284.6 | BH28: 324.4 | BI28: 327.1 | BJ28: 323.7 | BK28: 383.6 | BL28: 412.5 | BM28: 402.3 | BN28: 403.3 | BO28: 433.2 | BP28: 471.5 | BQ28: 502.1 | BR28: 482.4 | BS28: 495.3 | BT28: 545.4 | BU28: 600.7 | BV28: 674.8 | BW28: 735.2 | BX28: 800 | BY28: 871 | BZ28: 946.3 | CA28: 1037.8 | CB28: 991.7 | CC28: 885.1 | CD28: 891.8 | CE28: 960 | CF28: 1065.2 | CG28: 1193 | CH28: 1295.3 | CI28: 1311.5 | CJ28: 1049.8 | CK28: 1063.9 | CL28: 1182.4 | CM28: =CL28*(1585.5/1456.2) -> 1287.3885 | CN28: =CM28*(1656.6/1585.5) -> 1345.1201
A29: Chain-Type Quantity Index Gross Investment | B29: FA Table 6.8, line 2: Bill-$ | C29: IGRcorpindexbea | D29: 4.341 | E29: 4.369 | F29: 4.1 | G29: 4.202 | H29: 4.686 | I29: 4.075 | J29: 2.74 | K29: 1.776 | L29: 1.663 | M29: 2.008 | N29: 2.29 | O29: 3.006 | P29: 3.627 | Q29: 2.719 | R29: 2.979 | S29: 3.652 | T29: 4.138 | U29: 2.87 | V29: 2.375 | W29: 2.999 | X29: 4.106 | Y29: 5.658 | Z29: 6.328 | AA29: 6.593 | AB29: 5.828 | AC29: 6.25 | AD29: 6.927 | AE29: 7.097 | AF29: 7.616 | AG29: 7.356 | AH29: 8.027 | AI29: 9.022 | AJ29: 9.256 | AK29: 7.931 | AL29: 8.389 | AM29: 9.133 | AN29: 9.064 | AO29: 9.884 | AP29: 10.409 | AQ29: 11.802 | AR29: 13.97 | AS29: 15.96 | AT29: 15.875 | AU29: 16.812 | AV29: 18.042 | AW29: 17.712 | AX29: 17.616 | AY29: 19.429 | AZ29: 22.275 | BA29: 23.143 | BB29: 20.797 | BC29: 21.824 | BD29: 24.452 | BE29: 28.338 | BF29: 31.235 | BG29: 31.592 | BH29: 32.878 | BI29: 31.439 | BJ29: 31.457 | BK29: 37.465 | BL29: 40.149 | BM29: 38.793 | BN29: 38.662 | BO29: 40.552 | BP29: 43.32 | BQ29: 45.39 | BR29: 43.07 | BS29: 44.665 | BT29: 49.201 | BU29: 54.004 | BV29: 60.449 | BW29: 66.938 | BX29: 74.089 | BY29: 82.811 | BZ29: 91.39 | CA29: 100.294 | CB29: 96.265 | CC29: 86.285 | CD29: 87.116 | CE29: 92.709 | CF29: 100 | CG29: 108.115 | CH29: 115.008 | CI29: 114.026 | CJ29: 92.515 | CK29: 94.233 | CL29: 102.621 | CM29: =CL29*(120.696/112.46) -> 110.13644 | CN29: =CM29*(124.708/120.696) -> 113.79744
A30: Constant-Cost Quantity Index Gross Investment | B30: (IGRcorpindexbea(t)/100)*IGCcorpbea(2005): Bills-2005$ | C30: IGRcorpbea | D30: =(D29/100)*$CF$28 -> 46.240332 | E30: =(E29/100)*$CF$28 -> 46.538588 | F30: =(F29/100)*$CF$28 -> 43.6732 | G30: =(G29/100)*$CF$28 -> 44.759704 | H30: =(H29/100)*$CF$28 -> 49.915272 | I30: =(I29/100)*$CF$28 -> 43.4069 | J30: =(J29/100)*$CF$28 -> 29.18648 | K30: =(K29/100)*$CF$28 -> 18.917952 | ... CN30: =(CN29/100)*$CF$28 -> 1212.1703
A31: Implicit Price Deflator, Gross Investment | B31: (IGCcorpbea/IGRcorpbea)*100 | C31: pIGcorpbea | D31: =(D28/D30)*100 -> 15.787084 | E31: =(E28/E30)*100 -> 15.685908 | F31: =(F28/F30)*100 -> 15.799163 | G31: =(G28/G30)*100 -> 15.639067 | H31: =(H28/H30)*100 -> 15.426141 | I31: =(I28/I30)*100 -> 14.7442 | J31: =(J28/J30)*100 -> 13.704976 | K31: =(K28/K30)*100 -> 12.686363 | ... CN31: =(CN28/CN30)*100 -> 110.96791
A33: Current-cost approximation using Ch 6 eq. 6.57 | B33: KNC' = IGC + (1-d)*(pKN/pKN(-1))*KNC'(-1) | C33: KNCcorp' | D33: =D19 -> 98.1 | E33: =E28+(1-E26)*(E22/D22)*D33 -> 101.01839 | F33: =F28+(1-F26)*(F22/E22)*E33 -> 102.49926 | G33: =G28+(1-G26)*(G22/F22)*F33 -> 104.79002 | H33: =H28+(1-H26)*(H22/G22)*G33 -> 103.70879 | I33: =I28+(1-I26)*(I22/H22)*H33 -> 98.69751 | J33: =J28+(1-J26)*(J22/I22)*I33 -> 88.5405 | K33: =K28+(1-K26)*(K22/J22)*J33 -> 82.514764 | L33: =L28+(1-L26)*(L22/K22)*K33 -> 83.377983 | ... CL33: =CL28+(1-CL26)*(CL22/CK22)*CK33 -> 13531.22
A34: Constant-cost approximation using Ch 6 eq. 6.58 | B34: KNR' = (IGC*100/pKN) + (1-d)*KNR'(-1) | C34: KNRcorp' | D34: =D21 -> 1403.971 | E34: =(E28*100/E22)+(1-E26)*D34 -> 1441.0608 | F34: =(F28*100/F22)+(1-F26)*E34 -> 1471.1899 | G34: =(G28*100/G22)+(1-G26)*F34 -> 1501.2062 | H34: =(H28*100/H22)+(1-H26)*G34 -> 1541.2683 | I34: =(I28*100/I22)+(1-I26)*H34 -> 1566.5845 | J34: =(J28*100/J22)+(1-J26)*I34 -> 1557.6296 | K34: =(K28*100/K22)+(1-K26)*J34 -> 1527.8855 | L34: =(L28*100/L22)+(1-L26)*K34 -> 1499.0245 | ... CL34: =(CL28*100/CL22)+(1-CL26)*CK34 -> 11736.949
A35: Historical-cost approximation using Ch 6 eq. 6.59 | B35: KNH = INH + KNH(-1) where INH = IGC - DEPH, DEPH = hist cost deprec | C35: KNHcorp' | D35: =D23 -> 69.2 | E35: =(E28-E27)+D35 -> 72.3 | F35: =(F28-F27)+E35 -> 74.9 | G35: =(G28-G27)+F35 -> 77.6 | H35: =(H28-H27)+G35 -> 80.9 | I35: =(I28-I27)+H35 -> 82.8 | J35: =(J28-J27)+I35 -> 82.4 | K35: =(K28-K27)+J35 -> 80.6 | L35: =(L28-L27)+K35 -> 78.8 | ... CL35: =(CL28-CL27)+CK35 -> 9176.9
A37: Whelan-Liu Depreciation Rate | B37: Depcorp/KNCcorpbea(-1) | C37: dcorpWhelanLiu | E37: =E25/D19 -> 0.047910296 | F37: =F25/E19 -> 0.047524752 | G37: =G25/F19 -> 0.047851562 | H37: =H25/G19 -> 0.047755492 | I37: =I25/H19 -> 0.046332046 | J37: =J25/I19 -> 0.045685279 | K37: =K25/J19 -> 0.045248869 | L37: =L25/K19 -> 0.046116505 | ... CL37: =CL25/CK19 -> 0.08171856
A39: Relative Current-Cost Approximation | B39: KNCcorp'/KNCcorp | C39: KNCcorp'ratio | D39: =D33/D19 -> 1 | E39: =E33/E19 -> 1.000182 | F39: =F33/F19 -> 1.0009693 | G39: =G33/G19 -> 1.0008598 | H39: =H33/H19 -> 1.0010501 | I39: =I33/I19 -> 1.0020052 | J39: =J33/J19 -> 1.0015894 | K39: =K33/K19 -> 1.0013928 | ... CL39: =CL33/CL19 -> 1.000031
A40: Relative Constant-Cost Approximation | B40: KNRcorp'/KNRcorp | C40: KNRcorp'ratio | D40: =D34/D21 -> 1 | E40: =E34/E21 -> 1.000182 | F40: =F34/F21 -> 1.0009693 | G40: =G34/G21 -> 1.0008598 | H40: =H34/H21 -> 1.0010501 | I40: =I34/I21 -> 1.0020052 | J40: =J34/J21 -> 1.0015894 | K40: =K34/K21 -> 1.0013928 | ... CL40: =CL34/CL21 -> 1.000031
A41: Relative Historical-Cost Approximation | B41: KNHcorp'/KNhcorp | C41: KNHcorp'ratio | D41: =D35/D23 -> 1 | E41: =E35/E23 -> 1 | F41: =F35/F23 -> 1 | G41: =G35/G23 -> 1.0012903 | H41: =H35/H23 -> 1 | I41: =I35/I23 -> 1.0012092 | J41: =J35/J23 -> 1.0012151 | K41: =K35/K23 -> 1.0024876 | ... CL41: =CL35/CL23 -> 1.0059743
B43: Average Accuracy of GPIM rules, 1947-2009
A44: Average KNCcorpratio | B44: =AVERAGE(D39:CL39) -> 0.99612784
A45: Average KNRcorpratio | B45: =AVERAGE(D40:CL40) -> 0.99612784
A46: Average KNHcorpratio | B46: =AVERAGE(D41:CL41) -> 1.0022797

Sheet Appndx 6.8.II.2
A8: All estimates pertain to Corporate Current-Cost Net Stocks (IGC, d, and pKN are taken from Appendix 6.8B1)
A9: Appendix 7.2C2: Effects of Different Initial Values
A10: Description | B10: Source | C10: Variable | D10: 1925 | E10: 1926 | F10: 1927 | G10: 1928 | H10: 1929 | I10: 1930 | J10: 1931 | K10: 1932 | L10: 1933 | M10: 1934 | N10: 1935 | O10: 1936 | P10: 1937 | Q10: 1938 | R10: 1939 | S10: 1940 | T10: 1941 | U10: 1942 | V10: 1943 | W10: 1944 | X10: 1945 | Y10: 1946 | Z10: 1947 | AA10: 1948 | AB10: 1949 | AC10: 1950 | AD10: 1951 | AE10: 1952 | AF10: 1953 | AG10: 1954 | AH10: 1955 | AI10: 1956 | AJ10: 1957 | AK10: 1958 | AL10: 1959 | AM10: 1960 | AN10: 1961 | AO10: 1962 | AP10: 1963 | AQ10: 1964 | AR10: 1965 | AS10: 1966 | AT10: 1967 | AU10: 1968 | AV10: 1969 | AW10: 1970 | AX10: 1971 | AY10: 1972 | AZ10: 1973 | BA10: 1974 | BB10: 1975 | BC10: 1976 | BD10: 1977 | BE10: 1978 | BF10: 1979 | BG10: 1980 | BH10: 1981 | BI10: 1982 | BJ10: 1983 | BK10: 1984 | BL10: 1985 | BM10: 1986 | BN10: 1987 | BO10: 1988 | BP10: 1989 | BQ10: 1990 | BR10: 1991 | BS10: 1992 | BT10: 1993 | BU10: 1994 | BV10: 1995 | BW10: 1996 | BX10: 1997 | BY10: 1998 | BZ10: 1999 | CA10: 2000 | CB10: 2001 | CC10: 2002 | CD10: 2003 | CE10: 2004 | CF10: 2005 | CG10: 2006 | CH10: 2007 | CI10: 2008 | CJ10: 2009 | CK10: 2010 | CL10: 2011
A11: KNC' = IGC + (1-d)*(pKN/pKN(-1))*KNC'(-1)
A12: BEA 2011 initial value | B12: FA Table 6.1, line 1 | C12: KNCcorpbea | D12: 98.1 | E12: ='Appndx 6.8.II.1'!E28+(1-'Appndx 6.8.II.1'!E26)*('Appndx 6.8.II.1'!E22/'Appndx 6.8.II.1'!D22)*'Appndx 6.8.II.2'!D12 -> 101.01839 | F12: ='Appndx 6.8.II.1'!F28+(1-'Appndx 6.8.II.1'!F26)*('Appndx 6.8.II.1'!F22/'Appndx 6.8.II.1'!E22)*'Appndx 6.8.II.2'!E12 -> 102.49926 | G12: ='Appndx 6.8.II.1'!G28+(1-'Appndx 6.8.II.1'!G26)*('Appndx 6.8.II.1'!G22/'Appndx 6.8.II.1'!F22)*'Appndx 6.8.II.2'!F12 -> 104.79002 | H12: ='Appndx 6.8.II.1'!H28+(1-'Appndx 6.8.II.1'!H26)*('Appndx 6.8.II.1'!H22/'Appndx 6.8.II.1'!G22)*'Appndx 6.8.II.2'!G12 -> 103.70879 | I12: ='Appndx 6.8.II.1'!I28+(1-'Appndx 6.8.II.1'!I26)*('Appndx 6.8.II.1'!I22/'Appndx 6.8.II.1'!H22)*'Appndx 6.8.II.2'!H12 -> 98.69751 | J12: ='Appndx 6.8.II.1'!J28+(1-'Appndx 6.8.II.1'!J26)*('Appndx 6.8.II.1'!J22/'Appndx 6.8.II.1'!I22)*'Appndx 6.8.II.2'!I12 -> 88.5405 | K12: ='Appndx 6.8.II.1'!K28+(1-'Appndx 6.8.II.1'!K26)*('Appndx 6.8.II.1'!K22/'Appndx 6.8.II.1'!J22)*'Appndx 6.8.II.2'!J12 -> 82.514764 | L12: ='Appndx 6.8.II.1'!L28+(1-'Appndx 6.8.II.1'!L26)*('Appndx 6.8.II.1'!L22/'Appndx 6.8.II.1'!K22)*'Appndx 6.8.II.2'!K12 -> 83.377983 | ... CL12: ='Appndx 6.8.II.1'!CL28+(1-'Appndx 6.8.II.1'!CL26)*('Appndx 6.8.II.1'!CL22/'Appndx 6.8.II.1'!CK22)*'Appndx 6.8.II.2'!CK12 -> 13531.22
A13: BEA 1993 initial value | B13: Table A.13, p. 294 | C13: KNCcorp1' | D13: 77.769 | E13: ='Appndx 6.8.II.1'!E28+(1-'Appndx 6.8.II.1'!E26)*('Appndx 6.8.II.1'!E22/'Appndx 6.8.II.1'!D22)*D13 -> 81.595465 | F13: ='Appndx 6.8.II.1'!F28+(1-'Appndx 6.8.II.1'!F26)*('Appndx 6.8.II.1'!F22/'Appndx 6.8.II.1'!E22)*E13 -> 84.11828 | G13: ='Appndx 6.8.II.1'!G28+(1-'Appndx 6.8.II.1'!G26)*('Appndx 6.8.II.1'!G22/'Appndx 6.8.II.1'!F22)*F13 -> 87.253543 | H13: ='Appndx 6.8.II.1'!H28+(1-'Appndx 6.8.II.1'!H26)*('Appndx 6.8.II.1'!H22/'Appndx 6.8.II.1'!G22)*G13 -> 87.641839 | I13: ='Appndx 6.8.II.1'!I28+(1-'Appndx 6.8.II.1'!I26)*('Appndx 6.8.II.1'!I22/'Appndx 6.8.II.1'!H22)*H13 -> 84.398436 | J13: ='Appndx 6.8.II.1'!J28+(1-'Appndx 6.8.II.1'!J26)*('Appndx 6.8.II.1'!J22/'Appndx 6.8.II.1'!I22)*I13 -> 76.292461 | K13: ='Appndx 6.8.II.1'!K28+(1-'Appndx 6.8.II.1'!K26)*('Appndx 6.8.II.1'!K22/'Appndx 6.8.II.1'!J22)*J13 -> 71.43228 | L13: ='Appndx 6.8.II.1'!L28+(1-'Appndx 6.8.II.1'!L26)*('Appndx 6.8.II.1'!L22/'Appndx 6.8.II.1'!K22)*K13 -> 72.47504 | ... CL13: ='Appndx 6.8.II.1'!CL28+(1-'Appndx 6.8.II.1'!CL26)*('Appndx 6.8.II.1'!CL22/'Appndx 6.8.II.1'!CK22)*CK13 -> 13530.074
A14: SCB 1985 initial value | B14: Table 6, p. 56 | C14: KNCcorp2' | D14: 67.1 | E14: ='Appndx 6.8.II.1'!E28+(1-'Appndx 6.8.II.1'!E26)*('Appndx 6.8.II.1'!E22/'Appndx 6.8.II.1'!D22)*D14 -> 71.402994 | F14: ='Appndx 6.8.II.1'!F28+(1-'Appndx 6.8.II.1'!F26)*('Appndx 6.8.II.1'!F22/'Appndx 6.8.II.1'!E22)*E14 -> 74.472583 | G14: ='Appndx 6.8.II.1'!G28+(1-'Appndx 6.8.II.1'!G26)*('Appndx 6.8.II.1'!G22/'Appndx 6.8.II.1'!F22)*F14 -> 78.051009 | H14: ='Appndx 6.8.II.1'!H28+(1-'Appndx 6.8.II.1'!H26)*('Appndx 6.8.II.1'!H22/'Appndx 6.8.II.1'!G22)*G14 -> 79.210462 | I14: ='Appndx 6.8.II.1'!I28+(1-'Appndx 6.8.II.1'!I26)*('Appndx 6.8.II.1'!I22/'Appndx 6.8.II.1'!H22)*H14 -> 76.89478 | J14: ='Appndx 6.8.II.1'!J28+(1-'Appndx 6.8.II.1'!J26)*('Appndx 6.8.II.1'!J22/'Appndx 6.8.II.1'!I22)*I14 -> 69.865117 | K14: ='Appndx 6.8.II.1'!K28+(1-'Appndx 6.8.II.1'!K26)*('Appndx 6.8.II.1'!K22/'Appndx 6.8.II.1'!J22)*J14 -> 65.616578 | L14: ='Appndx 6.8.II.1'!L28+(1-'Appndx 6.8.II.1'!L26)*('Appndx 6.8.II.1'!L22/'Appndx 6.8.II.1'!K22)*K14 -> 66.753556 | ... CL14: ='Appndx 6.8.II.1'!CL28+(1-'Appndx 6.8.II.1'!CL26)*('Appndx 6.8.II.1'!CL22/'Appndx 6.8.II.1'!CK22)*CK14 -> 13529.472
A16: Ratio KNCcorp1' to KNCcorpbea | B16: KNCcorp1'/KNCcorpbea | C16: KNCcorp1'ratio | D16: =D13/D12 -> 0.79275229 | E16: =E13/E12 -> 0.80772886 | F16: =F13/F12 -> 0.82067208 | G16: =G13/G12 -> 0.83265123 | H16: =H13/H12 -> 0.84507627 | I16: =I13/I12 -> 0.85512223 | J16: =J13/J12 -> 0.86166739 | K16: =K13/K12 -> 0.86569089 | ... CL16: =CL13/CL12 -> 0.9999153
A17: Ratio KNCcorp2' to KNCcorpbea | B17: KNCCorp2'/KNCorpbea | C17: KNCCorp2'ratio | D17: =D14/D12 -> 0.68399592 | E17: =E14/E12 -> 0.70683166 | F17: =F14/F12 -> 0.72656704 | G17: =G14/G12 -> 0.74483243 | H17: =H14/H12 -> 0.76377769 | I17: =I14/I12 -> 0.77909543 | J17: =J14/J12 -> 0.78907525 | K17: =K14/K12 -> 0.79521015 | ... CL17: =CL14/CL12 -> 0.99987086

Sheet Appndx 6.8.II.3
A27: New Net Stock Calculations using BEA 1993 depreciation rates | D27: 1925 | E27: 1926 | F27: 1927 | G27: 1928 | H27: 1929 | I27: 1930 | J27: 1931 | K27: 1932 | L27: 1933 | M27: 1934 | N27: 1935 | O27: 1936 | P27: 1937 | Q27: 1938 | R27: 1939 | S27: 1940 | T27: 1941 | U27: 1942 | V27: 1943 | W27: 1944 | X27: 1945 | Y27: 1946 | Z27: 1947 | AA27: 1948 | AB27: 1949 | AC27: 1950 | AD27: 1951 | AE27: 1952 | AF27: 1953 | AG27: 1954 | AH27: 1955 | AI27: 1956 | AJ27: 1957 | AK27: 1958 | AL27: 1959 | AM27: 1960 | AN27: 1961 | AO27: 1962 | AP27: 1963 | AQ27: 1964 | AR27: 1965 | AS27: 1966 | AT27: 1967 | AU27: 1968 | AV27: 1969 | AW27: 1970 | AX27: 1971 | AY27: 1972 | AZ27: 1973 | BA27: 1974 | BB27: 1975 | BC27: 1976 | BD27: 1977 | BE27: 1978 | BF27: 1979 | BG27: 1980 | BH27: 1981 | BI27: 1982 | BJ27: 1983 | BK27: 1984 | BL27: 1985 | BM27: 1986 | BN27: 1987 | BO27: 1988 | BP27: 1989 | BQ27: 1990 | BR27: 1991 | BS27: 1992 | BT27: 1993 | BU27: 1994 | BV27: 1995 | BW27: 1996 | BX27: 1997 | BY27: 1998 | BZ27: 1999 | CA27: 2000 | CB27: 2001 | CC27: 2002 | CD27: 2003 | CE27: 2004 | CF27: 2005 | CG27: 2006 | CH27: 2007 | CI27: 2008 | CJ27: 2009 | CK27: 2010 | CL27: 2011
A28: Description | B28: Source | C28: Variable
A29: BEA 1993 Current-Cost Net stock | B29: BEA 1993, Table A13 | C29: KNCbea93 | D29: 77.769 | E29: 79.727 | F29: 80.892 | G29: 81.55 | H29: 81.369 | I29: 76.628 | J29: 68.367 | K29: 61.955 | L29: 60.951 | M29: 61.071 | N29: 61.096 | O29: 64.147 | P29: 67.517 | Q29: 66.281 | R29: 66.356 | S29: 69.879 | T29: 76.541 | U29: 80.512 | V29: 81.242 | W29: 82.345 | X29: 90.328 | Y29: 109.554 | Z29: 131.622 | AA29: 146.79 | AB29: 155.144 | AC29: 171.295 | AD29: 189.284 | AE29: 201.502 | AF29: 213.013 | AG29: 222.866 | AH29: 243.021 | AI29: 271.506 | AJ29: 292.041 | AK29: 301.41 | AL29: 314.077 | AM29: 323.054 | AN29: 331.447 | AO29: 343.819 | AP29: 357.177 | AQ29: 377.34 | AR29: 407.794 | AS29: 450.093 | AT29: 489.841 | AU29: 543.968 | AV29: 602.442 | AW29: 665.399 | AX29: 731.546 | AY29: 812.716 | AZ29: 922.601 | BA29: 1107.313 | BB29: 1252.398 | BC29: 1369.168 | BD29: 1520.544 | BE29: 1723.549 | BF29: 1976.173 | BG29: 2277.833 | BH29: 2579.67 | BI29: 2756.942 | BJ29: 2844.878 | BK29: 2993.218 | BL29: 3158.155 | BM29: 3317.184 | BN29: 3459.685 | BO29: 3681.151 | BP29: 3886.439
A30: BEA 1993 Constant-Cost Net stock (1987-$) | B30: BEA 1993, Table A12 | C30: KNRbea93 | D30: 822.004 | E30: 841.003 | F30: 855.083 | G30: 867.516 | H30: 887.887 | I30: 895.364 | J30: 879.613 | K30: 848.424 | L30: 816.242 | M30: 790.377 | N30: 769.43 | O30: 760.488 | P30: 759.942 | Q30: 745.033 | R30: 733.611 | S30: 732.947 | T30: 740.909 | U30: 728.618 | V30: 709.837 | W30: 701.423 | X30: 711.493 | Y30: 741.333 | Z30: 777.865 | AA30: 815.055 | AB30: 838.928 | AC30: 866.531 | AD30: 901.859 | AE30: 937.206 | AF30: 976.67 | AG30: 1009.261 | AH30: 1046.118 | AI30: 1094.62 | AJ30: 1140.899 | AK30: 1163.212 | AL30: 1191.814 | AM30: 1227.248 | AN30: 1259.146 | AO30: 1297.596 | AP30: 1339.206 | AQ30: 1394.866 | AR30: 1472.725 | AS30: 1563.775 | AT30: 1645.171 | AU30: 1734.351 | AV30: 1830.371 | AW30: 1912.185 | AX30: 1982.783 | AY30: 2055.337 | AZ30: 2157.155 | BA30: 2258.035 | BB30: 2320.562 | BC30: 2380.386 | BD30: 2457.278 | BE30: 2559.33 | BF30: 2678.474 | BG30: 2787.287 | BH30: 2894.056 | BI30: 2970.881 | BJ30: 3028.835 | BK30: 3130.834 | BL30: 3253.706 | BM30: 3344.065 | BN30: 3415.174 | BO30: 3492.368 | BP30: 3574.711
A31: BEA 1993 Implicit Price Deflator, Net Stock (1985 = 100) | B31: KNCbea93*100/KNRbea93 | C31: pKNbea93 | D31: =D29*100/D30 -> 9.4609029 | E31: =E29*100/E30 -> 9.47999 | F31: =F29*100/F30 -> 9.4601343 | G31: =G29*100/G30 -> 9.400403 | H31: =H29*100/H30 -> 9.1643419 | I31: =I29*100/I30 -> 8.558307 | J31: =J29*100/J30 -> 7.7723954 | K31: =K29*100/K30 -> 7.302363 | ... BP31: =BP29*100/BP30 -> 108.72037
A32: BEA 1993 Current-Cost Corporate Depreciation | B32: BEA 1993, Table A13 | C32: DEPcorpbea93 | D32: 4.96 | E32: 5.147 | F32: 5.237 | G32: 5.341 | H32: 5.45 | I32: 5.297 | J32: 4.956 | K32: 4.436 | L32: 4.258 | M32: 4.366 | N32: 4.406 | O32: 4.435 | P32: 4.919 | Q32: 4.999 | R32: 4.939 | S32: 5.107 | T32: 5.558 | U32: 6.136 | V32: 6.263 | W32: 6.356 | X32: 6.487 | Y32: 7.57 | Z32: 9.221 | AA32: 10.706 | AB32: 11.503 | AC32: 12.337 | AD32: 14.195 | AE32: 15.236 | AF32: 16.277 | AG32: 17.227 | AH32: 18.276 | AI32: 20.6 | AJ32: 22.672 | AK32: 23.71 | AL32: 24.826 | AM32: 25.867 | AN32: 26.644 | AO32: 27.623 | AP32: 28.863 | AQ32: 30.381 | AR32: 32.495 | AS32: 35.424 | AT32: 38.825 | AU32: 42.89 | AV32: 46.945 | AW32: 51.518 | AX32: 56.686 | AY32: 63.319 | AZ32: 68.921 | BA32: 81.145 | BB32: 97.739 | BC32: 109.176 | BD32: 122.479 | BE32: 139.412 | BF32: 161.376 | BG32: 184.656 | BH32: 216.612 | BI32: 242.989 | BJ32: 250.712 | BK32: 262.662 | BL32: 277.837 | BM32: 294.178 | BN32: 307.715 | BO32: 327.639 | BP32: 352.382
A33: BEA 1993 Depreciation Rate, Net Stock | B33: DEPcorp*100/[pKN*KNR(-1)] | C33: dcorpnew | E33: =E32*100/(E31*D30) -> 0.06604993 | F33: =F32*100/(F31*E30) -> 0.065824524 | G33: =G32*100/(G31*F30) -> 0.066445846 | H33: =H32*100/(H31*G30) -> 0.068551621 | I33: =I32*100/(I31*H30) -> 0.069708288 | J33: =J32*100/(J31*I30) -> 0.07121587 | K33: =K32*100/(K31*J30) -> 0.069061576 | L33: =L32*100/(L31*K30) -> 0.067209523 | ... BP33: =BP32*100/(BP31*BO30) -> 0.092807441 | BQ33: 0.090586019 | BR33: 0.090945938 | BS33: 0.091305857 | BT33: 0.091665776 | BU33: 0.092025696 | BV33: 0.092385615 | BW33: 0.092745534 | BX33: 0.093105454 | BY33: 0.093465373 | BZ33: 0.093825292 | CA33: 0.094185212 | CB33: 0.094545131 | CC33: 0.09490505 | CD33: 0.095264969 | CE33: 0.095624889 | CF33: 0.095984808 | CG33: 0.096344727 | CH33: 0.096704647 | CI33: 0.097064566 | CJ33: 0.097424485 | CK33: 0.097784404 | CL33: 0.098144324
A34: BEA 2011 Chain Index Net Stock Deflator, 2005 = 100 | B34: Appendix Table 6.8.II.1 | C34: pKN | D34: ='Appndx 6.8.II.1'!D22 -> 6.987324 | E34: ='Appndx 6.8.II.1'!E22 -> 7.0100016 | F34: ='Appndx 6.8.II.1'!F22 -> 6.9670989 | G34: ='Appndx 6.8.II.1'!G22 -> 6.9803885 | H34: ='Appndx 6.8.II.1'!H22 -> 6.7287953 | I34: ='Appndx 6.8.II.1'!I22 -> 6.3001716 | J34: ='Appndx 6.8.II.1'!J22 -> 5.6843103 | K34: ='Appndx 6.8.II.1'!K22 -> 5.4005857 | ... CL34: ='Appndx 6.8.II.1'!CL22 -> 115.28736
A35: BEA 2011 Current-Cost Gross Investment | B35: Appendix Table 6.8.II.1 | C35: IGCcorp | D35: ='Appndx 6.8.II.1'!D28 -> 7.3 | E35: ='Appndx 6.8.II.1'!E28 -> 7.3 | F35: ='Appndx 6.8.II.1'!F28 -> 6.9 | G35: ='Appndx 6.8.II.1'!G28 -> 7 | H35: ='Appndx 6.8.II.1'!H28 -> 7.7 | I35: ='Appndx 6.8.II.1'!I28 -> 6.4 | J35: ='Appndx 6.8.II.1'!J28 -> 4 | K35: ='Appndx 6.8.II.1'!K28 -> 2.4 | ... CL35: ='Appndx 6.8.II.1'!CL28 -> 1182.4
A36: New Net Current Cost Corp Stock | B36: KNCnew = IGC + (1-dcorpnew)* (pKN/pKN(-1))*KNCnew(-1) | C36: KNCcorpnew | D36: ='Appndx 6.8.II.1'!D19 -> 98.1 | E36: =E35+(1-E33)*(E34/D34)*D36 -> 99.217858 | F36: =F35+(1-F33)*(F34/E34)*E36 -> 99.019627 | G36: =G35+(1-G33)*(G34/F34)*F36 -> 99.616513 | H36: =H35+(1-H33)*(H34/G34)*G36 -> 97.143306 | I36: =I35+(1-I33)*(I34/H34)*H36 -> 91.014949 | J36: =J35+(1-J33)*(J34/I34)*I36 -> 80.269854 | K36: =K35+(1-K33)*(K34/J34)*J36 -> 73.396431 | L36: =L35+(1-L33)*(L34/K34)*K36 -> 72.711645 | ... CL36: =CL35+(1-CL33)*(CL34/CK34)*CK36 -> 11799.352
A38: New Gross Stock Calculations using BEA 1993 retirement rates
A39: BEA 1993 Current-Cost Gross stock | B39: BEA 1993, Table A13 | C39: KGCBEA93 | D39: 141.919 | E39: 145.696 | F39: 148.348 | G39: 150.074 | H39: 149.632 | I39: 141.978 | J39: 129.182 | K39: 120.679 | L39: 122.035 | M39: 124.88 | N39: 126.869 | O39: 133.765 | P39: 140.484 | Q39: 139.427 | R39: 140.596 | S39: 147.741 | T39: 160.425 | U39: 170.762 | V39: 174.908 | W39: 178.379 | X39: 194.582 | Y39: 231.343 | Z39: 270.887 | AA39: 294.768 | AB39: 306.807 | AC39: 334.333 | AD39: 364.49 | AE39: 384.138 | AF39: 400.577 | AG39: 415.992 | AH39: 449.719 | AI39: 496.142 | AJ39: 528.464 | AK39: 545.673 | AL39: 567.653 | AM39: 582.198 | AN39: 596.763 | AO39: 616.775 | AP39: 638.342 | AQ39: 669.61 | AR39: 715.007 | AS39: 778.039 | AT39: 840.995 | AU39: 926.971 | AV39: 1017.831 | AW39: 1121.216 | AX39: 1233.536 | AY39: 1367.632 | AZ39: 1548.379 | BA39: 1861.764 | BB39: 2119.815 | BC39: 2332.965 | BD39: 2602.04 | BE39: 2952.598 | BF39: 3381.143 | BG39: 3904.797 | BH39: 4435.338 | BI39: 4768.501 | BJ39: 4954.932 | BK39: 5215.763 | BL39: 5497.031 | BM39: 5795.792 | BN39: 6082.296 | BO39: 6510.176 | BP39: 6909.898
A40: BEA 1993 Constant-Cost Gross stock (1987-$) | B40: BEA 1993, Table A12 | C40: KGRBEA93 | D40: 1503.79 | E40: 1541.389 | F40: 1572.329 | G40: 1601.811 | H40: 1639.396 | I40: 1663.032 | J40: 1662.333 | K40: 1644.989 | L40: 1623.978 | M40: 1606.532 | N40: 1591.274 | O40: 1586.129 | P40: 1588.158 | Q40: 1575.011 | R40: 1563.651 | S40: 1561.845 | T40: 1567.567 | U40: 1555.591 | V40: 1535.969 | W40: 1525.874 | X40: 1534.589 | Y40: 1565.906 | Z40: 1602.502 | AA40: 1642.425 | AB40: 1670.512 | AC40: 1705.878 | AD40: 1750.068 | AE40: 1797.486 | AF40: 1850.221 | AG40: 1896.847 | AH40: 1949.082 | AI40: 2014.866 | AJ40: 2079.446 | AK40: 2119.727 | AL40: 2167.912 | AM40: 2222.912 | AN40: 2275.488 | AO40: 2334.487 | AP40: 2398.932 | AQ40: 2479.204 | AR40: 2584.572 | AS40: 2706.592 | AT40: 2823.715 | AU40: 2952.597 | AV40: 3092.516 | AW40: 3223.135 | AX40: 3346.056 | AY40: 3471.619 | AZ40: 3631.866 | BA40: 3797.505 | BB40: 3926.325 | BC40: 4054.95 | BD40: 4202.794 | BE40: 4381.082 | BF40: 4579.184 | BG40: 4769.888 | BH40: 4962.458 | BI40: 5124.66 | BJ40: 5266.702 | BK40: 5451.561 | BL40: 5660.945 | BM40: 5840.868 | BN40: 6002.256 | BO40: 6171.324 | BP40: 6346.12
A41: BEA 1993 Implicit Price Deflator, Gross Stock | B41: KGCbea93*100/KGRbea93 | C41: pKGbea93 | D41: =D39*100/D40 -> 9.4374214 | E41: =E39*100/E40 -> 9.4522538 | F41: =F39*100/F40 -> 9.4349211 | G41: =G39*100/G40 -> 9.3690204 | H41: =H39*100/H40 -> 9.1272639 | I41: =I39*100/I40 -> 8.5372981 | J41: =J39*100/J40 -> 7.7711265 | K41: =K39*100/K40 -> 7.3361585 | ... BP41: =BP39*100/BP40 -> 108.88382
A42: BEA 1993 Current-Cost Corporate Retirements (Discards) | B42: BEA 1993, Table A13 | C42: RETcorpBEA93 | D42: 2.962 | E42: 3.09 | F42: 3.377 | G42: 3.435 | H42: 3.484 | I42: 3.51 | J42: 3.406 | K42: 3.188 | L42: 3.277 | M42: 3.537 | N42: 3.769 | O42: 3.877 | P42: 4.385 | Q42: 4.582 | R42: 4.627 | S42: 4.767 | T42: 5.181 | U42: 5.719 | V42: 6 | W42: 6.228 | X42: 6.514 | Y42: 7.244 | Z42: 8.553 | AA42: 9.687 | AB42: 10.077 | AC42: 10.33 | AD42: 11.647 | AE42: 11.966 | AF42: 12.574 | AG42: 13.408 | AH42: 14.06 | AI42: 15.769 | AJ42: 17.222 | AK42: 17.756 | AL42: 18.654 | AM42: 19.55 | AN42: 20.047 | AO42: 20.77 | AP42: 21.545 | AQ42: 22.707 | AR42: 23.933 | AS42: 25.593 | AT42: 27.095 | AU42: 29.426 | AV42: 31.43 | AW42: 33.437 | AX42: 36.046 | AY42: 41.077 | AZ42: 43.136 | BA42: 49.836 | BB42: 60.504 | BC42: 67.389 | BD42: 76.393 | BE42: 86.116 | BF42: 100.625 | BG42: 115.714 | BH42: 135.809 | BI42: 155.672 | BJ42: 164.233 | BK42: 173.461 | BL42: 185.16 | BM42: 197.971 | BN42: 209.399 | BO42: 225.605 | BP42: 248.01
A43: BEA 1993 Retirement Rate, Gross Stock | B43: RETcorp/[pKG*KGR(-1)] | C43: ρ corpnew | E43: =E42*100/(E41*D40) -> 0.021738817 | F43: =F42*100/(F41*E40) -> 0.023220979 | G43: =G42*100/(G41*F40) -> 0.023317884 | H43: =H42*100/(H41*G40) -> 0.023830122 | I43: =I42*100/(I41*H40) -> 0.025078572 | J43: =J42*100/(J41*I40) -> 0.02635482 | K43: =K42*100/(K41*J40) -> 0.026141565 | L43: =L42*100/(L41*K40) -> 0.026509967 | ... BP43: =BP42*100/(BP41*BO40) -> 0.036908593 | BQ43: 0.034951698 | BR43: 0.035054434 | BS43: 0.03515717 | BT43: 0.035259907 | BU43: 0.035362643 | BV43: 0.035465379 | BW43: 0.035568115 | BX43: 0.035670851 | BY43: 0.035773587 | BZ43: 0.035876323 | CA43: 0.035979059 | CB43: 0.036081795 | CC43: 0.036184531 | CD43: 0.036287267 | CE43: 0.036390003 | CF43: 0.036492739 | CG43: 0.036595475 | CH43: 0.036698211 | CI43: 0.036800948 | CJ43: 0.036903684 | CK43: 0.03700642 | CL43: 0.037109156
A44: New Gross Current Cost Corp Stock | B44: KGCnew = IGC + (1-rcorpnew)*(pKN/pKN(-1))*KGCnew(-1) | C44: KGCcorpnew | D44: =D36 -> 98.1 | E44: =E35+(1-E43)*(E34/D34)*D44 -> 103.57889 | F44: =F35+(1-F43)*(F34/E34)*E44 -> 107.45448 | G44: =G35+(1-G43)*(G34/F34)*F44 -> 112.14906 | H44: =H35+(1-H43)*(H34/G34)*G44 -> 113.23068 | I44: =I35+(1-I43)*(I34/H34)*H44 -> 109.75912 | J44: =J35+(1-J43)*(J34/I34)*I44 -> 100.41991 | K44: =K35+(1-K43)*(K34/J34)*J44 -> 95.313487 | L44: =L35+(1-L43)*(L34/K34)*K44 -> 97.762537 | ... CL44: =CL35+(1-CL43)*(CL34/CK34)*CK44 -> 23096.765
A46: Ratio of New Current-Cost Net Stock to BEA Net Stock | C46: KNCorpnew/KNCbea | D46: =D36/'Appndx 6.8.II.1'!D19 -> 1 | E46: =E36/'Appndx 6.8.II.1'!E19 -> 0.98235503 | F46: =F36/'Appndx 6.8.II.1'!F19 -> 0.96698855 | G46: =G36/'Appndx 6.8.II.1'!G19 -> 0.95144711 | H46: =H36/'Appndx 6.8.II.1'!H19 -> 0.9376767 | I46: =I36/'Appndx 6.8.II.1'!I19 -> 0.92400963 | J46: =J36/'Appndx 6.8.II.1'!J19 -> 0.90803002 | K46: =K36/'Appndx 6.8.II.1'!K19 -> 0.89073338 | ... CL46: =CL36/'Appndx 6.8.II.1'!CL19 -> 0.87203653
A47: Ratio of New Current-Cost Net Stock to BEA Net Stock | C47: KGCcorpnew/KNCbea | D47: =D44/'Appndx 6.8.II.1'!D19 -> 1 | E47: =E44/'Appndx 6.8.II.1'!E19 -> 1.0255335 | F47: =F44/'Appndx 6.8.II.1'!F19 -> 1.0493602 | G47: =G44/'Appndx 6.8.II.1'!G19 -> 1.0711467 | H47: =H44/'Appndx 6.8.II.1'!H19 -> 1.0929603 | I47: =I44/'Appndx 6.8.II.1'!I19 -> 1.1143058 | J47: =J44/'Appndx 6.8.II.1'!J19 -> 1.1359719 | K47: =K44/'Appndx 6.8.II.1'!K19 -> 1.1567171 | ... CL47: =CL44/'Appndx 6.8.II.1'!CL19 -> 1.7069771
A49: Average depreciation rate (dcorpnew) based on BEA 1993 | B49: =AVERAGE(E33:CL33) -> 0.082847754
A50: Average retirement rate (ρcorpnew) based on BEA 1993 | B50: =AVERAGE(E43:CL43) -> 0.032742873

Sheet Appndx 6.8.II.4
A20: New Net Stock Calculations using BEA 1993 depreciation rates | D20: 1925 | E20: 1926 | F20: 1927 | G20: 1928 | H20: 1929 | I20: 1930 | J20: 1931 | K20: 1932 | L20: 1933 | M20: 1934 | N20: 1935 | O20: 1936 | P20: 1937 | Q20: 1938 | R20: 1939 | S20: 1940 | T20: 1941 | U20: 1942 | V20: 1943 | W20: 1944 | X20: 1945 | Y20: 1946 | Z20: 1947 | AA20: 1948 | AB20: 1949 | AC20: 1950 | AD20: 1951 | AE20: 1952 | AF20: 1953 | AG20: 1954 | AH20: 1955 | AI20: 1956 | AJ20: 1957 | AK20: 1958 | AL20: 1959 | AM20: 1960 | AN20: 1961 | AO20: 1962 | AP20: 1963 | AQ20: 1964 | AR20: 1965 | AS20: 1966 | AT20: 1967 | AU20: 1968 | AV20: 1969 | AW20: 1970 | AX20: 1971 | AY20: 1972 | AZ20: 1973 | BA20: 1974 | BB20: 1975 | BC20: 1976 | BD20: 1977 | BE20: 1978 | BF20: 1979 | BG20: 1980 | BH20: 1981 | BI20: 1982 | BJ20: 1983 | BK20: 1984 | BL20: 1985 | BM20: 1986 | BN20: 1987 | BO20: 1988 | BP20: 1989 | BQ20: 1990 | BR20: 1991 | BS20: 1992 | BT20: 1993 | BU20: 1994 | BV20: 1995 | BW20: 1996 | BX20: 1997 | BY20: 1998 | BZ20: 1999 | CA20: 2000 | CB20: 2001 | CC20: 2002 | CD20: 2003 | CE20: 2004 | CF20: 2005 | CG20: 2006 | CH20: 2007 | CI20: 2008 | CJ20: 2009 | CK20: 2010 | CL20: 2011
A21: Description | B21: Source | C21: Variable
A22: Book Value of Total Corporate Assets (incl. land) less Reserves [1] | B22: HS 1975, Series V 115, pp. 924-926 | C22: KTHcorpirs | D22: 93341.516 | E22: 97523 | F22: 104945 | G22: 109931 | H22: 116446 | I22: 120994 | J22: 114303 | K22: 108553 | L22: 104958 | M22: 102751 | N22: 100480 | O22: 97873 | P22: 100320 | Q22: 99299 | R22: 100226 | S22: 100214 | T22: 100698 | U22: 99772 | V22: 97728 | W22: 95128 | X22: 92057 | Y22: 100329 | Z22: 112194 | AA22: 125650 | AB22: 135617 | AC22: 144691 | AD22: 159325 | AE22: 169546 | AF22: 180612 | AG22: 191437 | AH22: 206388 | AI22: 225862 | AJ22: 244463 | AK22: 259613 | AL22: 275772 | AM22: 293215 | AN22: 310266 | AO22: 333992.45 | AP22: 342026 | AQ22: 365551 | AR22: 395297 | AS22: 432034 | AT22: 467446 | AU22: 504865 | AV22: 561306 | AW22: 599465
A23: KTHcorpirs relative to its initial value | C23: KTHcorpirsIndx | D23: =D22/$D$22 -> 1 | E23: =E22/$D$22 -> 1.0447977 | F23: =F22/$D$22 -> 1.1243121 | G23: =G22/$D$22 -> 1.1777289 | H23: =H22/$D$22 -> 1.2475263 | I23: =I22/$D$22 -> 1.2962506 | J23: =J22/$D$22 -> 1.2245676 | K23: =K22/$D$22 -> 1.1629659 | ... AW23: =AW22/$D$22 -> 6.4222762
A24: KNHcorbea relative to its initial value | B24: Appendix Table 6.8B1 | C24: KNHcorpbeaIndx | D24: ='Appndx 6.8.II.1'!D35/'Appndx 6.8.II.1'!$D$35 -> 1 | E24: ='Appndx 6.8.II.1'!E35/'Appndx 6.8.II.1'!$D$35 -> 1.0447977 | F24: ='Appndx 6.8.II.1'!F35/'Appndx 6.8.II.1'!$D$35 -> 1.0823699 | G24: ='Appndx 6.8.II.1'!G35/'Appndx 6.8.II.1'!$D$35 -> 1.1213873 | H24: ='Appndx 6.8.II.1'!H35/'Appndx 6.8.II.1'!$D$35 -> 1.1690751 | I24: ='Appndx 6.8.II.1'!I35/'Appndx 6.8.II.1'!$D$35 -> 1.1965318 | J24: ='Appndx 6.8.II.1'!J35/'Appndx 6.8.II.1'!$D$35 -> 1.1907514 | K24: ='Appndx 6.8.II.1'!K35/'Appndx 6.8.II.1'!$D$35 -> 1.1647399 | ... CL24: ='Appndx 6.8.II.1'!CL35/'Appndx 6.8.II.1'!$D$35 -> 132.61416
A26: Adjusted KNCcorp | B26: See text at top of sheet | C26: KNCcorpbeaAdj | D26: ='Appndx 6.8.II.1'!D19*D23 -> 98.1 | E26: =$D$26*E23 -> 102.49465 | F26: =$D$26*F23 -> 110.29502 | G26: =$D$26*G23 -> 115.5352 | H26: =$D$26*H23 -> 122.38233 | I26: =$D$26*I23 -> 127.16219 | J26: =$D$26*J23 -> 120.13009 | K26: =$D$26*K23 -> 114.08695 | L26: =$D$26*L23 -> 110.30868 | ... Z26: =$D$26*Z23 -> 117.91357 | AA26: ='Appndx 6.8.II.3'!AA35+(1-'Appndx 6.8.II.3'!AA33)*('Appndx 6.8.II.3'!AA34/'Appndx 6.8.II.3'!Z34)*'Appndx 6.8.II.4'!Z26 -> 132.67907 | AB26: ='Appndx 6.8.II.3'!AB35+(1-'Appndx 6.8.II.3'!AB33)*('Appndx 6.8.II.3'!AB34/'Appndx 6.8.II.3'!AA34)*'Appndx 6.8.II.4'!AA26 -> 138.24071 | AC26: ='Appndx 6.8.II.3'!AC35+(1-'Appndx 6.8.II.3'!AC33)*('Appndx 6.8.II.3'!AC34/'Appndx 6.8.II.3'!AB34)*'Appndx 6.8.II.4'!AB26 -> 157.62853 | AD26: ='Appndx 6.8.II.3'!AD35+(1-'Appndx 6.8.II.3'!AD33)*('Appndx 6.8.II.3'!AD34/'Appndx 6.8.II.3'!AC34)*'Appndx 6.8.II.4'!AC26 -> 174.5251 | AE26: ='Appndx 6.8.II.3'!AE35+(1-'Appndx 6.8.II.3'!AE33)*('Appndx 6.8.II.3'!AE34/'Appndx 6.8.II.3'!AD34)*'Appndx 6.8.II.4'!AD26 -> 187.64701 | AF26: ='Appndx 6.8.II.3'!AF35+(1-'Appndx 6.8.II.3'!AF33)*('Appndx 6.8.II.3'!AF34/'Appndx 6.8.II.3'!AE34)*'Appndx 6.8.II.4'!AE26 -> 200.04818 | AG26: ='Appndx 6.8.II.3'!AG35+(1-'Appndx 6.8.II.3'!AG33)*('Appndx 6.8.II.3'!AG34/'Appndx 6.8.II.3'!AF34)*'Appndx 6.8.II.4'!AF26 -> 208.42454 | AH26: ='Appndx 6.8.II.3'!AH35+(1-'Appndx 6.8.II.3'!AH33)*('Appndx 6.8.II.3'!AH34/'Appndx 6.8.II.3'!AG34)*'Appndx 6.8.II.4'!AG26 -> 231.63075 | ... CL26: ='Appndx 6.8.II.3'!CL35+(1-'Appndx 6.8.II.3'!CL33)*('Appndx 6.8.II.3'!CL34/'Appndx 6.8.II.3'!CK34)*'Appndx 6.8.II.4'!CK26 -> 11798.685
A27: Adjusted KNRcorp | B27: See text at top of sheet | C27: KNRcorpbeaAdj | D27: ='Appndx 6.8.II.1'!D21*D23 -> 1403.971 | E27: =$D$27*E23 -> 1466.8656 | F27: =$D$27*F23 -> 1578.5016 | G27: =$D$27*G23 -> 1653.4972 | H27: =$D$27*H23 -> 1751.4908 | I27: =$D$27*I23 -> 1819.8983 | J27: =$D$27*J23 -> 1719.2574 | K27: =$D$27*K23 -> 1632.7703 | L27: =$D$27*L23 -> 1578.6971 | ... Z27: =$D$27*Z23 -> 1687.5355 | AA27: =('Appndx 6.8.II.3'!AA35*100/'Appndx 6.8.II.3'!AA34)+(1-'Appndx 6.8.II.3'!AA33)*Z27 -> 1702.9506 | AB27: =('Appndx 6.8.II.3'!AB35*100/'Appndx 6.8.II.3'!AB34)+(1-'Appndx 6.8.II.3'!AB33)*AA27 -> 1704.9416 | AC27: =('Appndx 6.8.II.3'!AC35*100/'Appndx 6.8.II.3'!AC34)+(1-'Appndx 6.8.II.3'!AC33)*AB27 -> 1710.7839 | AD27: =('Appndx 6.8.II.3'!AD35*100/'Appndx 6.8.II.3'!AD34)+(1-'Appndx 6.8.II.3'!AD33)*AC27 -> 1731.064 | AE27: =('Appndx 6.8.II.3'!AE35*100/'Appndx 6.8.II.3'!AE34)+(1-'Appndx 6.8.II.3'!AE33)*AD27 -> 1751.9064 | AF27: =('Appndx 6.8.II.3'!AF35*100/'Appndx 6.8.II.3'!AF34)+(1-'Appndx 6.8.II.3'!AF33)*AE27 -> 1781.2867 | AG27: =('Appndx 6.8.II.3'!AG35*100/'Appndx 6.8.II.3'!AG34)+(1-'Appndx 6.8.II.3'!AG33)*AF27 -> 1802.8944 | AH27: =('Appndx 6.8.II.3'!AH35*100/'Appndx 6.8.II.3'!AH34)+(1-'Appndx 6.8.II.3'!AH33)*AG27 -> 1831.9122 | ... CL27: =('Appndx 6.8.II.3'!CL35*100/'Appndx 6.8.II.3'!CL34)+(1-'Appndx 6.8.II.3'!CL33)*CK27 -> 10236.166
A28: Adjusted KNHcorp | B28: See text at top of sheet | C28: KNHcorpbeaAdj | D28: ='Appndx 6.8.II.1'!D23*D23 -> 69.2 | E28: =$D$28*E23 -> 72.3 | F28: =$D$28*F23 -> 77.8024 | G28: =$D$28*G23 -> 81.498839 | H28: =$D$28*H23 -> 86.328823 | I28: =$D$28*I23 -> 89.700544 | J28: =$D$28*J23 -> 84.740081 | K28: =$D$28*K23 -> 80.47724 | L28: =$D$28*L23 -> 77.812038 | ... Z28: =$D$28*Z23 -> 83.176545 | AA28: =('Appndx 6.8.II.3'!AA35-'Appndx 6.8.II.1'!Y27)+Z28 -> 95.776545 | AB28: =('Appndx 6.8.II.3'!AB35-'Appndx 6.8.II.1'!Z27)+AA28 -> 105.97655 | AC28: =('Appndx 6.8.II.3'!AC35-'Appndx 6.8.II.1'!AA27)+AB28 -> 116.87655 | AD28: =('Appndx 6.8.II.3'!AD35-'Appndx 6.8.II.1'!AB27)+AC28 -> 130.87655 | AE28: =('Appndx 6.8.II.3'!AE35-'Appndx 6.8.II.1'!AC27)+AD28 -> 145.07655 | AF28: =('Appndx 6.8.II.3'!AF35-'Appndx 6.8.II.1'!AD27)+AE28 -> 160.57655 | AG28: =('Appndx 6.8.II.3'!AG35-'Appndx 6.8.II.1'!AE27)+AF28 -> 174.57655 | AH28: =('Appndx 6.8.II.3'!AH35-'Appndx 6.8.II.1'!AF27)+AG28 -> 190.07655 | ... CL28: =('Appndx 6.8.II.3'!CL35-'Appndx 6.8.II.1'!CJ27)+CK28 -> 10940.877
A30: [1] The IRS data begins in 1926 and is backcast to 1925 through the 1926/1925 ratio of BEA 2011 historical-cost stock
A31: [2] Historical Statistics of Income, Colonial Times to 1970, US Bureau of Census, 1975

Sheet Appndx 6.8.II.5
D12: 1925 | E12: 1926 | F12: 1927 | G12: 1928 | H12: 1929 | I12: 1930 | J12: 1931 | K12: 1932 | L12: 1933 | M12: 1934 | N12: 1935 | O12: 1936 | P12: 1937 | Q12: 1938 | R12: 1939 | S12: 1940 | T12: 1941 | U12: 1942 | V12: 1943 | W12: 1944 | X12: 1945 | Y12: 1946 | Z12: 1947 | AA12: 1948 | AB12: 1949 | AC12: 1950 | AD12: 1951 | AE12: 1952 | AF12: 1953 | AG12: 1954 | AH12: 1955 | AI12: 1956 | AJ12: 1957 | AK12: 1958 | AL12: 1959 | AM12: 1960 | AN12: 1961 | AO12: 1962 | AP12: 1963 | AQ12: 1964 | AR12: 1965 | AS12: 1966 | AT12: 1967 | AU12: 1968 | AV12: 1969 | AW12: 1970 | AX12: 1971 | AY12: 1972 | AZ12: 1973 | BA12: 1974 | BB12: 1975 | BC12: 1976 | BD12: 1977 | BE12: 1978 | BF12: 1979 | BG12: 1980 | BH12: 1981 | BI12: 1982 | BJ12: 1983 | BK12: 1984 | BL12: 1985 | BM12: 1986 | BN12: 1987 | BO12: 1988 | BP12: 1989 | BQ12: 1990 | BR12: 1991 | BS12: 1992 | BT12: 1993 | BU12: 1994 | BV12: 1995 | BW12: 1996 | BX12: 1997 | BY12: 1998 | BZ12: 1999 | CA12: 2000 | CB12: 2001 | CC12: 2002 | CD12: 2003 | CE12: 2004 | CF12: 2005 | CG12: 2006 | CH12: 2007 | CI12: 2008 | CJ12: 2009 | CK12: 2010 | CL12: 2011
A13: Description | B13: Source | C13: Variable
A14: Adjustment Ratio 1925-1947 | B14: Appendix 6.8B4 (KNHcorpirsIndx) | C14: Adj. Ratio | D14: ='Appndx 6.8.II.4'!D23 -> 1 | E14: ='Appndx 6.8.II.4'!E23 -> 1.0447977 | F14: ='Appndx 6.8.II.4'!F23 -> 1.1243121 | G14: ='Appndx 6.8.II.4'!G23 -> 1.1777289 | H14: ='Appndx 6.8.II.4'!H23 -> 1.2475263 | I14: ='Appndx 6.8.II.4'!I23 -> 1.2962506 | J14: ='Appndx 6.8.II.4'!J23 -> 1.2245676 | K14: ='Appndx 6.8.II.4'!K23 -> 1.1629659 | ... Z14: ='Appndx 6.8.II.4'!Z23 -> 1.2019732
A15: Net Historical-Cost Capital Stock, using BEA 1993 depreciation rate and initial value,adjusted for interwar period | B15: Adj. ratio applied to initial stock until 1947, KNH GPIM rule thereafter | C15: KNHcorp | D15: 57.457 | E15: =$D$15*E14 -> 60.030941 | F15: =$D$15*F14 -> 64.599603 | G15: =$D$15*G14 -> 67.668769 | H15: =$D$15*H14 -> 71.679121 | I15: =$D$15*I14 -> 74.478673 | J15: =$D$15*J14 -> 70.359983 | K15: =$D$15*K14 -> 66.820532 | L15: =$D$15*L14 -> 64.607605 | ... Z15: =$D$15*Z14 -> 69.061774 | AA15: =Z15+('Appndx 6.8.II.1'!Z28-'Appndx 6.8.II.1'!Z27) -> 78.761774 | AB15: =AA15+('Appndx 6.8.II.1'!AA28-'Appndx 6.8.II.1'!AA27) -> 89.661774 | AC15: =AB15+('Appndx 6.8.II.1'!AB28-'Appndx 6.8.II.1'!AB27) -> 98.161774 | AD15: =AC15+('Appndx 6.8.II.1'!AC28-'Appndx 6.8.II.1'!AC27) -> 107.46177 | AE15: =AD15+('Appndx 6.8.II.1'!AD28-'Appndx 6.8.II.1'!AD27) -> 119.86177 | AF15: =AE15+('Appndx 6.8.II.1'!AE28-'Appndx 6.8.II.1'!AE27) -> 132.46177 | AG15: =AF15+('Appndx 6.8.II.1'!AF28-'Appndx 6.8.II.1'!AF27) -> 146.16177 | AH15: =AG15+('Appndx 6.8.II.1'!AG28-'Appndx 6.8.II.1'!AG27) -> 158.16177 | ... CL15: =CK15+('Appndx 6.8.II.1'!CK28-'Appndx 6.8.II.1'!CK27) -> 8876.5618
A16: Net Current-Cost Capital Stock, using BEA 1993 depreciation rate and initial value,adjusted for interwar period | B16: Adj. ratio applied to initial stock until 1947, KNC GPIM rule thereafter | C16: KNCcorp | D16: 77.77 | E16: =$D$16*E14 -> 81.253916 | F16: =$D$16*F14 -> 87.437756 | G16: =$D$16*G14 -> 91.591976 | H16: =$D$16*H14 -> 97.020124 | I16: =$D$16*I14 -> 100.80941 | J16: =$D$16*J14 -> 95.234625 | K16: =$D$16*K14 -> 90.443858 | L16: =$D$16*L14 -> 87.448587 | ... Z16: =$D$16*Z14 -> 93.477455 | AA16: ='Appndx 6.8.II.3'!AA35+(1-'Appndx 6.8.II.3'!AA33)*('Appndx 6.8.II.3'!AA34/'Appndx 6.8.II.3'!Z34)*'Appndx 6.8.II.5'!Z16 -> 108.87182 | AB16: ='Appndx 6.8.II.3'!AB35+(1-'Appndx 6.8.II.3'!AB33)*('Appndx 6.8.II.3'!AB34/'Appndx 6.8.II.3'!AA34)*'Appndx 6.8.II.5'!AA16 -> 116.34235 | AC16: ='Appndx 6.8.II.3'!AC35+(1-'Appndx 6.8.II.3'!AC33)*('Appndx 6.8.II.3'!AC34/'Appndx 6.8.II.3'!AB34)*'Appndx 6.8.II.5'!AB16 -> 135.47864 | AD16: ='Appndx 6.8.II.3'!AD35+(1-'Appndx 6.8.II.3'!AD33)*('Appndx 6.8.II.3'!AD34/'Appndx 6.8.II.3'!AC34)*'Appndx 6.8.II.5'!AC16 -> 153.05019 | AE16: ='Appndx 6.8.II.3'!AE35+(1-'Appndx 6.8.II.3'!AE33)*('Appndx 6.8.II.3'!AE34/'Appndx 6.8.II.3'!AD34)*'Appndx 6.8.II.5'!AD16 -> 167.35066 | AF16: ='Appndx 6.8.II.3'!AF35+(1-'Appndx 6.8.II.3'!AF33)*('Appndx 6.8.II.3'!AF34/'Appndx 6.8.II.3'!AE34)*'Appndx 6.8.II.5'!AE16 -> 181.09292 | AG16: ='Appndx 6.8.II.3'!AG35+(1-'Appndx 6.8.II.3'!AG33)*('Appndx 6.8.II.3'!AG34/'Appndx 6.8.II.3'!AF34)*'Appndx 6.8.II.5'!AF16 -> 190.95915 | AH16: ='Appndx 6.8.II.3'!AH35+(1-'Appndx 6.8.II.3'!AH33)*('Appndx 6.8.II.3'!AH34/'Appndx 6.8.II.3'!AG34)*'Appndx 6.8.II.5'!AG16 -> 214.44975 | ... CL16: ='Appndx 6.8.II.3'!CL35+(1-'Appndx 6.8.II.3'!CL33)*('Appndx 6.8.II.3'!CL34/'Appndx 6.8.II.3'!CK34)*'Appndx 6.8.II.5'!CK16 -> 11797.97
A17: Gross Current-Cost Capital Stock, using BEA 1993 depreciation rate and initial value, adjusted for interwar period | B17: Adj. ratio applied to initial stock until 1947, KGC GPIM rule thereafter | C17: KGCcorp | D17: 141.919 | E17: =$D$17*E14 -> 148.27664 | F17: =$D$17*F14 -> 159.56126 | G17: =$D$17*G14 -> 167.14211 | H17: =$D$17*H14 -> 177.04769 | I17: =$D$17*I14 -> 183.96259 | J17: =$D$17*J14 -> 173.78942 | K17: =$D$17*K14 -> 165.04696 | L17: =$D$17*L14 -> 159.58102 | ... Z17: =$D$17*Z14 -> 170.58283 | AA17: ='Appndx 6.8.II.3'!AA35+(1-'Appndx 6.8.II.3'!AA43)*('Appndx 6.8.II.3'!AA34/'Appndx 6.8.II.3'!Z34)*'Appndx 6.8.II.5'!Z17 -> 191.68359 | AB17: ='Appndx 6.8.II.3'!AB35+(1-'Appndx 6.8.II.3'!AB43)*('Appndx 6.8.II.3'!AB34/'Appndx 6.8.II.3'!AA34)*'Appndx 6.8.II.5'!AA17 -> 200.70477 | AC17: ='Appndx 6.8.II.3'!AC35+(1-'Appndx 6.8.II.3'!AC43)*('Appndx 6.8.II.3'!AC34/'Appndx 6.8.II.3'!AB34)*'Appndx 6.8.II.5'!AB17 -> 230.20601 | AD17: ='Appndx 6.8.II.3'!AD35+(1-'Appndx 6.8.II.3'!AD43)*('Appndx 6.8.II.3'!AD34/'Appndx 6.8.II.3'!AC34)*'Appndx 6.8.II.5'!AC17 -> 255.84979 | AE17: ='Appndx 6.8.II.3'!AE35+(1-'Appndx 6.8.II.3'!AE43)*('Appndx 6.8.II.3'!AE34/'Appndx 6.8.II.3'!AD34)*'Appndx 6.8.II.5'!AD17 -> 276.73284 | AF17: ='Appndx 6.8.II.3'!AF35+(1-'Appndx 6.8.II.3'!AF43)*('Appndx 6.8.II.3'!AF34/'Appndx 6.8.II.3'!AE34)*'Appndx 6.8.II.5'!AE17 -> 296.53556 | AG17: ='Appndx 6.8.II.3'!AG35+(1-'Appndx 6.8.II.3'!AG43)*('Appndx 6.8.II.3'!AG34/'Appndx 6.8.II.3'!AF34)*'Appndx 6.8.II.5'!AF17 -> 311.2351 | AH17: ='Appndx 6.8.II.3'!AH35+(1-'Appndx 6.8.II.3'!AH43)*('Appndx 6.8.II.3'!AH34/'Appndx 6.8.II.3'!AG34)*'Appndx 6.8.II.5'!AG17 -> 347.98339 | ... CL17: ='Appndx 6.8.II.3'!CL35+(1-'Appndx 6.8.II.3'!CL43)*('Appndx 6.8.II.3'!CL34/'Appndx 6.8.II.3'!CK34)*'Appndx 6.8.II.5'!CK17 -> 23023.969
A19: Ratio of new net stock to BEA | C19: KNCcorp/KNCcorpbea | D19: =D16/'Appndx 6.8.II.2'!D12 -> 0.79276249 | E19: =E16/'Appndx 6.8.II.2'!E12 -> 0.8043478 | F19: =F16/'Appndx 6.8.II.2'!F12 -> 0.85305744 | G19: =G16/'Appndx 6.8.II.2'!G12 -> 0.87405243 | H19: =H16/'Appndx 6.8.II.2'!H12 -> 0.93550529 | I19: =I16/'Appndx 6.8.II.2'!I12 -> 1.0213977 | J19: =J16/'Appndx 6.8.II.2'!J12 -> 1.0756052 | K19: =K16/'Appndx 6.8.II.2'!K12 -> 1.096093 | ... CL19: =CL16/'Appndx 6.8.II.2'!CL12 -> 0.87190737
A20: Ratio of new gross stock to BEA | C20: KGCcorp/KNCcorpbea | D20: =D17/'Appndx 6.8.II.2'!D12 -> 1.4466769 | E20: =E17/'Appndx 6.8.II.2'!E12 -> 1.4678184 | F20: =F17/'Appndx 6.8.II.2'!F12 -> 1.5567064 | G20: =G17/'Appndx 6.8.II.2'!G12 -> 1.5950192 | H20: =H17/'Appndx 6.8.II.2'!H12 -> 1.7071618 | I20: =I17/'Appndx 6.8.II.2'!I12 -> 1.8639031 | J20: =J17/'Appndx 6.8.II.2'!J12 -> 1.962824 | K20: =K17/'Appndx 6.8.II.2'!K12 -> 2.0002112 | ... CL20: =CL17/'Appndx 6.8.II.2'!CL12 -> 1.7015442

Sheet Appndx 6.8.II.6
C15: CHECK
D24: 1946 | E24: 1947 | F24: =E24+1 -> 1948 | G24: =F24+1 -> 1949 | H24: =G24+1 -> 1950 | I24: =H24+1 -> 1951 | J24: =I24+1 -> 1952 | K24: =J24+1 -> 1953 | L24: =K24+1 -> 1954 | M24: =L24+1 -> 1955 | ... BQ24: =BP24+1 -> 2011
A25: Description | B25: Source | C25: Variable
A26: IRS corporate Inventories, 1947-2011 | B26: IRS Corporate Balance Sheets (to 1997).xlsx; IRS Corporate Balance Sheets (extended to 2011).xlsx (Thousands $) | C26: INVIRScorp | D26: 36965000 | E26: 44009000 | F26: 48293000 | G26: 44726000 | H26: 54496000 | I26: 63776000 | J26: 64520000 | K26: 65519000 | L26: 62914000 | M26: 70920000 | N26: 78744000 | O26: 80560000 | P26: 80047000 | Q26: 88304000 | R26: 91334000 | S26: 94818000 | T26: 100327000 | U26: 106340000 | V26: 112960000 | W26: 126341000 | X26: 141019000 | Y26: 151581000 | Z26: 164433000 | AA26: 184583000 | AB26: 190401642 | AC26: 199091682 | AD26: 223847520 | AE26: 262566242 | AF26: 312096928 | AG26: 317718545 | AH26: 350644363 | AI26: 396032639 | AJ26: 442652820 | AK26: 503033064 | AL26: 534806547 | AM26: 588219956 | AN26: 581241455 | AO26: 599445162 | AP26: 664243060 | AQ26: 714722928 | AR26: 732587518 | AS26: 829272682 | AT26: 845783686 | AU26: 879318508 | AV26: 893586141 | AW26: 883913179 | AX26: 915412953 | AY26: 947287758 | AZ26: 1125766128 | BA26: 1045010082 | BB26: 1079396261 | BC26: 1114311184 | BD26: 1139210381 | BE26: 1198184825 | BF26: 1271967443 | BG26: 1208206944 | BH26: 1221112550 | BI26: 1267289489 | BJ26: 1386128237 | BK26: 1505452196 | BL26: 1612997968 | BM26: 1655695450 | BN26: 1619270780 | BO26: 1473962805 | BP26: 1544085221 | BQ26: 1652538308
A27: Depreciable Assets, 1990-2011 | B27: IRS Corporate Balance Sheets (extended to 2011).xlsx (Thousands $) | C27: KGHIRScorp | AV27: 4317781452 | AW27: 4549055093 | AX27: 4755145257 | AY27: 4968959443 | AZ27: 5284097003 | BA27: 5571142501 | BB27: 5923297939 | BC27: 6208236257 | BD27: 6541280743 | BE27: 6935503013 | BF27: 7291998758 | BG27: 7613590480 | BH27: 7677626201 | BI27: 7804548186 | BJ27: 7973940602 | BK27: 8415761105 | BL27: 8817095391 | BM27: 9221635446 | BN27: 9466523654 | BO27: 9613451456 | BP27: 9875410289 | BQ27: 10225874777
A28: Accumulated Depreciation, 1990-2011 | B28: " | C28: DeprecIRScorp | AV28: 1848022862 | AW28: 1999540977 | AX28: 2131890499 | AY28: 2265345826 | AZ28: 2438539251 | BA28: 2600545415 | BB28: 2760002783 | BC28: 2898167422 | BD28: 3031634536 | BE28: 3227243753 | BF28: 3369214883 | BG28: 3549239594 | BH28: 3699383948 | BI28: 3812960901 | BJ28: 3930550044 | BK28: 4096350302 | BL28: 4241564417 | BM28: 4335284540 | BN28: 4514037135 | BO28: 4711042846 | BP28: 4874203678 | BQ28: 5021678762
A29: IRS Net Fixed Capital, 1990-2011 | B29: Depreciable assets - accumulated depreciation (Thousand $) | C29: KNHIRScorp | AV29: =AV27-AV28 -> 2469758590 | AW29: =AW27-AW28 -> 2549514116 | AX29: =AX27-AX28 -> 2623254758 | AY29: =AY27-AY28 -> 2703613617 | AZ29: =AZ27-AZ28 -> 2845557752 | BA29: =BA27-BA28 -> 2970597086 | BB29: =BB27-BB28 -> 3163295156 | BC29: =BC27-BC28 -> 3310068835 | ... BQ29: =BQ27-BQ28 -> 5204196015
A30: BEA Net Historical Cost Capital Stock | B30: Appndx 6.8.II.1 (Bills $), BEA Historical Cost Net Stock | C30: KNHcorpbea | D30: ='Appndx 6.8.II.1'!Y23 -> 95.3 | E30: ='Appndx 6.8.II.1'!Z23 -> 105 | F30: ='Appndx 6.8.II.1'!AA23 -> 115.9 | G30: ='Appndx 6.8.II.1'!AB23 -> 124.4 | H30: ='Appndx 6.8.II.1'!AC23 -> 133.7 | I30: ='Appndx 6.8.II.1'!AD23 -> 146 | J30: ='Appndx 6.8.II.1'!AE23 -> 158.6 | K30: ='Appndx 6.8.II.1'!AF23 -> 172.3 | ... BQ30: ='Appndx 6.8.II.1'!CL23 -> 9122.4
A31: See AppFig6.7.11 for graph and trend line | B31: (KNHIRS corp/ KNHcorpbea), actual for 1990-2011 | C31: (KNHIRScorp / KHNcorpbea) | AV31: =(AV29/1000000)/AV30 -> 0.755902 | AW31: =(AW29/1000000)/AW30 -> 0.74325524 | AX31: =(AX29/1000000)/AX30 -> 0.73113932 | AY31: =(AY29/1000000)/AY30 -> 0.71563927 | AZ31: =(AZ29/1000000)/AZ30 -> 0.712155 | BA31: =(BA29/1000000)/BA30 -> 0.69714325 | BB31: =(BB29/1000000)/BB30 -> 0.69472584 | BC31: =(BC29/1000000)/BC30 -> 0.67954606 | ... BQ31: =(BQ29/1000000)/BQ30 -> 0.5704854
B32: (KNHIRS / KHNBEA), actual for 1990-2011 and extrapolated via linear time trend for 1947-2011 | C32: (KNHIRScorp / KNHcorpbea)' | D32: =1.1584-0.0094*(D24-1946) -> 1.1584 | E32: =1.1584-0.0094*(E24-1946) -> 1.149 | F32: =1.1584-0.0094*(F24-1946) -> 1.1396 | G32: =1.1584-0.0094*(G24-1946) -> 1.1302 | H32: =1.1584-0.0094*(H24-1946) -> 1.1208 | I32: =1.1584-0.0094*(I24-1946) -> 1.1114 | J32: =1.1584-0.0094*(J24-1946) -> 1.102 | K32: =1.1584-0.0094*(K24-1946) -> 1.0926 | ... BQ32: =1.1584-0.0094*(BQ24-1946) -> 0.5474
B33: KNHIRS actual for 1990-2011, and estimated as KNHcorpbea*(KNHIRScorp / KHNcorpbea)' for 1947-1989 (Bill $) | C33: KNHIRScorpest | D33: =D30*D32 -> 110.39552 | E33: =E30*E32 -> 120.645 | F33: =F30*F32 -> 132.07964 | G33: =G30*G32 -> 140.59688 | H33: =H30*H32 -> 149.85096 | I33: =I30*I32 -> 162.2644 | J33: =J30*J32 -> 174.7772 | K33: =K30*K32 -> 188.25498 | ... BQ33: =BQ30*BQ32 -> 4993.6018
A35: Final Corporate Net Historical Cost Stock | B35: Appendix 6.8.II.5 | C35: KNHcorp | D35: ='Appndx 6.8.II.5'!Y15 -> 61.758193 | E35: ='Appndx 6.8.II.5'!Z15 -> 69.061774 | F35: ='Appndx 6.8.II.5'!AA15 -> 78.761774 | G35: ='Appndx 6.8.II.5'!AB15 -> 89.661774 | H35: ='Appndx 6.8.II.5'!AC15 -> 98.161774 | I35: ='Appndx 6.8.II.5'!AD15 -> 107.46177 | J35: ='Appndx 6.8.II.5'!AE15 -> 119.86177 | K35: ='Appndx 6.8.II.5'!AF15 -> 132.46177 | ... BQ35: ='Appndx 6.8.II.5'!CL15 -> 8876.5618
B36: INVcorp = (INVIRScorp)*KNHcorp/KNHIRScorp | C36: INVcorp | D36: =(D26/1000000)*(D35/D33) -> 20.679205 | E36: =(E26/1000000)*(E35/E33) -> 25.192421 | F36: =(F26/1000000)*(F35/F33) -> 28.798097 | G36: =(G26/1000000)*(G35/G33) -> 28.52277 | H36: =(H26/1000000)*(H35/H33) -> 35.698297 | I36: =(I26/1000000)*(I35/I33) -> 42.236511 | J36: =(J26/1000000)*(J35/J33) -> 44.247657 | K36: =(K26/1000000)*(K35/K33) -> 46.101107 | ... BQ36: =(BQ26/1000000)*(BQ35/BQ33) -> 2937.5307
A38: Inventory/net capital, IRS Corporate | B38: see variables above | C38: (INVIRScorp / KNHIRScorpest) | D38: =(D26/1000000)/D33 -> 0.33484149 | E38: =(E26/1000000)/E33 -> 0.36478097 | F38: =(F26/1000000)/F33 -> 0.36563546 | G38: =(G26/1000000)/G33 -> 0.31811517 | H38: =(H26/1000000)/H33 -> 0.36366801 | I38: =(I26/1000000)/I33 -> 0.39303754 | J38: =(J26/1000000)/J33 -> 0.3691557 | K38: =(K26/1000000)/K33 -> 0.34803329 | ... BQ38: =(BQ26/1000000)/BQ33 -> 0.33093114
A40: Estimated Corporate Inventories | B40: (INVIRScorp / KNHIRScorpest)*KNHcorp | C40: INVcorp | D40: =D38*D35 -> 20.679205 | E40: =E38*E35 -> 25.192421 | F40: =F38*F35 -> 28.798097 | G40: =G38*G35 -> 28.52277 | H40: =H38*H35 -> 35.698297 | I40: =I38*I35 -> 42.236511 | J40: =J38*J35 -> 44.247657 | K40: =K38*K35 -> 46.101107 | ... BQ40: =BQ38*BQ35 -> 2937.5307
A41: Final Corporate Gross Current Cost Fixed Capital Stock (plant, equipment) | B41: Appendix 6.8.II.5 | C41: KGCcorp | D41: ='Appndx 6.8.II.5'!Y17 -> 152.54296 | E41: ='Appndx 6.8.II.5'!Z17 -> 170.58283 | F41: ='Appndx 6.8.II.5'!AA17 -> 191.68359 | G41: ='Appndx 6.8.II.5'!AB17 -> 200.70477 | H41: ='Appndx 6.8.II.5'!AC17 -> 230.20601 | I41: ='Appndx 6.8.II.5'!AD17 -> 255.84979 | J41: ='Appndx 6.8.II.5'!AE17 -> 276.73284 | K41: ='Appndx 6.8.II.5'!AF17 -> 296.53556 | ... BQ41: ='Appndx 6.8.II.5'!CL17 -> 23023.969
A42: Final Corporate Current Cost Total Stock (plant, equipment, inventories) | B42: KGCcorp + INVcorp | C42: KTCcorp | D42: =D41+D40 -> 173.22217 | E42: =E41+E40 -> 195.77525 | F42: =F41+F40 -> 220.48169 | G42: =G41+G40 -> 229.22754 | H42: =H41+H40 -> 265.9043 | I42: =I41+I40 -> 298.0863 | J42: =J41+J40 -> 320.9805 | K42: =K41+K40 -> 342.63667 | ... BQ42: =BQ41+BQ40 -> 25961.499

Sheet Appndx 6.8.II.7
E1: 1946 | F1: 1946 | G1: 1947 | H1: 1948 | I1: 1949 | J1: 1950 | K1: 1951 | L1: 1952 | M1: 1953 | N1: 1954 | O1: 1955 | P1: 1956 | Q1: 1957 | R1: 1958 | S1: 1959 | T1: 1960 | U1: 1961 | V1: 1962 | W1: 1963 | X1: 1964 | Y1: 1965 | Z1: 1966 | AA1: 1967 | AB1: 1968 | AC1: 1969 | AD1: 1970 | AE1: 1971 | AF1: 1972 | AG1: 1973 | AH1: 1974 | AI1: 1975 | AJ1: 1976 | AK1: 1977 | AL1: 1978 | AM1: 1979 | AN1: 1980 | AO1: 1981 | AP1: 1982 | AQ1: 1983 | AR1: 1984 | AS1: 1985 | AT1: 1986 | AU1: 1987 | AV1: 1988 | AW1: 1989 | AX1: 1990 | AY1: 1991 | AZ1: 1992 | BA1: 1993 | BB1: 1994 | BC1: 1995 | BD1: 1996 | BE1: 1997 | BF1: 1998 | BG1: 1999 | BH1: 2000 | BI1: 2001 | BJ1: 2002 | BK1: 2003 | BL1: 2004 | BM1: 2005 | BN1: 2006 | BO1: 2007 | BP1: 2008 | BQ1: 2009 | BR1: 2010 | BS1: 2011
E19: 1946 | F19: 1946 | G19: 1947 | H19: 1948 | I19: 1949 | J19: 1950 | K19: 1951 | L19: 1952 | M19: 1953 | N19: 1954 | O19: 1955 | P19: 1956 | Q19: 1957 | R19: 1958 | S19: 1959 | T19: 1960 | U19: 1961 | V19: 1962 | W19: 1963 | X19: 1964 | Y19: 1965 | Z19: 1966 | AA19: 1967 | AB19: 1968 | AC19: 1969 | AD19: 1970 | AE19: 1971 | AF19: 1972 | AG19: 1973 | AH19: 1974 | AI19: 1975 | AJ19: 1976 | AK19: 1977 | AL19: 1978 | AM19: 1979 | AN19: 1980 | AO19: 1981 | AP19: 1982 | AQ19: 1983 | AR19: 1984 | AS19: 1985 | AT19: 1986 | AU19: 1987 | AV19: 1988 | AW19: 1989 | AX19: 1990 | AY19: 1991 | AZ19: 1992 | BA19: 1993 | BB19: 1994 | BC19: 1995 | BD19: 1996 | BE19: 1997 | BF19: 1998 | BG19: 1999 | BH19: 2000 | BI19: 2001 | BJ19: 2002 | BK19: 2003 | BL19: 2004 | BM19: 2005 | BN19: 2006 | BO19: 2007 | BP19: 2008 | BQ19: 2009 | BR19: 2010 | BS19: 2011
A20: Average | B20: Description | C20: Source | D20: Variable
A21: Final Measures
B22: Corporate Value Added adjusted for imputed interest | C22: Appendix Table 6..8.I-3 | D22: VAcorp | G22: ='Appndx6.8.I.1-3'!D128 -> 118.6 | H22: ='Appndx6.8.I.1-3'!E128 -> 136 | I22: ='Appndx6.8.I.1-3'!F128 -> 132.4 | J22: ='Appndx6.8.I.1-3'!G128 -> 150.6 | K22: ='Appndx6.8.I.1-3'!H128 -> 172.9 | L22: ='Appndx6.8.I.1-3'!I128 -> 180.9 | M22: ='Appndx6.8.I.1-3'!J128 -> 193.6 | N22: ='Appndx6.8.I.1-3'!K128 -> 190.4 | ... BS22: ='Appndx6.8.I.1-3'!BP128 -> 7614.3
B23: Corporate NOS adjusted for imputed interest (Earnings before Interest and Taxes) | C23: Appendix Table 6..8.I-4 | D23: NOScorp = Pcorp + NMINT | G23: ='Appndx6.8.I.1-3'!D129 -> 24.9 | H23: ='Appndx6.8.I.1-3'!E129 -> 32.1 | I23: ='Appndx6.8.I.1-3'!F129 -> 30.2 | J23: ='Appndx6.8.I.1-3'!G129 -> 37.2 | K23: ='Appndx6.8.I.1-3'!H129 -> 42.5 | L23: ='Appndx6.8.I.1-3'!I129 -> 40.6 | M23: ='Appndx6.8.I.1-3'!J129 -> 41.1 | N23: ='Appndx6.8.I.1-3'!K129 -> 40.3 | ... BS23: ='Appndx6.8.I.1-3'!BP129 -> 1862.4
B24: NIPA Corporate Profit | C24: Appendix Table 6..8.I-5 | D24: Pcorpnipa | G24: ='Appndx6.8.I.1-3'!D132 -> 22.5 | H24: ='Appndx6.8.I.1-3'!E132 -> 29.6 | I24: ='Appndx6.8.I.1-3'!F132 -> 27.6 | J24: ='Appndx6.8.I.1-3'!G132 -> 34.4 | K24: ='Appndx6.8.I.1-3'!H132 -> 39.1 | L24: ='Appndx6.8.I.1-3'!I132 -> 37 | M24: ='Appndx6.8.I.1-3'!J132 -> 37.3 | N24: ='Appndx6.8.I.1-3'!K132 -> 36.4 | ... BS24: ='Appndx6.8.I.1-3'!BP132 -> 1388.1
B25: Net Monetary Interest Paid and Transfers | C25: Corpnetmonint+corptransfers | D25: NMINT | G25: ='Appndx6.8.I.1-3'!D130+'Appndx6.8.I.1-3'!D131 -> 2.4 | H25: ='Appndx6.8.I.1-3'!E130+'Appndx6.8.I.1-3'!E131 -> 2.5 | I25: ='Appndx6.8.I.1-3'!F130+'Appndx6.8.I.1-3'!F131 -> 2.7 | J25: ='Appndx6.8.I.1-3'!G130+'Appndx6.8.I.1-3'!G131 -> 2.8 | K25: ='Appndx6.8.I.1-3'!H130+'Appndx6.8.I.1-3'!H131 -> 3.5 | L25: ='Appndx6.8.I.1-3'!I130+'Appndx6.8.I.1-3'!I131 -> 3.7 | M25: ='Appndx6.8.I.1-3'!J130+'Appndx6.8.I.1-3'!J131 -> 3.8 | N25: ='Appndx6.8.I.1-3'!K130+'Appndx6.8.I.1-3'!K131 -> 4 | ... BS25: ='Appndx6.8.I.1-3'!BP130+'Appndx6.8.I.1-3'!BP131 -> 474.3
B26: Corporate Current-Cost Fixed Capital (plant and equipment) Gross Stock | C26: Appendix Table 6.8.II.5 | D26: KGCcorp | E26: ='Appndx 6.8.II.5'!Y17 -> 152.54296 | G26: ='Appndx 6.8.II.5'!Z17 -> 170.58283 | H26: ='Appndx 6.8.II.5'!AA17 -> 191.68359 | I26: ='Appndx 6.8.II.5'!AB17 -> 200.70477 | J26: ='Appndx 6.8.II.5'!AC17 -> 230.20601 | K26: ='Appndx 6.8.II.5'!AD17 -> 255.84979 | L26: ='Appndx 6.8.II.5'!AE17 -> 276.73284 | M26: ='Appndx 6.8.II.5'!AF17 -> 296.53556 | N26: ='Appndx 6.8.II.5'!AG17 -> 311.2351 | ... BS26: ='Appndx 6.8.II.5'!CL17 -> 23023.969
B27: Corporate Inventories | C27: Appendix Table 6.8.II.6 | D27: INVcorp | E27: ='Appndx 6.8.II.6'!D36 -> 20.679205 | F27: ='Appndx 6.8.II.6'!D36 -> 20.679205 | G27: ='Appndx 6.8.II.6'!E36 -> 25.192421 | H27: ='Appndx 6.8.II.6'!F36 -> 28.798097 | I27: ='Appndx 6.8.II.6'!G36 -> 28.52277 | J27: ='Appndx 6.8.II.6'!H36 -> 35.698297 | K27: ='Appndx 6.8.II.6'!I36 -> 42.236511 | L27: ='Appndx 6.8.II.6'!J36 -> 44.247657 | M27: ='Appndx 6.8.II.6'!K36 -> 46.101107 | ... BS27: ='Appndx 6.8.II.6'!BQ36 -> 2937.5307
B28: Corporate Total Capital Stock (plant, equipment, inventories) | C28: KGCcorp + INVcorp | D28: KTCcorp | E28: =E26+E27 -> 173.22217 | F28: =E28 -> 173.22217 | G28: =G26+G27 -> 195.77525 | H28: =H26+H27 -> 220.48169 | I28: =I26+I27 -> 229.22754 | J28: =J26+J27 -> 265.9043 | K28: =K26+K27 -> 298.0863 | L28: =L26+L27 -> 320.9805 | M28: =M26+M27 -> 342.63667 | N28: =N26+N27 -> 357.27258 | ... BS28: =BS26+BS27 -> 25961.499
A30: =AVERAGE(G30:BS30) -> 0.45506548 | B30: Corp Max Rate of Profit, adj. for imputed interest and inventories | C30: VAcorp/KTCcorp(-1) | D30: Rcorp | G30: =G22/E28 -> 0.68466988 | H30: =H22/G28 -> 0.69467411 | I30: =I22/H28 -> 0.60050338 | J30: =J22/I28 -> 0.65698912 | K30: =K22/J28 -> 0.65023393 | L30: =L22/K28 -> 0.60687122 | M30: =M22/L28 -> 0.60315191 | N30: =N22/M28 -> 0.55569068 | O30: =O22/N28 -> 0.6037407 | ... BS30: =BS22/BR28 -> 0.30815798
A31: =AVERAGE(G31:BS31) -> 0.20595246 | B31: Corporate Profit Share, adj. for imputed interest | C31: NOScorp/VAcorp | D31: Profshcorp | G31: =G23/G22 -> 0.20994941 | H31: =H23/H22 -> 0.23602941 | I31: =I23/I22 -> 0.22809668 | J31: =J23/J22 -> 0.24701195 | K31: =K23/K22 -> 0.24580682 | L31: =L23/L22 -> 0.22443339 | M31: =M23/M22 -> 0.21229339 | N31: =N23/N22 -> 0.21165966 | ... BS31: =BS23/BS22 -> 0.24459241
A32: =AVERAGE(G32:BS32) -> 0.094742507 | B32: Corp Profit Rate, adj. for imputed interest and inventories | C32: NOS/KTC(-1) | D32: rcorp | G32: =G23/E28 -> 0.14374604 | H32: =H23/G28 -> 0.16396352 | I32: =I23/H28 -> 0.13697283 | J32: =J23/I28 -> 0.16228417 | K32: =K23/J28 -> 0.15983194 | L32: =L23/K28 -> 0.13620216 | M32: =M23/L28 -> 0.12804516 | N32: =N23/M28 -> 0.1176173 | O32: =O23/N28 -> 0.14358784 | ... BS32: =BS23/BR28 -> 0.075373104
A34: Conventional Measures (w/o imputed int correction, w/0 inventories, and w/o capital stock corrections)
B35: Corporate VA, w/o imputed interest adj. | C35: Appendix Table 6..8.I-3 | D35: VAcorpnipa | G35: ='Appndx6.8.I.1-3'!D89 -> 117.1 | H35: ='Appndx6.8.I.1-3'!E89 -> 134.1 | I35: ='Appndx6.8.I.1-3'!F89 -> 130.3 | J35: ='Appndx6.8.I.1-3'!G89 -> 148.4 | K35: ='Appndx6.8.I.1-3'!H89 -> 170.3 | L35: ='Appndx6.8.I.1-3'!I89 -> 178.1 | M35: ='Appndx6.8.I.1-3'!J89 -> 190.8 | N35: ='Appndx6.8.I.1-3'!K89 -> 187.4 | ... BS35: ='Appndx6.8.I.1-3'!BP89 -> 7431.5
B36: BEA 2011 Corp Current-Cost Net Stock | C36: FA Table 6.1, line 1 | D36: KNCcorpbea | E36: ='Appndx 6.8.II.1'!Y19 -> 159.4 | G36: ='Appndx 6.8.II.1'!Z19 -> 190.1 | H36: ='Appndx 6.8.II.1'!AA19 -> 208.1 | I36: ='Appndx 6.8.II.1'!AB19 -> 212.2 | J36: ='Appndx 6.8.II.1'!AC19 -> 238.1 | K36: ='Appndx 6.8.II.1'!AD19 -> 258.5 | L36: ='Appndx 6.8.II.1'!AE19 -> 273.5 | M36: ='Appndx 6.8.II.1'!AF19 -> 287 | N36: ='Appndx 6.8.II.1'!AG19 -> 295.3 | ... BS36: ='Appndx 6.8.II.1'!CL19 -> 13530.8
A37: =AVERAGE(G37:BS37) -> 0.66689519 | B37: Corp Max Rate of Profit, w/o imputed interest adj. or inventories | C37: VAcorpnipa/KNCcorpbea | D37: Rcorpnipa | G37: =G35/E36 -> 0.73462986 | H37: =H35/G36 -> 0.7054182 | I37: =I35/H36 -> 0.62614128 | J37: =J35/I36 -> 0.69934025 | K37: =K35/J36 -> 0.7152457 | L37: =L35/K36 -> 0.68897485 | M37: =M35/L36 -> 0.6976234 | N37: =N35/M36 -> 0.65296167 | O37: =O35/N36 -> 0.71926854 | ... BS37: =BS35/BR36 -> 0.5718914
A38: =AVERAGE(G38:BS38) -> 0.16340127 | B38: Corporate Profit Share, w/o imputed interest adj. | C38: Pcorpnipa/VAcorpnipa | D38: Profshcorpnipa | G38: =G24/G35 -> 0.19214347 | H38: =H24/H35 -> 0.2207308 | I38: =I24/I35 -> 0.21181888 | J38: =J24/J35 -> 0.23180593 | K38: =K24/K35 -> 0.22959483 | L38: =L24/L35 -> 0.20774846 | M38: =M24/M35 -> 0.19549266 | N38: =N24/N35 -> 0.19423693 | ... BS38: =BS24/BS35 -> 0.18678598
A39: =AVERAGE(G39:BS39) -> 0.10995818 | B39: Corp Profit Rate, w/o imputed interest adj. or inventories | C39: Pcorpnipa/KNCcorpbea(-1) | D39: rcorpnipa | G39: =G24/E36 -> 0.14115433 | H39: =H24/G36 -> 0.15570752 | I39: =I24/H36 -> 0.13262854 | J39: =J24/I36 -> 0.16211122 | K39: =K24/J36 -> 0.16421672 | L39: =L24/K36 -> 0.14313346 | M39: =M24/L36 -> 0.13638026 | N39: =N24/M36 -> 0.12682927 | O39: =O24/N36 -> 0.15780562 | ... BS39: =BS24/BR36 -> 0.10682129
A41: =AVERAGE(G41:BS41) -> 1.3162154 | B41: Multiplier for NIPA Profit | C41: x1 = 1 + (NMINTcorp/Pcorp) | D41: x1 | G41: =1+(G25/G24) -> 1.1066667 | H41: =1+(H25/H24) -> 1.0844595 | I41: =1+(I25/I24) -> 1.0978261 | J41: =1+(J25/J24) -> 1.0813953 | K41: =1+(K25/K24) -> 1.0895141 | L41: =1+(L25/L24) -> 1.1 | M41: =1+(M25/M24) -> 1.1018767 | N41: =1+(N25/N24) -> 1.1098901 | ... BS41: =1+(BS25/BS24) -> 1.3416901
A42: =AVERAGE(G42:BS42) -> 1.1522618 | B42: Multiplier for Lagged Gross Stock | C42: x2 = 1 + (INVcorp(-1)/KNCcorpbea(-1)) | D42: x2 | G42: =1+(E27/E26) -> 1.1355632 | H42: =1+(G27/G26) -> 1.1476844 | I42: =1+(H27/H26) -> 1.1502377 | J42: =1+(I27/I26) -> 1.1421131 | K42: =1+(J27/J26) -> 1.1550711 | L42: =1+(K27/K26) -> 1.1650832 | M42: =1+(L27/L26) -> 1.159893 | N42: =1+(M27/M26) -> 1.1554657 | O42: =1+(N27/N26) -> 1.1479187 | ... BS42: =1+(BR27/BR26) -> 1.1240555
A43: =AVERAGE(G43:BS43) -> 0.76778339 | B43: Gross Fixed Capital / Net NIPA Capital | C43: x3 = KNCcorpbea(-1) / KGCcorp(-1) | D43: x3 | G43: =E36/E26 -> 1.0449515 | H43: =G36/G26 -> 1.1144146 | I43: =H36/H26 -> 1.0856433 | J43: =I36/I26 -> 1.0572743 | K43: =J36/J26 -> 1.034291 | L43: =K36/K26 -> 1.0103584 | M43: =L36/L26 -> 0.98831782 | N43: =M36/M26 -> 0.96784346 | O43: =N36/N26 -> 0.94880043 | ... BS43: =BR36/BR26 -> 0.5911451
A44: =AVERAGE(G44:BS44) -> 0.86277993 | B44: Multiplier for Conventional Profit Rate | C44: rcorp/rcorpnipa = x3*(x1 / x2) | D44: x3*(x1 / x2) | G44: =G43*(G41/G42) -> 1.0183608 | H44: =H43*(H41/H42) -> 1.0530225 | I44: =I43*(I41/I42) -> 1.036175 | J44: =J43*(J41/J42) -> 1.0010669 | K44: =K43*(K41/K42) -> 0.97558895 | L44: =L43*(L41/L42) -> 0.95391836 | M44: =M43*(M41/M42) -> 0.93888343 | N44: =N43*(N41/N42) -> 0.92966834 | ... BS44: =BS43*(BS41/BS42) -> 0.70559998
B46: Proxy Measures (only effect due to new KGCcorp)
A47: =AVERAGE(G47:BS47) -> 0.51579043 | B47: NIPA Corporate Max Rate of Profit | C47: VAcorpnipa/KGCcorp(-1) | D47: Rcorp' | G47: =G35/E26 -> 0.76765259 | H47: =H35/G26 -> 0.78612834 | I47: =I35/H26 -> 0.67976606 | J47: =J35/I26 -> 0.73939449 | K47: =K35/J26 -> 0.73977218 | L47: =L35/K26 -> 0.69611156 | M47: =M35/L26 -> 0.68947364 | N47: =N35/M26 -> 0.63196468 | O47: =O35/N26 -> 0.6824423 | ... BS47: =BS35/BR26 -> 0.3380708
A48: =AVERAGE(G48:BS48) -> 0.087134417 | B48: NIPA Corporate Rate of Profit | C48: Pcorpnipa/KGCcorpbea(-1) | D48: rcorp' | G48: =G24/E26 -> 0.14749943 | H48: =H24/G26 -> 0.17352274 | I48: =I24/H26 -> 0.14398728 | J48: =J24/I26 -> 0.17139603 | K48: =K24/J26 -> 0.16984787 | L48: =L24/K26 -> 0.1446161 | M48: =M24/L26 -> 0.13478704 | N48: =N24/M26 -> 0.12275088 | O48: =O24/N26 -> 0.14972604 | ... BS48: =BS24/BR26 -> 0.063146885
B50: Capacity Utilization
B51: Corp Capacity Utilization | C51: See derivation in Appendix 6.7.VI | D51: uK | G51: 0.88510638 | H51: 0.92389321 | I51: 0.86980039 | J51: 0.87900776 | K51: 0.92584294 | L51: 0.91023296 | M51: 0.92477167 | N51: 0.87672096 | O51: 0.9031142 | P51: 0.86929578 | Q51: 0.84395123 | R51: 0.79810518 | S51: 0.8610478 | T51: 0.8809312 | U51: 0.88277721 | V51: 0.93909597 | W51: 0.97143567 | X51: 1.0016412 | Y51: 1.0422728 | Z51: 1.0647478 | AA51: 1.0427352 | AB51: 1.0570937 | AC51: 1.0494517 | AD51: 0.98441243 | AE51: 0.97354418 | AF51: 1.003911 | AG51: 1.0048655 | AH51: 0.88432848 | AI51: 0.85354692 | AJ51: 0.87999582 | AK51: 0.90109199 | AL51: 0.91149122 | AM51: 0.88534153 | AN51: 0.83406603 | AO51: 0.84334219 | AP51: 0.82005543 | AQ51: 0.858657 | AR51: 0.92487085 | AS51: 0.93559808 | AT51: 0.92921442 | AU51: 0.94841212 | AV51: 0.97139305 | AW51: 0.96777576 | AX51: 0.96064013 | AY51: 0.95897973 | AZ51: 0.97564614 | BA51: 0.97915554 | BB51: 1.0114442 | BC51: 1.0193809 | BD51: 1.0421993 | BE51: 1.071829 | BF51: 1.0945773 | BG51: 1.1084234 | BH51: 1.1150987 | BI51: 1.0632526 | BJ51: 1.0390701 | BK51: 1.0476862 | BL51: 1.0378709 | BM51: 1.0308002 | BN51: 1.0236577 | BO51: 0.98620385 | BP51: 0.92536759 | BQ51: 0.89943755 | BR51: 0.92929506 | BS51: 0.94152617
B52: FRB Capacity Utilization (1967 onward) | C52: http://www.federalreserve.gov/ | D52: uFRB | AA52: 0.86997 | AB52: 0.873409 | AC52: 0.874147 | AD52: 0.812481 | AE52: 0.79615 | AF52: 0.846681 | AG52: 0.883077 | AH52: 0.851318 | AI52: 0.758114 | AJ52: 0.797758 | AK52: 0.834158 | AL52: 0.85072 | AM52: 0.850005 | AN52: 0.807607 | AO52: 0.795681 | AP52: 0.736072 | AQ52: 0.749042 | AR52: 0.804315 | AS52: 0.792294 | AT52: 0.78649 | AU52: 0.812016 | AV52: 0.843358 | AW52: 0.838114 | AX52: 0.825042 | AY52: 0.798462 | AZ52: 0.805751 | BA52: 0.814481 | BB52: 0.835745 | BC52: 0.839053 | BD52: 0.833554 | BE52: 0.840503 | BF52: 0.826825 | BG52: 0.816545 | BH52: 0.813751 | BI52: 0.760084 | BJ52: 0.749103 | BK52: 0.759452 | BL52: 0.779868 | BM52: 0.798989 | BN52: 0.801997 | BO52: 0.805486 | BP52: 0.776171 | BQ52: 0.686643 | BR52: 0.738467 | BS52: 0.763009
B53: Normal Corp Max Rate of Profit | C53: Rcorpn / uK | D53: Rcorpn | G53: =G30/G51 -> 0.77354529 | H53: =H30/H51 -> 0.7518987 | I53: =I30/I51 -> 0.69039217 | J53: =J30/J51 -> 0.7474213 | K53: =K30/K51 -> 0.70231559 | L53: =L30/L51 -> 0.66672077 | M53: =M30/M51 -> 0.65221711 | N53: =N30/N51 -> 0.63382843 | ... BS53: =BS30/BS51 -> 0.32729625
C54: ProfshcorpHP100 | D54: Profshcorpn | G54: 0.22944928 | H54: 0.22932417 | I54: 0.22900357 | J54: 0.22835874 | K54: 0.22725191 | L54: 0.22573173 | M54: 0.22403231 | N54: 0.22237447 | O54: 0.22086168 | P54: 0.21949069 | Q54: 0.21842762 | R54: 0.21783067 | S54: 0.21778079 | T54: 0.21816761 | U54: 0.21889295 | V54: 0.21975096 | W54: 0.22042486 | X54: 0.22058536 | Y54: 0.21994691 | Z54: 0.21831812 | AA54: 0.21571614 | AB54: 0.2123499 | AC54: 0.20852022 | AD54: 0.20461338 | AE54: 0.20097648 | AF54: 0.19774347 | AG54: 0.19495856 | AH54: 0.19264949 | AI54: 0.19082246 | AJ54: 0.18931812 | AK54: 0.18798795 | AL54: 0.18674121 | AM54: 0.1856033 | AN54: 0.1847352 | AO54: 0.18432085 | AP54: 0.18439686 | AQ54: 0.18494262 | AR54: 0.18578454 | AS54: 0.18672161 | AT54: 0.18768099 | AU54: 0.1886786 | AV54: 0.18967658 | AW54: 0.19062624 | AX54: 0.19155418 | AY54: 0.19254069 | AZ54: 0.19364254 | BA54: 0.19487108 | BB54: 0.19614026 | BC54: 0.1972623 | BD54: 0.19804101 | BE54: 0.1983806 | BF54: 0.19835785 | BG54: 0.19825674 | BH54: 0.19839868 | BI54: 0.19911449 | BJ54: 0.20060804 | BK54: 0.20287603 | BL54: 0.20575006 | BM54: 0.20893302 | BN54: 0.21220427 | BO54: 0.21554183 | BP54: 0.21915469 | BQ54: 0.22326743 | BR54: 0.22776006 | BS54: 0.23237495
B55: Normal Corp Rate of Profit | C55: Profshcorpn*Rcorpn | D55: rcorpn | G55: =G54*G53 -> 0.17748941 | H55: =H54*H53 -> 0.17242855 | I55: =I54*I53 -> 0.15810227 | J55: =J54*J53 -> 0.17068019 | K55: =K54*K53 -> 0.15960256 | L55: =L54*L53 -> 0.15050003 | M55: =M54*M53 -> 0.14611771 | N55: =N54*N53 -> 0.14094726 | ... BS55: =BS54*BS53 -> 0.07605545
B56: Normal NIPA Maximum Corp Rate of Profit (using uFRB) | C56: Rcorpnipa / uFRB (1967 onward) | D56: Rcorpnipan | AA56: =AA37/AA52 -> 0.90280126 | AB56: =AB37/AB52 -> 0.91568875 | AC56: =AC37/AC52 -> 0.90415656 | AD56: =AD37/AD52 -> 0.90977082 | AE56: =AE37/AE52 -> 0.91050538 | AF56: =AF37/AF52 -> 0.86681313 | AG56: =AG37/AG52 -> 0.8569324 | AH56: =AH37/AH52 -> 0.84678784 | ... BS56: =BS37/BS52 -> 0.74952117
C57: ProfshcorpnipaHP(100 | D57: Profshcorpnipan | G57: 0.21392905 | H57: 0.21358785 | I57: 0.21302835 | J57: 0.2121034 | K57: 0.21065354 | L57: 0.20871627 | M57: 0.20651859 | N57: 0.2042773 | O57: 0.20209904 | P57: 0.19998966 | Q57: 0.19812802 | R57: 0.1966891 | S57: 0.19575559 | T57: 0.19518528 | U57: 0.19485742 | V57: 0.19455239 | W57: 0.19393602 | X57: 0.19265959 | Y57: 0.19042704 | Z57: 0.18704969 | AA57: 0.18256463 | AB57: 0.1772304 | AC57: 0.17140994 | AD57: 0.16556887 | AE57: 0.16011169 | AF57: 0.15516325 | AG57: 0.15073925 | AH57: 0.14685478 | AI57: 0.14350751 | AJ57: 0.14046161 | AK57: 0.13744212 | AL57: 0.13428349 | AM57: 0.13103476 | AN57: 0.12797712 | AO57: 0.12546941 | AP57: 0.1237097 | AQ57: 0.12279339 | AR57: 0.12257574 | AS57: 0.12288211 | AT57: 0.12364309 | AU57: 0.12486645 | AV57: 0.12649253 | AW57: 0.12847901 | AX57: 0.13086963 | AY57: 0.13366836 | AZ57: 0.13676345 | BA57: 0.13994449 | BB57: 0.14293943 | BC57: 0.14544876 | BD57: 0.14724459 | BE57: 0.14825054 | BF57: 0.14861578 | BG57: 0.14875798 | BH57: 0.14911164 | BI57: 0.1500937 | BJ57: 0.15189298 | BK57: 0.15435534 | BL57: 0.15713873 | BM57: 0.15981155 | BN57: 0.1621178 | BO57: 0.16409437 | BP57: 0.16611598 | BQ57: 0.16857539 | BR57: 0.17141221 | BS57: 0.1743733
B58: Normal NIPA Corp Rate of Profit (using uFRB) | C58: Profshcorpnipan*Rcorpnipan (1967 onward) | D58: rcorpnipan | AA58: =AA57*AA56 -> 0.16481957 | AB58: =AB57*AB56 -> 0.16228788 | AC58: =AC57*AC56 -> 0.15498142 | AD58: =AD57*AD56 -> 0.15062972 | AE58: =AE57*AE56 -> 0.14578256 | AF58: =AF57*AF56 -> 0.13449754 | AG58: =AG57*AG56 -> 0.12917335 | AH58: =AH57*AH56 -> 0.12435484 | ... BS58: =BS57*BS56 -> 0.13069648
B59: Proxy Normal Max Profit Rate using uK | C59: Rcorp'/uK | D59: Rcorp'n | G59: =G47/G51 -> 0.8672998 | H59: =H47/H51 -> 0.85088658 | I59: =I47/I51 -> 0.78151961 | J59: =J47/J51 -> 0.84116947 | K59: =K47/K51 -> 0.79902557 | L59: =L47/L51 -> 0.76476198 | M59: =M47/M51 -> 0.74556095 | N59: =N47/N51 -> 0.72082762 | ... BS59: =BS47/BS51 -> 0.35906681
B60: Proxy Normal Average Profit Rate using uK | C60: Profshcorpnipan*Rcorp'n | D60: rcorp'n | G60: =G57*G59 -> 0.18554062 | H60: =H57*H59 -> 0.18173903 | I60: =I57*I59 -> 0.16648583 | J60: =J57*J59 -> 0.1784149 | K60: =K57*K59 -> 0.16831756 | L60: =L57*L59 -> 0.15961827 | M60: =M57*M59 -> 0.1539722 | N60: =N57*N59 -> 0.14724872 | ... BS60: =BS57*BS59 -> 0.062611663
B62: Nominal and Current (Real) Incremental Rates of Profit
B63: Corporate Gross Investment in Fixed Capital | C63: Appendix Table 6.8.II.1 (from BEA FA T6.7) | D63: IGCcorpbea | F63: ='Appndx 6.8.II.1'!Y28 -> 12 | G63: ='Appndx 6.8.II.1'!Z28 -> 15.7 | H63: ='Appndx 6.8.II.1'!AA28 -> 17.8 | I63: ='Appndx 6.8.II.1'!AB28 -> 16.2 | J63: ='Appndx 6.8.II.1'!AC28 -> 17.8 | K63: ='Appndx 6.8.II.1'!AD28 -> 21.7 | L63: ='Appndx 6.8.II.1'!AE28 -> 22.7 | M63: ='Appndx 6.8.II.1'!AF28 -> 24.8 | ... BS63: ='Appndx 6.8.II.1'!CL28 -> 1182.4
B64: Corporate Current Cost Consumption of Fixed Capital (Depreciation) | C64: Appendix Table 6.8.II.1 (from BEA FA T6.4) | D64: DEPCcorp | G64: ='Appndx 6.8.II.1'!Z25 -> 8.9 | H64: ='Appndx 6.8.II.1'!AA25 -> 10.4 | I64: ='Appndx 6.8.II.1'!AB25 -> 11.2 | J64: ='Appndx 6.8.II.1'!AC25 -> 12 | K64: ='Appndx 6.8.II.1'!AD25 -> 13.6 | L64: ='Appndx 6.8.II.1'!AE25 -> 14.5 | M64: ='Appndx 6.8.II.1'!AF25 -> 15.4 | N64: ='Appndx 6.8.II.1'!AG25 -> 16.2 | ... BS64: ='Appndx 6.8.II.1'!CL25 -> 1061.9
B65: Gross Corporate NIPA Profit | C65: Pcorp + DEPCcorp | D65: PGcorp | G65: =G24+G64 -> 31.4 | H65: =H24+H64 -> 40 | I65: =I24+I64 -> 38.8 | J65: =J24+J64 -> 46.4 | K65: =K24+K64 -> 52.7 | L65: =L24+L64 -> 51.5 | M65: =M24+M64 -> 52.7 | N65: =N24+N64 -> 52.6 | ... BS65: =BS24+BS64 -> 2450
D66: ∆PGcorp | H66: =H65-G65 -> 8.6 | I66: =I65-H65 -> -1.2 | J66: =J65-I65 -> 7.6 | K66: =K65-J65 -> 6.3 | L66: =L65-K65 -> -1.2 | M66: =M65-L65 -> 1.2 | N66: =N65-M65 -> -0.1 | O66: =O65-N65 -> 11.1 | ... BS66: =BS65-BR65 -> 122.6
B67: Gross Operating Surplus (adjusted) | C67: NOScorp + DEPcorp | D67: GOScorp | G67: =G23+G64 -> 33.8 | H67: =H23+H64 -> 42.5 | I67: =I23+I64 -> 41.4 | J67: =J23+J64 -> 49.2 | K67: =K23+K64 -> 56.1 | L67: =L23+L64 -> 55.1 | M67: =M23+M64 -> 56.5 | N67: =N23+N64 -> 56.5 | ... BS67: =BS23+BS64 -> 2924.3
D68: ∆GOScorp | H68: =H67-G67 -> 8.7 | I68: =I67-H67 -> -1.1 | J68: =J67-I67 -> 7.8 | K68: =K67-J67 -> 6.9 | L68: =L67-K67 -> -1 | M68: =M67-L67 -> 1.4 | N68: =N67-M67 -> 0 | O68: =O67-N67 -> 11.9 | ... BS68: =BS67-BR67 -> 159.2
B69: Change in Corporate Inventories | D69: ∆INVcorp | G69: =G27-F27 -> 4.5132156 | H69: =H27-G27 -> 3.6056767 | I69: =I27-H27 -> -0.27532727 | J69: =J27-I27 -> 7.1755265 | K69: =K27-J27 -> 6.5382142 | L69: =L27-K27 -> 2.0111465 | M69: =M27-L27 -> 1.8534496 | N69: =N27-M27 -> -0.063627784 | ... BS69: =BS27-BR27 -> 210.53342
B70: Corporate Gross Investment in Fixed Capital and Inventories | D70: IGcorpbea + ∆INVcorp | G70: =G63+G69 -> 20.213216 | H70: =H63+H69 -> 21.405677 | I70: =I63+I69 -> 15.924673 | J70: =J63+J69 -> 24.975526 | K70: =K63+K69 -> 28.238214 | L70: =L63+L69 -> 24.711146 | M70: =M63+M69 -> 26.65345 | N70: =N63+N69 -> 24.036372 | ... BS70: =BS63+BS69 -> 1392.9334
A71: =AVERAGE(H71:BS71) -> 0.13447268 | B71: Adjusted Corp. Nominal Incremental Rate of Profit | C71: ∆GOScorp/(IGcorpbea + ∆INVcorp)-1 | D71: iropcorp | H71: =H68/G70 -> 0.43041148 | I71: =I68/H70 -> -0.051388238 | J71: =J68/I70 -> 0.48980598 | K71: =K68/J70 -> 0.27627045 | L71: =L68/K70 -> -0.035413004 | M71: =M68/L70 -> 0.056654595 | N71: =N68/M70 -> 0 | O71: =O68/N70 -> 0.49508303 | ... BS71: =BS68/BR70 -> 0.1295538
A72: =AVERAGE(H72:BS72) -> 0.13618539 | B72: NIPA Corp. Nominal Incremental Rate of Profit | C72: ∆PGcorp/IGCcorpbea-1 | D72: iropcorpnipa | H72: =H66/F63 -> 0.71666667 | I72: =I66/G63 -> -0.076433121 | J72: =J66/H63 -> 0.42696629 | K72: =K66/I63 -> 0.38888889 | L72: =L66/J63 -> -0.06741573 | M72: =M66/K63 -> 0.055299539 | N72: =N66/L63 -> -0.0044052863 | O72: =O66/M63 -> 0.44758065 | ... BS72: =BS66/BQ63 -> 0.11678415
B73: Real Corporate Gross Investment | C73: Appendix Table 6.8.II.1 (from BEA FA T6.8) | D73: IGRcorpbea | G73: ='Appndx 6.8.II.1'!Z30 -> 67.405856 | H73: ='Appndx 6.8.II.1'!AA30 -> 70.228636 | I73: ='Appndx 6.8.II.1'!AB30 -> 62.079856 | J73: ='Appndx 6.8.II.1'!AC30 -> 66.575 | K73: ='Appndx 6.8.II.1'!AD30 -> 73.786404 | L73: ='Appndx 6.8.II.1'!AE30 -> 75.597244 | M73: ='Appndx 6.8.II.1'!AF30 -> 81.125632 | N73: ='Appndx 6.8.II.1'!AG30 -> 78.356112 | ... BS73: ='Appndx 6.8.II.1'!CL30 -> 1093.1189
B74: Price index Corporate Gross Investment (2005 = 100) | C74: Appendix Table 6.8.II.1 | D74: pIGcorpbea | F74: ='Appndx 6.8.II.1'!Y31 -> 19.910728 | G74: ='Appndx 6.8.II.1'!Z31 -> 23.291745 | H74: ='Appndx 6.8.II.1'!AA31 -> 25.345786 | I74: ='Appndx 6.8.II.1'!AB31 -> 26.095421 | J74: ='Appndx 6.8.II.1'!AC31 -> 26.736763 | K74: ='Appndx 6.8.II.1'!AD31 -> 29.409212 | L74: ='Appndx 6.8.II.1'!AE31 -> 30.02755 | M74: ='Appndx 6.8.II.1'!AF31 -> 30.56987 | ... BU74: ='Appndx 6.8.II.1'!CN31 -> 110.96791
B75: Real Gross Operating Surplus | C75: (NOScorp + DEPcorp)/pIGcorpbea | D75: GOSRcorp | G75: =(G23+G64)*100/G74 -> 145.11579 | H75: =(H23+H64)*100/H74 -> 167.68073 | I75: =(I23+I64)*100/I74 -> 158.64852 | J75: =(J23+J64)*100/J74 -> 184.01629 | K75: =(K23+K64)*100/K74 -> 190.75656 | L75: =(L23+L64)*100/L74 -> 183.49816 | M75: =(M23+M64)*100/M74 -> 184.82251 | N75: =(N23+N64)*100/N74 -> 183.69794 | ... BS75: =(BS23+BS64)*100/BS74 -> 2703.4908
B76: Real Corporate Gross Profit (deflated by gross investment price index) | C76: PGcorp/pIGcorpbea | D76: PGRcorp | G76: =G65*100/G74 -> 134.81171 | H76: =H65*100/H74 -> 157.81716 | I76: =I65*100/I74 -> 148.68509 | J76: =J65*100/J74 -> 173.54382 | K76: =K65*100/K74 -> 179.19555 | L76: =L65*100/L74 -> 171.50917 | M76: =M65*100/M74 -> 172.39197 | N76: =N65*100/N74 -> 171.0179 | ... BS76: =BS65*100/BS74 -> 2265.0045
B77: Real Corporate Inventories (deflated by gross investment price index) | C77: INVcorp/pIGcorpbea | D77: INVRcorp | F77: =F27*100/F74 -> 103.85961 | G77: =G27*100/G74 -> 108.1603 | H77: =H27*100/H74 -> 113.62085 | I77: =I27*100/I74 -> 109.30182 | J77: =J27*100/J74 -> 133.51765 | K77: =K27*100/K74 -> 143.6166 | L77: =L27*100/L74 -> 147.35687 | M77: =M27*100/M74 -> 150.8057 | ... BS77: =BS27*100/BS74 -> 2715.7225
D78: ∆GOSRcorp | H78: =H75-G75 -> 22.56494 | I78: =I75-H75 -> -9.0322111 | J78: =J75-I75 -> 25.367771 | K78: =K75-J75 -> 6.7402638 | L78: =L75-K75 -> -7.2583998 | M78: =M75-L75 -> 1.3243522 | N78: =N75-M75 -> -1.1245695 | O78: =O75-N75 -> 36.168471 | ... BS78: =BS75-BR75 -> 94.670285
B79: Change in Real Gross Corporate Profit | D79: ∆PGRcorp | H79: =H76-G76 -> 23.005448 | I79: =I76-H76 -> -9.1320723 | J79: =J76-I76 -> 24.858733 | K79: =K76-J76 -> 5.6517323 | L79: =L76-K76 -> -7.6863867 | M79: =M76-L76 -> 0.8828021 | N79: =N76-M76 -> -1.3740638 | O79: =O76-N76 -> 33.740726 | ... BS79: =BS76-BR76 -> 69.14574
B80: Change in Real Corporate Inventories | D80: ∆INVRcorp | G80: =G77-F77 -> 4.3006864 | H80: =H77-G77 -> 5.46055 | I80: =I77-H77 -> -4.3190296 | J80: =J77-I77 -> 24.215827 | K80: =K77-J77 -> 10.098955 | L80: =L77-K77 -> 3.7402683 | M80: =M77-L77 -> 3.4488332 | N80: =N77-M77 -> -1.1244635 | ... BS80: =BS77-BR77 -> 142.85116
B81: Real Corporate Gross Investment in Fixed Capital and Inventories | D81: IGRcorpbea + ∆INVRcorp | G81: =G73+G80 -> 71.706542 | H81: =H73+H80 -> 75.689186 | I81: =I73+I80 -> 57.760826 | J81: =J73+J80 -> 90.790827 | K81: =K73+K80 -> 83.885359 | L81: =L73+L80 -> 79.337512 | M81: =M73+M80 -> 84.574465 | N81: =N73+N80 -> 77.231648 | ... BS81: =BS73+BS80 -> 1235.9701
A82: =AVERAGE(H82:BS82) -> 0.095010927 | B82: Adjusted Corp. Real Incremental Rate of Profit | C82: ∆GOSRcorp/(IGRcorpbea + ∆INVRcorp)-1 | D82: iroprcorp | H82: =H78/G81 -> 0.31468454 | I82: =I78/H81 -> -0.11933291 | J82: =J78/I81 -> 0.43918643 | K82: =K78/J81 -> 0.07423948 | L82: =L78/K81 -> -0.086527612 | M82: =M78/L81 -> 0.016692636 | N82: =N78/M81 -> -0.013296797 | O82: =O78/N81 -> 0.46831153 | ... BS82: =BS78/BR81 -> 0.080805881
A83: =AVERAGE(H83:BS83) -> 0.084926832 | B83: NIPA Corp. Real Incremental Rate of Profit | C83: ∆PGRcorp/IGRcorpbea-1 | D83: iroprcorpnipa | H83: =H79/G73 -> 0.34129746 | I83: =I79/H73 -> -0.13003346 | J83: =J79/I73 -> 0.40043155 | K83: =K79/J73 -> 0.084892713 | L83: =L79/K73 -> -0.10417077 | M83: =M79/L73 -> 0.011677702 | N83: =N79/M73 -> -0.01693748 | O83: =O79/N73 -> 0.43060746 | ... BS83: =BS79/BR73 -> 0.068886046
B86: Corrected and NIPA Incremental Rates of Profit | C86: Mean | D86: Standard Deviation | F86: Coefficient of Variation
B87: Nominal Corrected Incremental Rate of Profit | C87: =A71 -> 0.13447268 | D87: =STDEV(H71:BS71) -> 0.12817295 | F87: =D87/C87 -> 0.95315234
B88: Nominal NIPA Incremental Rate of Profit | C88: =A72 -> 0.13618539 | D88: =STDEV(H72:BS72) -> 0.15803971 | F88: =D88/C88 -> 1.1604748
B89: Current (Real) Corrected Incremental Rate of Profit | C89: =A82 -> 0.095010927 | D89: =STDEV(H82:BS82) -> 0.13207153 | F89: =D89/C89 -> 1.3900668
B90: Current (Real) NIPA Incremental Rate of Profit | C90: =A83 -> 0.084926832 | D90: =STDEV(H83:BS83) -> 0.14276839 | F90: =D90/C90 -> 1.6810751
B95: Decomposition of Average Rates of Change of US Corporate Profit Rates and Components
B96: 1947-1982 | C96: Maximum Profit Rate | D96: Profit Share | E96: Profit Rate
B97: Corrected Normal-Capacity Measures | C97: =D104 -> -0.015880358 | D97: =D105 -> -0.0062066492 | E97: =D106 -> -0.022020676
B98: Conventional Normal-Capacity Measures | C98: =D111 -> -0.011756995 | D98: =D112 -> -0.037536277 | E98: =D113 -> -0.037064412
B99: 1982-2011 | C99: Maximum Profit Rate | D99: Profit Share | E99: Profit Rate
B100: Corrected Normal-Capacity Measures | C100: =E104 -> -0.011181546 | D100: =E105 -> 0.0077712808 | E100: =E106 -> -0.0034604249
B101: Conventional Normal-Capacity Measures | C101: =E111 -> -0.00050694334 | D101: =E112 -> 0.023770311 | E101: =E113 -> 0.010544863
B103: Growth rates | D103: Avg 1948-82 | E103: Avg 1982-2011
B104: Corrected Normal-Capacity Measures | C104: gRcorpn | D104: =AVERAGE(H104:AP104) -> -0.015880358 | E104: =AVERAGE(AP104:BS104) -> -0.011181546 | H104: =(H53-G53)/G53 -> -0.027983611 | I104: =(I53-H53)/H53 -> -0.081801617 | J104: =(J53-I53)/I53 -> 0.082603964 | K104: =(K53-J53)/J53 -> -0.060348445 | L104: =(L53-K53)/K53 -> -0.050682084 | M104: =(M53-L53)/L53 -> -0.021753721 | N104: =(N53-M53)/M53 -> -0.028194108 | O104: =(O53-N53)/N53 -> 0.054717298 | ... BS104: =(BS53-BR53)/BR53 -> 0.0070300155
C105: gProfshcorpn | D105: =AVERAGE(H105:AP105) -> -0.0062066492 | E105: =AVERAGE(AP105:BS105) -> 0.0077712808 | H105: =(H54-G54)/G54 -> -0.00054526266 | I105: =(I54-H54)/H54 -> -0.0013980339 | J105: =(J54-I54)/I54 -> -0.0028158095 | K105: =(K54-J54)/J54 -> -0.0048468834 | L105: =(L54-K54)/K54 -> -0.0066894208 | M105: =(M54-L54)/L54 -> -0.0075284765 | N105: =(N54-M54)/M54 -> -0.0074000152 | O105: =(O54-N54)/N54 -> -0.0068028777 | ... BS105: =(BS54-BR54)/BR54 -> 0.020262064
C106: grcorpn | D106: =AVERAGE(H106:AP106) -> -0.022020676 | E106: =AVERAGE(AP106:BS106) -> -0.0034604249 | H106: =(H55-G55)/G55 -> -0.028513615 | I106: =(I55-H55)/H55 -> -0.083085289 | J106: =(J55-I55)/I55 -> 0.079555558 | K106: =(K55-J55)/J55 -> -0.064902826 | L106: =(L55-K55)/K55 -> -0.057032471 | M106: =(M55-L55)/L55 -> -0.029118425 | N106: =(N55-M55)/M55 -> -0.035385487 | O106: =(O55-N55)/N55 -> 0.047542185 | ... BS106: =(BS55-BR55)/BR55 -> 0.027434522
D110: Avg 1947-82 or 1967-82 | E110: Avg 1982-2011
B111: Conventional (uFRB only available 1967-2011) | C111: gRcorpnipan (1967-82) | D111: =AVERAGE(AB111:AP111) -> -0.011756995 | E111: =AVERAGE(AP111:BS111) -> -0.00050694334 | AB111: =(AB56-AA56)/AA56 -> 0.014275 | AC111: =(AC56-AB56)/AB56 -> -0.012594002 | AD111: =(AD56-AC56)/AC56 -> 0.0062093835 | AE111: =(AE56-AD56)/AD56 -> 0.00080741945 | AF111: =(AF56-AE56)/AE56 -> -0.047986812 | AG111: =(AG56-AF56)/AF56 -> -0.011398913 | AH111: =(AH56-AG56)/AG56 -> -0.011838232 | AI111: =(AI56-AH56)/AH56 -> -0.01658757 | ... BS111: =(BS56-BR56)/BR56 -> -0.0042281479
C112: gProfshcorpnipa (1947-82) | D112: =AVERAGE(AB112:AP112) -> -0.037536277 | E112: =AVERAGE(AP112:BS112) -> 0.023770311 | H112: =(H38-G38)/G38 -> 0.14878117 | I112: =(I38-H38)/H38 -> -0.040374603 | J112: =(J38-I38)/I38 -> 0.094359155 | K112: =(K38-J38)/J38 -> -0.0095385708 | L112: =(L38-K38)/K38 -> -0.095151866 | M112: =(M38-L38)/L38 -> -0.058993427 | N112: =(N38-M38)/M38 -> -0.0064234437 | O112: =(O38-N38)/N38 -> 0.12953478 | ... BS112: =(BS38-BR38)/BR38 -> 0.013718477
C113: grcorpnipan (1967-82) | D113: =AVERAGE(AB113:AP113) -> -0.037064412 | E113: =AVERAGE(AP113:BS113) -> 0.010544863 | AB113: =(AB58-AA58)/AA58 -> -0.015360373 | AC113: =(AC58-AB58)/AB58 -> -0.045021601 | AD113: =(AD58-AC58)/AC58 -> -0.028078858 | AE113: =(AE58-AD58)/AD58 -> -0.032179341 | AF113: =(AF58-AE58)/AE58 -> -0.077409915 | AG113: =(AG58-AF58)/AF58 -> -0.039585805 | AH113: =(AH58-AG58)/AG58 -> -0.037302659 | AI113: =(AI58-AH58)/AH58 -> -0.039002491 | ... BS113: =(BS58-BR58)/BR58 -> 0.01297348

Sheet Sheet1
A1: KGHIRScorp | AT1: 4317781452 | AU1: 4549055093 | AV1: 4755145257 | AW1: 4968959443 | AX1: 5284097003 | AY1: 5571142501 | AZ1: 5923297939 | BA1: 6208236257 | BB1: 6541280743 | BC1: 6935503013 | BD1: 7291998758 | BE1: 7613590480 | BF1: 7677626201 | BG1: 7804548186 | BH1: 7973940602 | BI1: 8415761105 | BJ1: 8817095391 | BK1: 9221635446 | BL1: 9466523654 | BM1: 9613451456 | BN1: 9875410289 | BO1: 10225874777
A2: DeprecIRScorp | AT2: 1848022862 | AU2: 1999540977 | AV2: 2131890499 | AW2: 2265345826 | AX2: 2438539251 | AY2: 2600545415 | AZ2: 2760002783 | BA2: 2898167422 | BB2: 3031634536 | BC2: 3227243753 | BD2: 3369214883 | BE2: 3549239594 | BF2: 3699383948 | BG2: 3812960901 | BH2: 3930550044 | BI2: 4096350302 | BJ2: 4241564417 | BK2: 4335284540 | BL2: 4514037135 | BM2: 4711042846 | BN2: 4874203678 | BO2: 5021678762
A3: KNHIRScorp | AT3: 2469758590 | AU3: 2549514116 | AV3: 2623254758 | AW3: 2703613617 | AX3: 2845557752 | AY3: 2970597086 | AZ3: 3163295156 | BA3: 3310068835 | BB3: 3509646207 | BC3: 3708259260 | BD3: 3922783875 | BE3: 4064350886 | BF3: 3978242253 | BG3: 3991587285 | BH3: 4043390558 | BI3: 4319410803 | BJ3: 4575530974 | BK3: 4886350906 | BL3: 4952486519 | BM3: 4902408610 | BN3: 5001206611 | BO3: 5204196015
A4: KNHcorpbea | B4: 95.3 | C4: 105 | D4: 115.9 | E4: 124.4 | F4: 133.7 | G4: 146 | H4: 158.6 | I4: 172.3 | J4: 184.4 | K4: 197.9 | L4: 216 | M4: 235.4 | N4: 248.7 | O4: 263.6 | P4: 280.9 | Q4: 296.5 | R4: 313.9 | S4: 331.7 | T4: 353.5 | U4: 382.1 | V4: 417.3 | W4: 450.7 | X4: 487.4 | Y4: 529 | Z4: 569.4 | AA4: 609.7 | AB4: 657.3 | AC4: 718.2 | AD4: 790.1 | AE4: 858.5 | AF4: 934.6 | AG4: 1030.7 | AH4: 1156.7 | AI4: 1310.3 | AJ4: 1474.4 | AK4: 1662.3 | AL4: 1834.5 | AM4: 1987.1 | AN4: 2181.8 | AO4: 2383.8 | AP4: 2556.7 | AQ4: 2712.7 | AR4: 2881.4 | AS4: 3067.8 | AT4: 3267.3 | AU4: 3430.2 | AV4: 3587.9 | AW4: 3777.9 | AX4: 3995.7 | AY4: 4261.1 | AZ4: 4553.3 | BA4: 4871 | BB4: 5215.3 | BC4: 5585.3 | BD4: 5995.7 | BE4: 6306.5 | BF4: 6499.8 | BG4: 6684.5 | BH4: 6906.9 | BI4: 7201.1 | BJ4: 7605.3 | BK4: 8068.8 | BL4: 8508.3 | BM4: 8673.5 | BN4: 8848.6 | BO4: 9122.4
B7: 0.20994941 | C7: 0.23602941 | D7: 0.22809668 | E7: 0.24701195 | F7: 0.24580682 | G7: 0.22443339 | H7: 0.21229339 | I7: 0.21165966 | J7: 0.23783032 | K7: 0.21869565 | L7: 0.21068002 | M7: 0.1987152 | N7: 0.21897533 | O7: 0.20739666 | P7: 0.20783345 | Q7: 0.21845757 | R7: 0.22484848 | S7: 0.23003642 | T7: 0.24075491 | U7: 0.23754075 | V7: 0.22490583 | W7: 0.22086504 | X7: 0.20457059 | Y7: 0.18327974 | Z7: 0.19202119 | AA7: 0.19612807 | AB7: 0.19275189 | AC7: 0.17612863 | AD7: 0.19193437 | AE7: 0.19510947 | AF7: 0.19963817 | AG7: 0.20028488 | AH7: 0.18791515 | AI7: 0.16996809 | AJ7: 0.17864295 | AK7: 0.16908406 | AL7: 0.18218881 | AM7: 0.19862179 | AN7: 0.19558152 | AO7: 0.18226269 | AP7: 0.18763468 | AQ7: 0.1972383 | AR7: 0.19602089 | AS7: 0.1891742 | AT7: 0.18800406 | AU7: 0.18386707 | AV7: 0.18470934 | AW7: 0.1953171 | AX7: 0.20732106 | AY7: 0.21532509 | AZ7: 0.21913082 | BA7: 0.20210385 | BB7: 0.19922482 | BC7: 0.18569453 | BD7: 0.17844875 | BE7: 0.18413469 | BF7: 0.1900198 | BG7: 0.21343474 | BH7: 0.22875955 | BI7: 0.23525145 | BJ7: 0.21706706 | BK7: 0.18472324 | BL7: 0.20949593 | BM7: 0.24128791 | BN7: 0.24459241
B9: 0.20994941 | C9: 0.23602941 | D9: 0.22809668 | E9: 0.24701195 | F9: 0.24580682 | G9: 0.22443339 | H9: 0.21229339 | I9: 0.21165966 | J9: 0.23783032 | K9: 0.21869565 | L9: 0.21068002 | M9: 0.1987152 | N9: 0.21897533 | O9: 0.20739666 | P9: 0.20783345 | Q9: 0.21845757 | R9: 0.22484848 | S9: 0.23003642 | T9: 0.24075491 | U9: 0.23754075 | V9: 0.22490583 | W9: 0.22086504 | X9: 0.20457059 | Y9: 0.18327974 | Z9: 0.19202119 | AA9: 0.19612807 | AB9: 0.19275189 | AC9: 0.17612863 | AD9: 0.19193437 | AE9: 0.19510947 | AF9: 0.19963817 | AG9: 0.20028488 | AH9: 0.18791515 | AI9: 0.16996809 | AJ9: 0.17864295 | AK9: 0.16908406 | AL9: 0.18218881 | AM9: 0.19862179 | AN9: 0.19558152 | AO9: 0.18226269 | AP9: 0.18763468 | AQ9: 0.1972383 | AR9: 0.19602089 | AS9: 0.1891742 | AT9: 0.18800406 | AU9: 0.18386707 | AV9: 0.18470934 | AW9: 0.1953171 | AX9: 0.20732106 | AY9: 0.21532509 | AZ9: 0.21913082 | BA9: 0.20210385 | BB9: 0.19922482 | BC9: 0.18569453 | BD9: 0.17844875 | BE9: 0.18413469 | BF9: 0.1900198 | BG9: 0.21343474 | BH9: 0.22875955 | BI9: 0.23525145 | BJ9: 0.21706706 | BK9: 0.18472324 | BL9: 0.20949593 | BM9: 0.24128791 | BN9: 0.24459241
B11: 0.21392905
B12: 0.21358785
B13: 0.21302835
B14: 0.2121034
B15: 0.21065354
B16: 0.20871627
B17: 0.20651859
B18: 0.2042773
B19: 0.20209904
B20: 0.19998966
B21: 0.19812802
B22: 0.1966891
... B75: 0.1743733
